Workbook

Sheet 설정_및_규칙
A1: 항목 | B1: 내용
A2: §0.5 제품 설정 블록 (승인분)
A3: PRODUCT | B3: RemoteView
A4: PREFIX | B4: RV
A5: SOURCE_ROOT | B5: RAG_RV_data/ (docs/chunks export 2026-07-10, indexed 2026-07-01~02)
A6: HELPDESK_BASE | B6: https://help.rview.com/hc/ko/ — 링크로만 존재, 코퍼스 미인입 (인입 누락 리포트 후보)
A7: ACL_DEFAULT | B7: 공개
A9: 부가 조항 (설계본부 확정)
A10: ⑥ 보일러플레이트 규칙 | B10: 발췌·사실 필드는 본문 문장만. 제외: 내비게이션·바로가기·서비스 가동배너·구매/기술지원 전화·푸터(Tel/FAX/주소/사업자번호/저작권)
A11: ⑧ 시점 앵커 규칙(B2 검수 명문화) | B11: 가격·할인율·기간 등 변동성 수치를 포함하는 단위 전건에 [시점 앵커: 인덱싱일] 명기. 정본 개정 시 재검토 대상 표식. 완료 보고는 적용 N / 불요 N(수치 부재) 분리 계리
A12: ⑨ 약관·SLA 시점 장치 | B12: 약관 전건 [시행 기준: 2021-02-16] 명기 (부칙 제1조 실측)
A13: 트랙 | B13: 코퍼스판 단독 트랙 — 코퍼스 내 문서 자체가 정본(설계본부 확정 1). 작업 기준: 실측 chunks 5,139
A15: 시스템팀 공유 후보 목록
A16: 1호 | B16: docs.chunk_count 메타 합계 4,594 ≠ 실제 청크 5,139 (+545, 35문서) — export 정합성 이슈
A17: 2호 | B17: help.rview.com 헬프데스크 미인입 — 링크로만 존재. 인입 누락 리포트 후보
A18: 3호 | B18: 반응형 3중 렌더 크롤 — 동일 섹션 ×3 중복 인입(B2 폴딩 246건 실측). top-k 잠식 위험
A19: 4호 | B19: 이용약관 시행일 2021-02-16 vs 크롤 2026-07 — 5년 격차, 약관 최신성 확인 요망
A21: ⑥ 추가(B4 승인분) — 영상 아티팩트 | B21: 차단: "Your browser does not support the video tag" / "브라우저가 video 태그를 지원하지 않습니다" / YouTube embed URL 단독 행 / [목록](…videoguide…) 복귀 링크. 존재 자체는 영상 의존 판정 신호로 사용
A22: ① 출제 경계(B4 승인분) | B22: 메타 사실 단위는 존재·위치형 질문만 성립. 방법 상세형 출제 금지(영상 의존) — 상세 부재는 E형 소재
A23: ① 판정 3분기(B4-1 사후 승인 반영) | B23: (1) 성립(메타): 존재 사실만 텍스트 성립 → 존재·위치형 출제만, 방법 상세 금지 / (2) 성립(대본 전문): 절차가 텍스트로 완결 실재 → 방법 상세 출제 허용, 화면 지시 표현부는 발췌 제외 / (3) 부분 성립(요약): 요약 수준 → 방법 상세 금지 / (+불성립: 텍스트 부재 → 사람확인)
A24: 5호 | B24: URL 정규화 누락 — ?p=ID ↔ pretty slug 동일 포스트 이중 인입. 최종 실측: ?p= 120문서 중 변형 119(영상가이드 64 + 사례 35 + 블로그 19 + 제품 랜딩 1[p=24107→rvbox-advanced]) / 고유 1(p=13953 구매안내). 중복 청크 합계 1077(467+230+375+5). url_variants 전건 variant_count=1(변형 미접힘 증거). 검색 top-k 잠식·저장 낭비
A25: 정정 이력 | B25: B0 계리표 "영상가이드 64건 별개 콘텐츠" 판단 정정(2026-07-13) — 동일 포스트 URL 변형. B4 계획서 ④의 B4-2 예상 규모(65~100단위) 전제도 함께 무효(실제: 폴딩 64/신규 0). 레거시 규칙 ②는 B4-2 적용 대상 소멸, 규칙 자체는 존치(향후 배치 유효)
A26: B6 폴딩 수정 소명(v1_3) | B26: 반려 원인: 폴딩대장 대표 ID 생성 코드가 Unit ID(r[0]) 대신 type 필드(r[1]="BlogPost")를 참조. 병기도 잘못된 대표로 매칭돼 1건만 우연 성립. "병기 완료" 상태는 실측 없이 코드 상수로 선기재된 것 — 보고 규율 위반(숫자 없는 완료의 상태값 버전) 인정. 수정: 대표를 실제 첫 단위 ID로 교체(19/19 실재), 본체 병기 재적용 후 실측(19/19), 상태값을 "병기 완료(실측)"로 명기

Sheet B0_계리
A1: 분류 | B1: 건수 | C1: 배치 배정 | D1: 비고
A2: 영상가이드 | B2: =COUNTIF(B0_분류표!D:D,A2) | C2: B4 | D2: [정정 2026-07-13] 당초 "정식 67건과 제목 중복 0 — 별개 콘텐츠"로 보고했으나 내용 수준 재대조 결과 64/64 동일 포스트(URL 변형)로 확인. B4-2에서 문서 수준 폴딩 처리. 원인: CSV title 필드 대조 공전(내용 수준 대조 부재)
A3: 도입사례 | B3: =COUNTIF(B0_분류표!D:D,A3) | C3: B5 | D3: Customer Success story / CASE STUDY 마커
A4: 블로그 | B4: =COUNTIF(B0_분류표!D:D,A4) | C4: B6 | D4: 사이트 자체 태그 보유(인사이트12·소식4·기능2·활용팁1)
A5: 제품·기능 안내 | B5: =COUNTIF(B0_분류표!D:D,A5) | C5: B2 | D5: 리모트뷰박스 랜딩 1건
A6: 구매·안내 페이지 | B6: =COUNTIF(B0_분류표!D:D,A6) | C6: B2 | D6: 라이선스 구매 로그인 안내 1건
A7: 합계 | B7: =SUM(B2:B6) | D7: 분류별 건수 합 = 120 (소실 0)

Sheet B0_분류표
A1: # | B1: doc_key | C1: canonical_url | D1: 분류 | E1: 분류 근거 | F1: 추출 제목 | G1: 게시일 | H1: 본문 자수(보일러플레이트 제거 후) | I1: 청크 수(실측) | J1: 배치 배정
A2: 1 | B2: eae37f69e968 | C2: https://content.rview.com/ko/?p=15295 | D2: 영상가이드 | E2: videoguide 관련콘텐츠 구조·무날짜 | F2: 10\. 원격으로 PC를 켜고 제어하기 | H2: 1993 | I2: 6 | J2: B4
A3: 2 | B3: 1f4ec3cab231 | C3: https://content.rview.com/ko/?p=15296 | D3: 영상가이드 | E3: videoguide 관련콘텐츠 구조·무날짜 | F3: 9\. RemoteView에서 WOL 등록확인 | H3: 1972 | I3: 6 | J3: B4
A4: 3 | B4: 75a315543d3e | C4: https://content.rview.com/ko/?p=15297 | D4: 영상가이드 | E4: videoguide 관련콘텐츠 구조·무날짜 | F4: 8\. 고정 IP 환경에서 RemoteView로 WOL 기기를 등록하는 방법 | H4: 1981 | I4: 6 | J4: B4
A5: 4 | B5: 45852ee51824 | C5: https://content.rview.com/ko/?p=15298 | D5: 영상가이드 | E5: videoguide 관련콘텐츠 구조·무날짜 | F5: 7\. 고정 IP 환경에서 WOL 설정 | H5: 1957 | I5: 6 | J5: B4
A6: 5 | B6: 6e25ca3ff5b2 | C6: https://content.rview.com/ko/?p=15299 | D6: 영상가이드 | E6: videoguide 관련콘텐츠 구조·무날짜 | F6: 6\. DHCP 환경에서 WOL 설정 | H6: 1996 | I6: 6 | J6: B4
A7: 6 | B7: 5ed31f27c762 | C7: https://content.rview.com/ko/?p=15300 | D7: 영상가이드 | E7: videoguide 관련콘텐츠 구조·무날짜 | F7: 5\. WOL 장비 및 MAC Address 확인 | H7: 1959 | I7: 6 | J7: B4
A8: 7 | B8: 2298df8e6ee8 | C8: https://content.rview.com/ko/?p=15301 | D8: 영상가이드 | E8: videoguide 관련콘텐츠 구조·무날짜 | F8: 4\. WOL 도입 전 테스트하기 | H8: 2001 | I8: 6 | J8: B4
A9: 8 | B9: 4843ba5b636a | C9: https://content.rview.com/ko/?p=15302 | D9: 영상가이드 | E9: videoguide 관련콘텐츠 구조·무날짜 | F9: 3\. WOL 기능 사용을 위한 BIOS(UEFI) 진입과 설정 | H9: 1970 | I9: 6 | J9: B4
A10: 9 | B10: 0e774a5ac260 | C10: https://content.rview.com/ko/?p=15303 | D10: 영상가이드 | E10: videoguide 관련콘텐츠 구조·무날짜 | F10: 2\. 윈도우 설정 방법 (WOL 체크) | H10: 1962 | I10: 6 | J10: B4
A11: 10 | B11: 068e4cf3778c | C11: https://content.rview.com/ko/?p=15304 | D11: 영상가이드 | E11: videoguide 관련콘텐츠 구조·무날짜 | F11: 1\. RemoteWOL 소개 | H11: 1952 | I11: 6 | J11: B4
A12: 11 | B12: a8cdc3a693d9 | C12: https://content.rview.com/ko/?p=15305 | D12: 영상가이드 | E12: videoguide 관련콘텐츠 구조·무날짜 | F12: 14\. Windows LogOn 사용하기 | H12: 2853 | I12: 7 | J12: B4
A13: 12 | B13: e9c7bd2ff6cc | C13: https://content.rview.com/ko/?p=15306 | D13: 영상가이드 | E13: videoguide 관련콘텐츠 구조·무날짜 | F13: 13\. Google OTP 사용하기 | H13: 2860 | I13: 7 | J13: B4
... A100: 99 | B100: 71315a714aa9 | C100: https://content.rview.com/ko/?p=25175 | D100: 도입사례 | E100: 제조 | F100: 고위험 현장 이동 120분 단축! 중공업 특수 장비 원격제어 사례 H사 | H100: 5184 | I100: 10 | J100: B5
A101: 100 | B101: a82bd97bf31b | C101: https://content.rview.com/ko/?p=15916 | D101: 블로그 | E101: 사이트 태그: 인사이트 (2022.07.25) | F101: 값비싼 데스크톱 가상화(VDI)? | G101: 2022.07.25 | H101: 5666 | I101: 11 | J101: B6
A102: 101 | B102: b4a45fe674f2 | C102: https://content.rview.com/ko/?p=17447 | D102: 블로그 | E102: 사이트 태그: 활용팁 (2023.10.17) | F102: 공공기관 외주 용역 관리의 숨은 조력자, 온라인 용역 통제 시스템 | G102: 2023.10.17 | H102: 13937 | I102: 26 | J102: B6
A103: 102 | B103: 282efa49c554 | C103: https://content.rview.com/ko/?p=18745 | D103: 블로그 | E103: 사이트 태그: 기능 (2024.06.14) | F103: \[기능 업데이트\] RS 어시스턴트 | G103: 2024.06.14 | H103: 2686 | I103: 7 | J103: B6
A104: 103 | B104: 6edadeb7f817 | C104: https://content.rview.com/ko/?p=19265 | D104: 블로그 | E104: 사이트 태그: 소식 (2024.11.06) | F104: \[이벤트\] ‘제 24회 공공솔루션마켓’ 행사 참가 안내 | G104: 2024.11.06 | H104: 6369 | I104: 14 | J104: B6
A105: 104 | B105: 0a18a0284d2a | C105: https://content.rview.com/ko/?p=19655 | D105: 블로그 | E105: 사이트 태그: 소식 (2025.02.24) | F105: 정보 보안 국제 표준 ISO/IEC 27001:2022 인증 취득! | G105: 2025.02.24 | H105: 7988 | I105: 16 | J105: B6
A106: 105 | B106: d982b98e20d1 | C106: https://content.rview.com/ko/?p=19735 | D106: 블로그 | E106: 사이트 태그: 소식 (2025.03.06) | F106: \[이벤트\] 알서포트, 제25회 공공솔루션마켓 참가 안내 | G106: 2025.03.06 | H106: 6178 | I106: 14 | J106: B6
A107: 106 | B107: 03f026a436d5 | C107: https://content.rview.com/ko/?p=19867 | D107: 블로그 | E107: 사이트 태그: 소식 (2025.03.27) | F107: AI로 진화한 OT 관리 솔루션 – 리모트뷰 | G107: 2025.03.27 | H107: 8039 | I107: 15 | J107: B6
A108: 107 | B108: d3581b53e37e | C108: https://content.rview.com/ko/?p=19899 | D108: 블로그 | E108: 사이트 태그: 인사이트 (2025.03.28) | F108: 이제는 상주 개발보다 효율적인 원격 개발 시대 | G108: 2025.03.28 | H108: 9264 | I108: 17 | J108: B6
A109: 108 | B109: bea46814a07b | C109: https://content.rview.com/ko/?p=20341 | D109: 블로그 | E109: 사이트 태그: 인사이트 (2025.05.12) | F109: No.1 키오스크 원격제어 서비스 짚어보기: | G109: 2025.05.12 | H109: 12640 | I109: 23 | J109: B6
A110: 109 | B110: 55b79b0f37f2 | C110: https://content.rview.com/ko/?p=20397 | D110: 블로그 | E110: 사이트 태그: 인사이트 (2025.05.16) | F110: \[제조업 랜섬웨어 비상!\] | G110: 2025.05.16 | H110: 13544 | I110: 24 | J110: B6
A111: 110 | B111: 0ba6f1ac53e3 | C111: https://content.rview.com/ko/?p=24689 | D111: 블로그 | E111: 사이트 태그: 인사이트 (2026.03.30) | F111: 설비 교체 없이 5분 만에? 노후 시설 공장 스마트팩토리 구현 전략 | G111: 2026.03.30 | H111: 12707 | I111: 23 | J111: B6
A112: 111 | B112: 2111acd6ec34 | C112: https://content.rview.com/ko/?p=24705 | D112: 블로그 | E112: 사이트 태그: 인사이트 (2026.03.25) | F112: 정부 재택근무 권고와 차량 5부제 의무화: 기업 필수 대응 가이드 | G112: 2026.03.25 | H112: 16949 | I112: 29 | J112: B6
... A119: 118 | B119: 5fafe59d7c38 | C119: https://content.rview.com/ko/?p=24849 | D119: 블로그 | E119: 사이트 태그: 기능 (2026.04.14) | F119: \[리모트뷰 8.5.0 업데이트\] 최대 60FPS로 끊김 없이 부드럽게! MS SSO 연동 & macOS 강화 | G119: 2026.04.14 | H119: 13329 | I119: 24 | J119: B6
A120: 119 | B120: ed3f92a006a7 | C120: https://content.rview.com/ko/?p=24107 | D120: 제품·기능 안내 | E120: 리모트뷰박스 제품 랜딩 (무날짜·기능 사양 서술) | F120: 현장 제어가 필요한 순간, | H120: 2078 | I120: 5 | J120: B2
A121: 120 | B121: 0a81e5359018 | C121: https://content.rview.com/ko/?p=13953 | D121: 구매·안내 페이지 | E121: 라이선스 구매 로그인 안내 (제목 헤딩 부재) | F121: 리모트뷰 라이선스 구매 안내 | H121: 1243 | I121: 5 | J121: B2

Sheet B1_커버리지맵
A1: # | B1: Unit ID | C1: type | D1: title | E1: description | F1: product | G1: feature | H1: user_type | I1: acl_level | J1: intent | K1: source/resource | L1: source_location | M1: related_units | N1: 이 단위가 말하는 사실 | O1: 답변 가능한 질문 | P1: tags | Q1: citation_id | R1: extracted_by | S1: confidence | T1: 상태 | U1: 비고
A2: 1 | B2: RV-MANUAL-ENT-001 | C2: Manual | D2: RemoteView Enterprise SaaS 사용자 가이드 | E2: 이중 로그인을 통한 보안 강화 | F2: RemoteView | G2: 이중 로그인을 통한 보안 강화 | H2: 관리자 | I2: 공개 | J2: 기능/가능 여부 확인 | K2: https://files.rsupport.com/ko/remoteview/guides/RemoteView_Enterprise_SaaS_User_Guide_kr.pdf | L2: chunk 19 / ● 이중 로그인을 통한 보안 강화 | N2: 서비스 이용 최소/권장 환경 리모트뷰에서 사용자는 사용자 페이지 또는 전용 PC 애플리케이션 콘솔을 이용해 원격지 PC를 관리할 수 있습니다. PC 환경은 다음과 같이 사용할 것을 권장합니다. <Windows> 운영체제 Windows 10 이상, Windows Server 2019 이상 ~ Windows 11 25H2 (Standard/Enterprise Edition 기준) CPU Pentium 4 2.0 GHz 메모리 512MB 이상 웹 브라우저 Chrome 100 이상/ Edge 97 이상 Whale 3.15.136.16 이상 / Firefox 96 이상 / Opera 83 이상 네트워크 Modem, ADSL, LAN, 공인 IP 또는 가상 IP 지원 (무선지원) 방화벽 Out Bound 80(http) / 443(https) Port Open *Windows 10 미만 버전(예: Windows 7, 8 등)에서도 제품이 실행될 수는 있으나, 보다 안정적인 사용을 위해 Windows 10 이상 환경에서의 사용을 권장 드립니다. <macOS> 운영체제 OS 13~OS 26 웹 브라우저 Chrome 100 이상 / Safari 16이상 Whale 3.16.138.21 이상 / Firefox 96 이상 /Opera 83 이상 네트워크 Modem, ADSL, LAN, 공인 IP 또는 가상 IP 지원 (무선지원) 방화벽 Out Bound 80(http) / 443(https) Port Open <Linux> (에이전트) 운영체제 Cent OS 7.0 (64bit), Redhat OS 7.0, 8.0(64bit) Ubuntu 18.04, 20.04, 22.04(64bit) Rocky Linux: 8.0 한컴OS Gooroom 2~3, TMax OS 21 웹 브라우저 Chrome 100 이상/ Firefox 96 이상 CPU 1GHz 이상 메모리 512MB 이상 네트워크 Fast Ethernet 방화벽 Out Bound 80(http) / 443(https) Port Open <Android> 뷰어 운영체제 Android 8.0 ~16.0 에이전트 운영체제 Android 8.0 ~16.0 <iOS> (전용 뷰어 앱) 운영체제 iOS 16.0 ~ 26.0 4. 리모트뷰 사용자 페이지 메인 페이지 리모트뷰 사용자 페이지는 모든 사용자가 접속하여 리모트뷰 기능을 사용할 수 있는 페이지입니다. 관리자는 리모트뷰 서비스에 관한 모든 사항을 확인/변경할 수 있습니다. 접속 URL: https://www.rview.com/ 로그인 전 로그인 후 (로그인 후 브라우저의 뒤로 가기 클릭 시, 로그인 정보가 노출되지 않을 경우 브라우저 새로고침 버튼을 클릭하면 로그인 정보 페이지가 노출됩니다.) | O2: RemoteView의 이중 로그인을 통한 보안 강화은(는) 무엇인가요? | P2: RemoteView, ENT, 이중 로그인을 통한 보안 강화 | Q2: RV-MANUAL-ENT-001 | R2: Claude(Fable5) | S2: 상 | T2: 미검토
A3: 2 | B3: RV-MANUAL-ENT-002 | C3: Manual | D3: RemoteView Enterprise SaaS 사용자 가이드 | E3: 메뉴 (LNB_Local Navigation Bar) > 원격지 PC 관리 | F3: RemoteView | G3: 원격지 PC 관리 | H3: 관리자 | I3: 공개 | J3: 기능/가능 여부 확인 | K3: https://files.rsupport.com/ko/remoteview/guides/RemoteView_Enterprise_SaaS_User_Guide_kr.pdf | L3: chunk 24 / §메뉴 (LNB_Local Navigation Bar) / ● 원격지 PC 관리 | N3: 리모트뷰 에이전트가 설치된 기기를 관리하고 원격 접속을 할 수 있는 페이지입니다. | O3: RemoteView의 원격지 PC 관리은(는) 무엇인가요? | P3: RemoteView, ENT, 원격지 PC 관리 | Q3: RV-MANUAL-ENT-002 | R3: Claude(Fable5) | S3: 중 | T3: 미검토
A4: 3 | B4: RV-MANUAL-ENT-003 | C4: Manual | D4: RemoteView Enterprise SaaS 사용자 가이드 | E4: 메뉴 (LNB_Local Navigation Bar) > 라이브뷰 | F4: RemoteView | G4: 라이브뷰 | H4: 관리자 | I4: 공개 | J4: 기능/가능 여부 확인 | K4: https://files.rsupport.com/ko/remoteview/guides/RemoteView_Enterprise_SaaS_User_Guide_kr.pdf | L4: chunk 24 / §메뉴 (LNB_Local Navigation Bar) / ● 라이브뷰 | N4: 등록된 기기를 모니터링 할 수 있는 페이지입니다. | O4: RemoteView의 라이브뷰은(는) 무엇인가요? | P4: RemoteView, ENT, 라이브뷰 | Q4: RV-MANUAL-ENT-003 | R4: Claude(Fable5) | S4: 중 | T4: 미검토
A5: 4 | B5: RV-MANUAL-ENT-004 | C5: Manual | D5: RemoteView Enterprise SaaS 사용자 가이드 | E5: 메뉴 (LNB_Local Navigation Bar) > 사용자 관리 | F5: RemoteView | G5: 사용자 관리 | H5: 관리자 | I5: 공개 | J5: 기능/가능 여부 확인 | K5: https://files.rsupport.com/ko/remoteview/guides/RemoteView_Enterprise_SaaS_User_Guide_kr.pdf | L5: chunk 24 / §메뉴 (LNB_Local Navigation Bar) / ● 사용자 관리 | N5: 등록된 모든 사용자에 대해 관리할 수 있는 페이지입니다. * 관리자, 매니저계정 권한에서만 제공됩니다. | O5: RemoteView의 사용자 관리은(는) 무엇인가요? | P5: RemoteView, ENT, 사용자 관리 | Q5: RV-MANUAL-ENT-004 | R5: Claude(Fable5) | S5: 중 | T5: 미검토
A6: 5 | B6: RV-MANUAL-ENT-005 | C6: Manual | D6: RemoteView Enterprise SaaS 사용자 가이드 | E6: 메뉴 (LNB_Local Navigation Bar) > 조직관리 | F6: RemoteView | G6: 조직관리 | H6: 관리자 | I6: 공개 | J6: 기능/가능 여부 확인 | K6: https://files.rsupport.com/ko/remoteview/guides/RemoteView_Enterprise_SaaS_User_Guide_kr.pdf | L6: chunk 24 / §메뉴 (LNB_Local Navigation Bar) / ● 조직관리 | N6: 사용자 그룹 추가를 통해 등록된 모든 사용자에 대해 관리할 수 있는 페이지입니다. * 관리자, 매니저계정 권한에서만 제공됩니다. | O6: RemoteView의 조직관리은(는) 무엇인가요? | P6: RemoteView, ENT, 조직관리 | Q6: RV-MANUAL-ENT-005 | R6: Claude(Fable5) | S6: 상 | T6: 미검토
A7: 6 | B7: RV-MANUAL-ENT-006 | C7: Manual | D7: RemoteView Enterprise SaaS 사용자 가이드 | E7: 메뉴 (LNB_Local Navigation Bar) > 사용통계 | F7: RemoteView | G7: 사용통계 | H7: 관리자 | I7: 공개 | J7: 기능/가능 여부 확인 | K7: https://files.rsupport.com/ko/remoteview/guides/RemoteView_Enterprise_SaaS_User_Guide_kr.pdf | L7: chunk 24 / §메뉴 (LNB_Local Navigation Bar) / ● 사용통계 | N7: 원격접속 및 제어 이력과 통계가 차트 및 기록으로 제공되는 페이지입니다. | O7: RemoteView의 사용통계은(는) 무엇인가요? | P7: RemoteView, ENT, 사용통계 | Q7: RV-MANUAL-ENT-006 | R7: Claude(Fable5) | S7: 중 | T7: 미검토
A8: 7 | B8: RV-MANUAL-ENT-007 | C8: Manual | D8: RemoteView Enterprise SaaS 사용자 가이드 | E8: 메뉴 (LNB_Local Navigation Bar) > 환경설정 | F8: RemoteView | G8: 환경설정 | H8: 관리자 | I8: 공개 | J8: 기능/가능 여부 확인 | K8: https://files.rsupport.com/ko/remoteview/guides/RemoteView_Enterprise_SaaS_User_Guide_kr.pdf | L8: chunk 24 / §메뉴 (LNB_Local Navigation Bar) / ● 환경설정 | N8: 계정 정보관리, 옵션 설정, 라이선스 구매 및 관리, 매뉴얼과 콘솔 애플리케이션을 다운로드할 수 있는 페이지입니다. | O8: RemoteView의 환경설정은(는) 무엇인가요? | P8: RemoteView, ENT, 환경설정 | Q8: RV-MANUAL-ENT-007 | R8: Claude(Fable5) | S8: 상 | T8: 미검토
A9: 8 | B9: RV-MANUAL-ENT-008 | C9: Manual | D9: RemoteView Enterprise SaaS 사용자 가이드 | E9: 메뉴 (LNB_Local Navigation Bar) > Simple Launcher 설치 | F9: RemoteView | G9: Simple Launcher 설치 | H9: 관리자 | I9: 공개 | J9: 설정/사용 방법 문의 | K9: https://files.rsupport.com/ko/remoteview/guides/RemoteView_Enterprise_SaaS_User_Guide_kr.pdf | L9: chunk 24 / §메뉴 (LNB_Local Navigation Bar) / ● Simple Launcher 설치 | N9: 웹 브라우저에 접속하여 로그인 후 원격제어를 하기 전에 자동으로 Simple Launcher가 설치됩니다. ① 아래 이미지와 같이 Simple Launcher를 설치할 exe파일을 실행합니다. (Simple Launcher 설치 안내 팝업) ② 다운로드 파일을 실행하여, 컴퓨터에 설치를 진행합니다. ③ 웹 브라우저에 Launcher 설치 안내 팝업의 [닫기] 버튼을 클릭하여, 창을 닫고 원격제어 서비스를 이용합니다. | O9: RemoteView에서 Simple Launcher 설치은(는) 어떻게 하나요? | P9: RemoteView, ENT, Simple Launcher 설치 | Q9: RV-MANUAL-ENT-008 | R9: Claude(Fable5) | S9: 상 | T9: 미검토
A10: 9 | B10: RV-MANUAL-ENT-009 | C10: Manual | D10: RemoteView Enterprise SaaS 사용자 가이드 | E10: 메뉴 (LNB_Local Navigation Bar) > Simple Launcher 수동 설치하기 | F10: RemoteView | G10: Simple Launcher 수동 설치하기 | H10: 관리자 | I10: 공개 | J10: 기능/가능 여부 확인 | K10: https://files.rsupport.com/ko/remoteview/guides/RemoteView_Enterprise_SaaS_User_Guide_kr.pdf | L10: chunk 24 / §메뉴 (LNB_Local Navigation Bar) / ● Simple Launcher 수동 설치하기 | N10: 원격제어가 정상적으로 실행되지 않을 경우, Launcher 파일을 수동으로 설치하여 문제를 해결하도록 합니다. 화면 상단의 [Simple Launcher 설치] 메뉴를 클릭하여, 파일을 수동으로 다운로드 받아 설치합니다. (Simple Launcher 설치 메뉴) | O10: RemoteView의 Simple Launcher 수동 설치하기은(는) 무엇인가요? | P10: RemoteView, ENT, Simple Launcher 수동 설 | Q10: RV-MANUAL-ENT-009 | R10: Claude(Fable5) | S10: 상 | T10: 미검토
A11: 10 | B11: RV-MANUAL-ENT-010 | C11: Manual | D11: RemoteView Enterprise SaaS 사용자 가이드 | E11: 메뉴 (LNB_Local Navigation Bar) > Simple Launcher 삭제하기 | F11: RemoteView | G11: Simple Launcher 삭제하기 | H11: 관리자 | I11: 공개 | J11: 설정/사용 방법 문의 | K11: https://files.rsupport.com/ko/remoteview/guides/RemoteView_Enterprise_SaaS_User_Guide_kr.pdf | L11: chunk 24 / §메뉴 (LNB_Local Navigation Bar) / ● Simple Launcher 삭제하기 | N11: ① 시작>제어판>프로그램>프로그램 추가/삭제 or 프로그램 및 기능을 엽니다. ② 프로그램 목록에서 ‘RemoteView Simple Launcher’를 선택합니다. ③ [제거]를 클릭합니다. ④ 삭제 프로세스가 동작합니다. | O11: RemoteView에서 Simple Launcher 삭제하기은(는) 어떻게 하나요? | P11: RemoteView, ENT, Simple Launcher 삭제하기 | Q11: RV-MANUAL-ENT-010 | R11: Claude(Fable5) | S11: 상 | T11: 미검토
A12: 11 | B12: RV-MANUAL-ENT-011 | C12: Manual | D12: RemoteView Enterprise SaaS 사용자 가이드 | E12: 원격지 PC 탐색기 > 즐겨찾기 | F12: RemoteView | G12: 즐겨찾기 | H12: 관리자 | I12: 공개 | J12: 설정 방법 문의 | K12: https://files.rsupport.com/ko/remoteview/guides/RemoteView_Enterprise_SaaS_User_Guide_kr.pdf | L12: chunk 26 / §원격지 PC 탐색기 / ● 즐겨찾기 | N12: 사용자가 주로 사용하는 에이전트에 대해 카테고리를 생성해 사용할 수 있으며 우 클릭 시 제공되는 Context Menu로 보다 쉽게 관리할 수 있습니다. ⮚ 최대 5개 카테고리 생성이 가능하며, 카테고리명은 최소 1글자 이상으로 설정할 수 있습니다. ⮚ 카테고리 명 우측 숫자 표시는 on 상태 PC 와 그룹의 전체 PC의 수를 의미합니다. | O12: RemoteView의 즐겨찾기은(는) 무엇인가요? | P12: RemoteView, ENT, 즐겨찾기 | Q12: RV-MANUAL-ENT-011 | R12: Claude(Fable5) | S12: 상 | T12: 미검토
A13: 12 | B13: RV-MANUAL-ENT-012 | C13: Manual | D13: RemoteView Enterprise SaaS 사용자 가이드 | E13: 원격지 PC 탐색기 > 원격지 PC 리스트 | F13: RemoteView | G13: 원격지 PC 리스트 | H13: 관리자 | I13: 공개 | J13: 기능/가능 여부 확인 | K13: https://files.rsupport.com/ko/remoteview/guides/RemoteView_Enterprise_SaaS_User_Guide_kr.pdf | L13: chunk 26 / §원격지 PC 탐색기 / ● 원격지 PC 리스트 | N13: 대표 아이디에 등록된 모든 그룹과 PC 목록을 트리 구조의 형태로 볼 수 있으며 우 클릭 시 제공되는 Context Menu로 대표, 그룹, PC를 보다 쉽게 관리 및 원격제어 기능을 사용할 수 있습니다. ⮚ 환경설정 or 라이선스 상품에 따라 사용할 수 있는 기능의 차이가 있습니다 ⮚ 그룹 명 우측 숫자 표시는 on 상태 PC 와 그룹의 전체 PC의 수를 의미합니다. | O13: RemoteView의 원격지 PC 리스트은(는) 무엇인가요? | P13: RemoteView, ENT, 원격지 PC 리스트 | Q13: RV-MANUAL-ENT-012 | R13: Claude(Fable5) | S13: 상 | T13: 미검토
... A29: 28 | B29: RV-MANUAL-ENT-028 | C29: Manual | D29: RemoteView Enterprise SaaS 사용자 가이드 | E29: 사용자별 제어 권한 > 보기 | F29: RemoteView | G29: 보기 | H29: 관리자 | I29: 공개 | J29: 설정/사용 방법 문의 | K29: https://files.rsupport.com/ko/remoteview/guides/RemoteView_Enterprise_SaaS_User_Guide_kr.pdf | L29: chunk 34 / §사용자별 제어 권한 / ● 보기 | N29: ① [아이콘으로 표시], [목록으로 표시]을 클릭합니다. ② Contents 영역의 페이지 정렬이 아이콘 정렬, 리스트 정렬로 전환됩니다. | O29: RemoteView에서 보기은(는) 어떻게 하나요? | P29: RemoteView, ENT, 보기 | Q29: RV-MANUAL-ENT-028 | R29: Claude(Fable5) | S29: 상 | T29: 미검토
A30: 29 | B30: RV-MANUAL-ENT-029 | C30: Manual | D30: RemoteView Enterprise SaaS 사용자 가이드 | E30: 사용자별 제어 권한 > 소팅 | F30: RemoteView | G30: 소팅 | H30: 관리자 | I30: 공개 | J30: 기능/가능 여부 확인 | K30: https://files.rsupport.com/ko/remoteview/guides/RemoteView_Enterprise_SaaS_User_Guide_kr.pdf | L30: chunk 34 / §사용자별 제어 권한 / ● 소팅 | N30: 선택한 옵션값대로 목록이 소팅 됩니다. | O30: RemoteView의 소팅은(는) 무엇인가요? | P30: RemoteView, ENT, 소팅 | Q30: RV-MANUAL-ENT-029 | R30: Claude(Fable5) | S30: 하 | T30: 근거약함 | U30: 본문 25자 미만 — 원문 근거 짧음
A31: 30 | B31: RV-MANUAL-ENT-030 | C31: Manual | D31: RemoteView Enterprise SaaS 사용자 가이드 | E31: 사용자별 제어 권한 > 검색 | F31: RemoteView | G31: 검색 | H31: 관리자 | I31: 공개 | J31: 기능/가능 여부 확인 | K31: https://files.rsupport.com/ko/remoteview/guides/RemoteView_Enterprise_SaaS_User_Guide_kr.pdf | L31: chunk 34 / §사용자별 제어 권한 / ● 검색 | N31: 입력한 검색어와 일치하는 데이터가 검색됩니다. 라이브뷰 | O31: RemoteView의 검색은(는) 무엇인가요? | P31: RemoteView, ENT, 검색 | Q31: RV-MANUAL-ENT-030 | R31: Claude(Fable5) | S31: 중 | T31: 미검토
A32: 31 | B32: RV-MANUAL-ENT-031 | C32: Manual | D32: RemoteView Enterprise SaaS 사용자 가이드 | E32: 사용자별 제어 권한 > 새로고침 | F32: RemoteView | G32: 새로고침 | H32: 관리자 | I32: 공개 | J32: 설정/사용 방법 문의 | K32: https://files.rsupport.com/ko/remoteview/guides/RemoteView_Enterprise_SaaS_User_Guide_kr.pdf | L32: chunk 34 / §사용자별 제어 권한 / ● 새로고침 | N32: ① [새로고침] 아이콘을 클릭합니다. ② 웹 페이지 화면의 데이터가 갱신됩니다. | O32: RemoteView에서 새로고침은(는) 어떻게 하나요? | P32: RemoteView, ENT, 새로고침 | Q32: RV-MANUAL-ENT-031 | R32: Claude(Fable5) | S32: 중 | T32: 미검토
A33: 32 | B33: RV-MANUAL-ENT-032 | C33: Manual | D33: RemoteView Enterprise SaaS 사용자 가이드 | E33: 사용자별 제어 권한 > 즐겨찾기 | F33: RemoteView | G33: 즐겨찾기 | H33: 관리자 | I33: 공개 | J33: 설정/사용 방법 문의 | K33: https://files.rsupport.com/ko/remoteview/guides/RemoteView_Enterprise_SaaS_User_Guide_kr.pdf | L33: chunk 34 / §사용자별 제어 권한 / ● 즐겨찾기 | N33: ① [즐겨찾기 추가] 아이콘을 클릭합니다. <접근방법> 1 툴바 > [즐겨찾기 추가] 버튼 클릭 2 원격지PC탐색기 -> PC 마우스 오른쪽 버튼 클릭 -> ‘즐겨찾기’ 클릭 3 Contents 영역 -> PC 마우스 오른쪽 버튼 클릭 -> ‘즐겨찾기’ 클릭 ② 카테고리를 선택합니다. ③ [적용] or [취소] 버튼을 클릭합니다. ④ [적용] : 선택한 카테고리에 PC 추가 ✔ [적용] : 선택한 카테고리에 PC 추가 ✔ [취소] : 취소 | O33: RemoteView에서 즐겨찾기은(는) 어떻게 하나요? | P33: RemoteView, ENT, 즐겨찾기 | Q33: RV-MANUAL-ENT-032 | R33: Claude(Fable5) | S33: 상 | T33: 미검토
A34: 33 | B34: RV-MANUAL-ENT-033 | C34: Manual | D34: RemoteView Enterprise SaaS 사용자 가이드 | E34: 사용자별 제어 권한 > 이동 | F34: RemoteView | G34: 이동 | H34: 관리자 | I34: 공개 | J34: 설정/사용 방법 문의 | K34: https://files.rsupport.com/ko/remoteview/guides/RemoteView_Enterprise_SaaS_User_Guide_kr.pdf | L34: chunk 35 / §사용자별 제어 권한 / ● 이동 | N34: ① [이동] 아이콘을 클릭합니다. <접근방법> 즐겨찾기 그룹 선택 -> PC 선택 -> 툴바 [이동] 버튼 클릭 ② 에이전트 그룹 이동 팝업이 노출됩니다. ③ 이동할 그룹을 선택합니다. ④ [적용] or [취소] 버튼을 클릭합니다. ✔ [적용] : 선택한 그룹으로 PC 이동 ✔ [취소] : 취소 | O34: RemoteView에서 이동은(는) 어떻게 하나요? | P34: RemoteView, ENT, 이동 | Q34: RV-MANUAL-ENT-033 | R34: Claude(Fable5) | S34: 상 | T34: 미검토
A35: 34 | B35: RV-MANUAL-ENT-034 | C35: Manual | D35: RemoteView Enterprise SaaS 사용자 가이드 | E35: 사용자별 제어 권한 > 삭제 | F35: RemoteView | G35: 삭제 | H35: 관리자 | I35: 공개 | J35: 설정/사용 방법 문의 | K35: https://files.rsupport.com/ko/remoteview/guides/RemoteView_Enterprise_SaaS_User_Guide_kr.pdf | L35: chunk 35 / §사용자별 제어 권한 / ● 삭제 | N35: ① [삭제] 아이콘을 클릭합니다. <접근방법> 1 즐겨찾기 그룹 선택 -> PC 선택 -> 툴바 [삭제] 버튼 클릭 2 즐겨찾기 그룹 선택 -> PC 마우스 오른쪽 버튼 클릭 -> ‘삭제’ 클릭 ② “삭제하시겠습니까?” 메시지창이 팝업 됩니다. ⮚ 보안확인 설정 시 보안확인창 팝업이 노출됩니다. ③ [적용] or [취소] 버튼을 클릭합니다. ✔ [적용] : 선택한 그룹 or PC 삭제 ✔ [취소] : 취소 | O35: RemoteView에서 삭제은(는) 어떻게 하나요? | P35: RemoteView, ENT, 삭제 | Q35: RV-MANUAL-ENT-034 | R35: Claude(Fable5) | S35: 상 | T35: 미검토
A36: 35 | B36: RV-MANUAL-ENT-035 | C36: Manual | D36: RemoteView Enterprise SaaS 사용자 가이드 | E36: 사용자별 제어 권한 > 크게보기 | F36: RemoteView | G36: 크게보기 | H36: 관리자 | I36: 공개 | J36: 설정/사용 방법 문의 | K36: https://files.rsupport.com/ko/remoteview/guides/RemoteView_Enterprise_SaaS_User_Guide_kr.pdf | L36: chunk 35 / §사용자별 제어 권한 / ● 크게보기 | N36: ① [크게보기] 아이콘을 클릭합니다. <접근방법> 1 ON 상태 PC 선택 -> 툴바 [크게보기] 버튼 클릭 2 원격지 PC 탐색기 영역 -> ON 상태 PC마우스 오른쪽 버튼 클릭 -> ‘크게보기’ 또는 ‘재생’ 클릭 3 Contents 영역 -> ON 상태 PC 마우스 오른쪽 버튼 클릭 -> ‘크게보기’ 또는 ‘재생’ 클릭 ② 라이브뷰 팝업이 노출됩니다. ③ 원격지 PC 화면이 라이브뷰 팝업으로 보여 집니다. | O36: RemoteView에서 크게보기은(는) 어떻게 하나요? | P36: RemoteView, ENT, 크게보기 | Q36: RV-MANUAL-ENT-035 | R36: Claude(Fable5) | S36: 상 | T36: 미검토
A37: 36 | B37: RV-MANUAL-ENT-036 | C37: Manual | D37: RemoteView Enterprise SaaS 사용자 가이드 | E37: 사용자별 제어 권한 > 등록정보 | F37: RemoteView | G37: 등록정보 | H37: 관리자 | I37: 공개 | J37: 설정/사용 방법 문의 | K37: https://files.rsupport.com/ko/remoteview/guides/RemoteView_Enterprise_SaaS_User_Guide_kr.pdf | L37: chunk 35 / §사용자별 제어 권한 / ● 등록정보 | N37: ① [등록정보] 아이콘을 클릭합니다. <접근방법> 1 툴바 > [등록정보] 버튼 클릭 2 그룹, PC 마우스 오른쪽 버튼 클릭 -> ‘등록정보’’ 클릭 ② 그룹 or PC 등록정보 팝업이 노출됩니다. ③ 데이터를 변경합니다. ④ [적용] or [취소] 버튼을 클릭합니다. ✔ [적용] : 변경된 데이터로 등록정보가 변경됩니다. ✔ [취소] : 기존 데이터가 유지됩니다. | O37: RemoteView에서 등록정보은(는) 어떻게 하나요? | P37: RemoteView, ENT, 등록정보 | Q37: RV-MANUAL-ENT-036 | R37: Claude(Fable5) | S37: 상 | T37: 미검토
A38: 37 | B38: RV-MANUAL-ENT-037 | C38: Manual | D38: RemoteView Enterprise SaaS 사용자 가이드 | E38: 사용자별 제어 권한 > 슬라이더 | F38: RemoteView | G38: 슬라이더 | H38: 관리자 | I38: 공개 | J38: 설정/사용 방법 문의 | K38: https://files.rsupport.com/ko/remoteview/guides/RemoteView_Enterprise_SaaS_User_Guide_kr.pdf | L38: chunk 35 / §사용자별 제어 권한 / ● 슬라이더 | N38: ① 슬라이더 Bar에 마우스 클릭을 합니다. ② Bar를 좌, 우로 이동합니다. ③ Contents 영역의 화면 아이콘 크기가 축소되거나, 확대됩니다. 화면의 아이콘 크기가 조절됩니다. | O38: RemoteView에서 슬라이더은(는) 어떻게 하나요? | P38: RemoteView, ENT, 슬라이더 | Q38: RV-MANUAL-ENT-037 | R38: Claude(Fable5) | S38: 상 | T38: 미검토
A39: 38 | B39: RV-MANUAL-ENT-038 | C39: Manual | D39: RemoteView Enterprise SaaS 사용자 가이드 | E39: 사용자별 제어 권한 > 소팅 | F39: RemoteView | G39: 소팅 | H39: 관리자 | I39: 공개 | J39: 기능/가능 여부 확인 | K39: https://files.rsupport.com/ko/remoteview/guides/RemoteView_Enterprise_SaaS_User_Guide_kr.pdf | L39: chunk 36 / §사용자별 제어 권한 / ● 소팅 | N39: 선택한 옵션값 대로 목록이 소팅 됩니다. | O39: RemoteView의 소팅은(는) 무엇인가요? | P39: RemoteView, ENT, 소팅 | Q39: RV-MANUAL-ENT-038 | R39: Claude(Fable5) | S39: 하 | T39: 근거약함 | U39: 본문 25자 미만 — 원문 근거 짧음
A40: 39 | B40: RV-MANUAL-ENT-039 | C40: Manual | D40: RemoteView Enterprise SaaS 사용자 가이드 | E40: 사용자별 제어 권한 > 검색 | F40: RemoteView | G40: 검색 | H40: 관리자 | I40: 공개 | J40: 기능/가능 여부 확인 | K40: https://files.rsupport.com/ko/remoteview/guides/RemoteView_Enterprise_SaaS_User_Guide_kr.pdf | L40: chunk 36 / §사용자별 제어 권한 / ● 검색 | N40: 입력한 검색어와 일치하는 데이터가 검색됩니다. | O40: RemoteView의 검색은(는) 무엇인가요? | P40: RemoteView, ENT, 검색 | Q40: RV-MANUAL-ENT-039 | R40: Claude(Fable5) | S40: 중 | T40: 미검토
A41: 40 | B41: RV-MANUAL-ENT-040 | C41: Manual | D41: RemoteView Enterprise SaaS 사용자 가이드 | E41: 사용자/조직관리 > 원격지 PC > 새로고침 | F41: RemoteView | G41: 새로고침 | H41: 관리자 | I41: 공개 | J41: 설정/사용 방법 문의 | K41: https://files.rsupport.com/ko/remoteview/guides/RemoteView_Enterprise_SaaS_User_Guide_kr.pdf | L41: chunk 36 / §사용자/조직관리 > 원격지 PC / ● 새로고침 | N41: ① [새로고침] 아이콘을 클릭합니다. ② 웹 페이지 화면의 데이터가 갱신됩니다. | O41: RemoteView에서 새로고침은(는) 어떻게 하나요? | P41: RemoteView, ENT, 새로고침 | Q41: RV-MANUAL-ENT-040 | R41: Claude(Fable5) | S41: 중 | T41: 미검토
A42: 41 | B42: RV-MANUAL-ENT-041 | C42: Manual | D42: RemoteView Enterprise SaaS 사용자 가이드 | E42: 사용자/조직관리 > 원격지 PC > 매니저 추가 | F42: RemoteView | G42: 매니저 추가 | H42: 관리자 | I42: 공개 | J42: 설정/사용 방법 문의 | K42: https://files.rsupport.com/ko/remoteview/guides/RemoteView_Enterprise_SaaS_User_Guide_kr.pdf | L42: chunk 36 / §사용자/조직관리 > 원격지 PC / ● 매니저 추가 | N42: ① [매니저 추가] 아이콘을 클릭합니다. <접근방법> 1 툴바 > [매니저 추가] 버튼 클릭 2 마우스 오른쪽 버튼 클릭 -> ‘매니저 추가’ 클릭 3 하단 상세정보 -> 추가기능 -> ‘매니저 추가’ 클릭 ② 사용자 정보를 입력합니다. ③ [적용] or [취소] 버튼을 클릭합니다. ✔ [적용] : 새로운 매니저가 추가됩니다. ✔ [취소] : 취소 | O42: RemoteView에서 매니저 추가은(는) 어떻게 하나요? | P42: RemoteView, ENT, 매니저 추가 | Q42: RV-MANUAL-ENT-041 | R42: Claude(Fable5) | S42: 상 | T42: 미검토
A43: 42 | B43: RV-MANUAL-ENT-042 | C43: Manual | D43: RemoteView Enterprise SaaS 사용자 가이드 | E43: 사용자/조직관리 > 원격지 PC > 사용자 추가 | F43: RemoteView | G43: 사용자 추가 | H43: 관리자 | I43: 공개 | J43: 설정/사용 방법 문의 | K43: https://files.rsupport.com/ko/remoteview/guides/RemoteView_Enterprise_SaaS_User_Guide_kr.pdf | L43: chunk 36 / §사용자/조직관리 > 원격지 PC / ● 사용자 추가 | N43: ① [사용자 추가] 아이콘을 클릭합니다. <접근방법> 1 툴바 > [사용자 추가] 버튼 클릭 2 마우스 오른쪽 버튼 클릭 -> ‘사용자 추가’ 클릭 3 하단 상세정보 -> 추가기능 -> ‘사용자 추가’ 클릭 ② 사용자 정보를 입력합니다. ③ [적용] or [취소] 버튼을 클릭합니다. ✔ [적용] : 새로운 사용자가 추가됩니다. ✔ [취소] : 취소 | O43: RemoteView에서 사용자 추가은(는) 어떻게 하나요? | P43: RemoteView, ENT, 사용자 추가 | Q43: RV-MANUAL-ENT-042 | R43: Claude(Fable5) | S43: 상 | T43: 미검토
A44: 43 | B44: RV-MANUAL-ENT-043 | C44: Manual | D44: RemoteView Enterprise SaaS 사용자 가이드 | E44: 사용자/조직관리 > 원격지 PC > 즐겨찾기 | F44: RemoteView | G44: 즐겨찾기 | H44: 관리자 | I44: 공개 | J44: 설정/사용 방법 문의 | K44: https://files.rsupport.com/ko/remoteview/guides/RemoteView_Enterprise_SaaS_User_Guide_kr.pdf | L44: chunk 37 / §사용자/조직관리 > 원격지 PC / ● 즐겨찾기 | N44: ① [즐겨찾기] 아이콘을 클릭합니다. <접근방법> 1 툴바 > [즐겨찾기] 버튼 클릭 2 마우스 오른쪽 버튼 클릭 -> ‘즐겨찾기’ 클릭 3 하단 상세정보 -> 추가기능 -> ‘즐겨찾기’ 클릭 ② 카테고리를 선택합니다. ③ [적용] or [취소] 버튼을 클릭합니다. ✔ [적용] : 선택한 카테고리에 사용자 추가 ✔ [취소] : 취소 | O44: RemoteView에서 즐겨찾기은(는) 어떻게 하나요? | P44: RemoteView, ENT, 즐겨찾기 | Q44: RV-MANUAL-ENT-043 | R44: Claude(Fable5) | S44: 상 | T44: 미검토
A45: 44 | B45: RV-MANUAL-ENT-044 | C45: Manual | D45: RemoteView Enterprise SaaS 사용자 가이드 | E45: 사용자/조직관리 > 원격지 PC > 사용자 권한 할당 | F45: RemoteView | G45: 사용자 권한 할당 | H45: 관리자 | I45: 공개 | J45: 설정/사용 방법 문의 | K45: https://files.rsupport.com/ko/remoteview/guides/RemoteView_Enterprise_SaaS_User_Guide_kr.pdf | L45: chunk 37 / §사용자/조직관리 > 원격지 PC / ● 사용자 권한 할당 | N45: ① [사용자 권한 할당] 아이콘을 클릭합니다. <접근방법> 1 툴바 > [사용자 권한 할당] 버튼 클릭 2 사용자 마우스 오른쪽 버튼 클릭 -> ‘권한 할당’ 클릭 3 하단 상세정보 -> 추가기능 -> ‘권한 할당’ 클릭 ② 사용자 권한 할당 팝업이 노출됩니다. ③ 그룹, 에이전트를 선택합니다. ④ [적용] or [취소] 버튼을 클릭합니다. ✔ [적용] : 선택한 그룹, 에이전트에 사용자 할당 ✔ [취소] : 취소 참고: 상단 체크박스 선택/해제 시, 하단 사용자제어권한 열의 체크박스가 모두 일괄 선택/해제됩니다. 사용자 권한 이 [할당불가]인 경우, 권한 제어가 비활성 되어 있으므로 일괄선택/일괄해제가 불가능하고 [할당가능], [변경가능] 상태만 일괄선택/일괄해제 가능합니다. | O45: RemoteView에서 사용자 권한 할당은(는) 어떻게 하나요? | P45: RemoteView, ENT, 사용자 권한 할당 | Q45: RV-MANUAL-ENT-044 | R45: Claude(Fable5) | S45: 상 | T45: 미검토
A46: 45 | B46: RV-MANUAL-ENT-045 | C46: Manual | D46: RemoteView Enterprise SaaS 사용자 가이드 | E46: 사용자/조직관리 > 원격지 PC > 이동(즐겨찾기) | F46: RemoteView | G46: 이동(즐겨찾기) | H46: 관리자 | I46: 공개 | J46: 설정/사용 방법 문의 | K46: https://files.rsupport.com/ko/remoteview/guides/RemoteView_Enterprise_SaaS_User_Guide_kr.pdf | L46: chunk 37 / §사용자/조직관리 > 원격지 PC / ● 이동(즐겨찾기) | N46: ① [이동] 아이콘을 클릭합니다. <접근방법> 툴바 > [이동] 버튼 클릭 ② 즐겨찾기 이동 팝업 됩니다. ③ 이동할 그룹을 선택합니다. ④ [적용] or [취소] 버튼을 클릭합니다. ✔ [적용] : 선택한 즐겨찾기 카테고리에 사용자 추가 ✔ [취소] : 취소 | O46: RemoteView에서 이동(즐겨찾기)은(는) 어떻게 하나요? | P46: RemoteView, ENT, 이동(즐겨찾기) | Q46: RV-MANUAL-ENT-045 | R46: Claude(Fable5) | S46: 상 | T46: 미검토
A47: 46 | B47: RV-MANUAL-ENT-046 | C47: Manual | D47: RemoteView Enterprise SaaS 사용자 가이드 | E47: 사용자/조직관리 > 원격지 PC > 삭제 | F47: RemoteView | G47: 삭제 | H47: 관리자 | I47: 공개 | J47: 설정/사용 방법 문의 | K47: https://files.rsupport.com/ko/remoteview/guides/RemoteView_Enterprise_SaaS_User_Guide_kr.pdf | L47: chunk 38 / §사용자/조직관리 > 원격지 PC / ● 삭제 | N47: ① [삭제] 아이콘을 클릭합니다. <접근방법> 1 툴바 > [삭제] 버튼 클릭 2 마우스 오른쪽 버튼 클릭 -> ‘삭제’ 클릭 3 하단 상세정보 -> 추가기능 -> ‘삭제’ 클릭 ② “삭제하시겠습니까?” 메시지창이 팝업이 노출됩니다. ⮚ 보안확인 설정 시 보안 확인 창 팝업이 노출됩니다. ③ [적용] or [취소] 버튼을 클릭합니다. ✔ [적용] : 선택한 사용자 삭제 ✔ [취소] : 취소 | O47: RemoteView에서 삭제은(는) 어떻게 하나요? | P47: RemoteView, ENT, 삭제 | Q47: RV-MANUAL-ENT-046 | R47: Claude(Fable5) | S47: 상 | T47: 미검토
A48: 47 | B48: RV-MANUAL-ENT-047 | C48: Manual | D48: RemoteView Enterprise SaaS 사용자 가이드 | E48: 사용자/조직관리 > 원격지 PC > 등록정보 | F48: RemoteView | G48: 등록정보 | H48: 관리자 | I48: 공개 | J48: 설정/사용 방법 문의 | K48: https://files.rsupport.com/ko/remoteview/guides/RemoteView_Enterprise_SaaS_User_Guide_kr.pdf | L48: chunk 38 / §사용자/조직관리 > 원격지 PC / ● 등록정보 | N48: ① [등록정보] 아이콘을 클릭합니다. <접근방법> 1 툴바 > [등록정보] 버튼 클릭 2 마우스 오른쪽 버튼 클릭 -> ‘등록정보’ 클릭 3 하단 상세정보 -> 추가기능 -> ‘등록정보’ 클릭 ② 사용자 등록정보 팝업이 노출됩니다. 이메일 항목은 이메일 등록 여부 및 인증 상태에 따라 미등록, 미인증, 인증완료로 표시됩니다. - 미등록 : 이메일이 등록되지 않은 상태 - 미인증 : 이메일이 등록되어 있으나 인증 절차를 완료하지 않은 상태 - 인증완료 : 등록된 이메일로 인증 완료된 상태 대표 옵션 설정에서 이메일 보안 강화 설정에 따라 이메일 미등록이나 미인증 상태에서는 로그인, 에이전트 연결 등이 제한될 수 있습니다. ③ 데이터를 변경합니다. ④ 사용자/매니저 계정에 ‘에이전트 설치 허용’옵션 적용하여 에이전트 등록 권한과 설치 허용 대수(제한없음 또는 1~5대)를 설정할 수 있습니다. ⑤ [적용] or [취소] 버튼을 클릭합니다. ✔ [적용] : 사용자 등록정보 변경 ✔ [취소] : 기존 데이터가 유지 | O48: RemoteView에서 등록정보은(는) 어떻게 하나요? | P48: RemoteView, ENT, 등록정보 | Q48: RV-MANUAL-ENT-047 | R48: Claude(Fable5) | S48: 상 | T48: 미검토
A49: 48 | B49: RV-MANUAL-ENT-048 | C49: Manual | D49: RemoteView Enterprise SaaS 사용자 가이드 | E49: 사용자 별 에이전트 설치 수 제한 기능 > 엑셀 파일로 내보내기 | F49: RemoteView | G49: 엑셀 파일로 내보내기 | H49: 관리자 | I49: 공개 | J49: 설정/사용 방법 문의 | K49: https://files.rsupport.com/ko/remoteview/guides/RemoteView_Enterprise_SaaS_User_Guide_kr.pdf | L49: chunk 39 / §사용자 별 에이전트 설치 수 제한 기능 / ● 엑셀 파일로 내보내기 | N49: ① [엑셀 파일로 내보내기] 아이콘을 클릭합니다. <접근방법> 툴바 > [엑셀 파일로 내보내기] 버튼 클릭 ✔ [저장] : user-list.xlsx 파일이 PC에 저장됩니다. | O49: RemoteView에서 엑셀 파일로 내보내기은(는) 어떻게 하나요? | P49: RemoteView, ENT, 엑셀 파일로 내보내기 | Q49: RV-MANUAL-ENT-048 | R49: Claude(Fable5) | S49: 상 | T49: 미검토
A50: 49 | B50: RV-MANUAL-ENT-049 | C50: Manual | D50: RemoteView Enterprise SaaS 사용자 가이드 | E50: 사용자 별 에이전트 설치 수 제한 기능 > 엑셀 파일로 일괄등록 | F50: RemoteView | G50: 엑셀 파일로 일괄등록 | H50: 관리자 | I50: 공개 | J50: 설정/사용 방법 문의 | K50: https://files.rsupport.com/ko/remoteview/guides/RemoteView_Enterprise_SaaS_User_Guide_kr.pdf | L50: chunk 39 / §사용자 별 에이전트 설치 수 제한 기능 / ● 엑셀 파일로 일괄등록 | N50: ① [엑셀 파일로 일괄등록] 아이콘을 클릭합니다. <접근방법> 툴바 -> [엑셀 파일로 일괄등록] 버튼 클릭 ② 사용자 정보 일괄 등록 팝업 확인 ✔ [엑셀 양식 다운로드] : 사용자 정보 양식 .xlsx파일이 PC에 저장됩니다. ✔ [파일 선택] : Windows 파일 탐색기가 열립니다. ③ [등록] or [취소] 버튼을 클릭합니다. ✔ [등록] : 저장한 사용자 정보.xlsx파일이 등록됩니다. ✔ [취소] : 사용자 정보 일괄 등록 팝업 창이 닫힙니다. | O50: RemoteView에서 엑셀 파일로 일괄등록은(는) 어떻게 하나요? | P50: RemoteView, ENT, 엑셀 파일로 일괄등록 | Q50: RV-MANUAL-ENT-049 | R50: Claude(Fable5) | S50: 상 | T50: 미검토
A51: 50 | B51: RV-MANUAL-ENT-050 | C51: Manual | D51: RemoteView Enterprise SaaS 사용자 가이드 | E51: 사용자 별 에이전트 설치 수 제한 기능 > 소팅 | F51: RemoteView | G51: 소팅 | H51: 관리자 | I51: 공개 | J51: 기능/가능 여부 확인 | K51: https://files.rsupport.com/ko/remoteview/guides/RemoteView_Enterprise_SaaS_User_Guide_kr.pdf | L51: chunk 39 / §사용자 별 에이전트 설치 수 제한 기능 / ● 소팅 | N51: 전체보기/사용자 보기/그룹 보기의 옵션 값 대로 목록이 소팅 됩니다. | O51: RemoteView의 소팅은(는) 무엇인가요? | P51: RemoteView, ENT, 소팅 | Q51: RV-MANUAL-ENT-050 | R51: Claude(Fable5) | S51: 중 | T51: 미검토
A52: 51 | B52: RV-MANUAL-ENT-051 | C52: Manual | D52: RemoteView Enterprise SaaS 사용자 가이드 | E52: 사용자 별 에이전트 설치 수 제한 기능 > 소팅 | F52: RemoteView | G52: 소팅 | H52: 관리자 | I52: 공개 | J52: 기능/가능 여부 확인 | K52: https://files.rsupport.com/ko/remoteview/guides/RemoteView_Enterprise_SaaS_User_Guide_kr.pdf | L52: chunk 39 / §사용자 별 에이전트 설치 수 제한 기능 / ● 소팅 (2차) | N52: 선택한 옵션값대로 목록이 소팅 됩니다. | O52: RemoteView의 소팅은(는) 무엇인가요? | P52: RemoteView, ENT, 소팅 | Q52: RV-MANUAL-ENT-051 | R52: Claude(Fable5) | S52: 하 | T52: 근거약함 | U52: 본문 25자 미만 — 원문 근거 짧음
A53: 52 | B53: RV-MANUAL-ENT-052 | C53: Manual | D53: RemoteView Enterprise SaaS 사용자 가이드 | E53: 사용자 별 에이전트 설치 수 제한 기능 > 검색 | F53: RemoteView | G53: 검색 | H53: 관리자 | I53: 공개 | J53: 기능/가능 여부 확인 | K53: https://files.rsupport.com/ko/remoteview/guides/RemoteView_Enterprise_SaaS_User_Guide_kr.pdf | L53: chunk 39 / §사용자 별 에이전트 설치 수 제한 기능 / ● 검색 | N53: 입력한 검색어와 일치하는 데이터가 검색됩니다. | O53: RemoteView의 검색은(는) 무엇인가요? | P53: RemoteView, ENT, 검색 | Q53: RV-MANUAL-ENT-052 | R53: Claude(Fable5) | S53: 중 | T53: 미검토
A54: 53 | B54: RV-MANUAL-ENT-053 | C54: Manual | D54: RemoteView Enterprise SaaS 사용자 가이드 | E54: 사용자/조직관리 > 사용자 조직 > 새로고침 | F54: RemoteView | G54: 새로고침 | H54: 관리자 | I54: 공개 | J54: 설정/사용 방법 문의 | K54: https://files.rsupport.com/ko/remoteview/guides/RemoteView_Enterprise_SaaS_User_Guide_kr.pdf | L54: chunk 39 / §사용자/조직관리 > 사용자 조직 / ● 새로고침 | N54: ① [새로고침] 아이콘을 클릭합니다. ② 웹 페이지 화면의 데이터가 갱신됩니다. | O54: RemoteView에서 새로고침은(는) 어떻게 하나요? | P54: RemoteView, ENT, 새로고침 | Q54: RV-MANUAL-ENT-053 | R54: Claude(Fable5) | S54: 중 | T54: 미검토
A55: 54 | B55: RV-MANUAL-ENT-054 | C55: Manual | D55: RemoteView Enterprise SaaS 사용자 가이드 | E55: 사용자/조직관리 > 사용자 조직 > 매니저 추가 | F55: RemoteView | G55: 매니저 추가 | H55: 관리자 | I55: 공개 | J55: 설정/사용 방법 문의 | K55: https://files.rsupport.com/ko/remoteview/guides/RemoteView_Enterprise_SaaS_User_Guide_kr.pdf | L55: chunk 39 / §사용자/조직관리 > 사용자 조직 / ● 매니저 추가 | N55: ① [매니저 추가] 아이콘을 클릭합니다. <접근방법> 1 툴바 > [매니저 추가] 버튼 클릭 2 마우스 오른쪽 버튼 클릭 -> ‘매니저 추가’ 클릭 ② 사용자 정보를 입력합니다. ③ [적용] or [취소] 버튼을 클릭합니다. ✔ [적용] : 새로운 매니저가 추가됩니다. ✔ [취소] : 취소 | O55: RemoteView에서 매니저 추가은(는) 어떻게 하나요? | P55: RemoteView, ENT, 매니저 추가 | Q55: RV-MANUAL-ENT-054 | R55: Claude(Fable5) | S55: 상 | T55: 미검토
A56: 55 | B56: RV-MANUAL-ENT-055 | C56: Manual | D56: RemoteView Enterprise SaaS 사용자 가이드 | E56: 사용자/조직관리 > 사용자 조직 > 사용자 추가 | F56: RemoteView | G56: 사용자 추가 | H56: 관리자 | I56: 공개 | J56: 설정/사용 방법 문의 | K56: https://files.rsupport.com/ko/remoteview/guides/RemoteView_Enterprise_SaaS_User_Guide_kr.pdf | L56: chunk 39 / §사용자/조직관리 > 사용자 조직 / ● 사용자 추가 | N56: ① [사용자 추가] 아이콘을 클릭합니다. <접근방법> 1 툴바 > [사용자 추가] 버튼 클릭 2 마우스 오른쪽 버튼 클릭 -> ‘사용자 추가’ 클릭 ② 사용자 정보를 입력합니다. ③ [적용] or [취소] 버튼을 클릭합니다. ✔ [적용] : 새로운 사용자가 추가됩니다. ✔ [취소] : 취소 | O56: RemoteView에서 사용자 추가은(는) 어떻게 하나요? | P56: RemoteView, ENT, 사용자 추가 | Q56: RV-MANUAL-ENT-055 | R56: Claude(Fable5) | S56: 상 | T56: 미검토
A57: 56 | B57: RV-MANUAL-ENT-056 | C57: Manual | D57: RemoteView Enterprise SaaS 사용자 가이드 | E57: 사용자/조직관리 > 사용자 조직 > 사용자 그룹 추가 | F57: RemoteView | G57: 사용자 그룹 추가 | H57: 관리자 | I57: 공개 | J57: 설정/사용 방법 문의 | K57: https://files.rsupport.com/ko/remoteview/guides/RemoteView_Enterprise_SaaS_User_Guide_kr.pdf | L57: chunk 39 / §사용자/조직관리 > 사용자 조직 / ● 사용자 그룹 추가 | N57: ① [사용자 그룹 추가] 아이콘을 클릭합니다. <접근방법> 툴바 > [사용자 그룹 추가] 버튼 클릭 ② 사용자 그룹 정보를 입력합니다. ③ [적용] or [취소] 버튼을 클릭합니다. ✔ [적용] : 새로운 사용자 그룹이 추가됩니다. ✔ [취소] : 취소 | O57: RemoteView에서 사용자 그룹 추가은(는) 어떻게 하나요? | P57: RemoteView, ENT, 사용자 그룹 추가 | Q57: RV-MANUAL-ENT-056 | R57: Claude(Fable5) | S57: 상 | T57: 미검토
A58: 57 | B58: RV-MANUAL-ENT-057 | C58: Manual | D58: RemoteView Enterprise SaaS 사용자 가이드 | E58: 사용자/조직관리 > 사용자 조직 > 담당 매니저 설정 | F58: RemoteView | G58: 담당 매니저 설정 | H58: 관리자 | I58: 공개 | J58: 설정/사용 방법 문의 | K58: https://files.rsupport.com/ko/remoteview/guides/RemoteView_Enterprise_SaaS_User_Guide_kr.pdf | L58: chunk 40 / §사용자/조직관리 > 사용자 조직 / ● 담당 매니저 설정 | N58: ① Contents 영역 > 사용자 그룹을 선택합니다. ② 마우스 오른쪽 버튼 클릭 > [등록정보] 버튼을 클릭합니다. ③ 사용자 그룹 정보 수정 팝업에서 담당 매니저를 선택합니다. ④ [적용] or [취소] 버튼을 클릭합니다. ✔ [적용] : 새로운 사용자 그룹이 추가됩니다. ✔ [취소] : 취소 | O58: RemoteView에서 담당 매니저 설정은(는) 어떻게 하나요? | P58: RemoteView, ENT, 담당 매니저 설정 | Q58: RV-MANUAL-ENT-057 | R58: Claude(Fable5) | S58: 상 | T58: 미검토
A59: 58 | B59: RV-MANUAL-ENT-058 | C59: Manual | D59: RemoteView Enterprise SaaS 사용자 가이드 | E59: 사용자/조직관리 > 사용자 조직 > 이동 | F59: RemoteView | G59: 이동 | H59: 관리자 | I59: 공개 | J59: 설정/사용 방법 문의 | K59: https://files.rsupport.com/ko/remoteview/guides/RemoteView_Enterprise_SaaS_User_Guide_kr.pdf | L59: chunk 40 / §사용자/조직관리 > 사용자 조직 / ● 이동 | N59: ① Contents 영역 -> 이동할 그룹/매니저/사용자를 선택합니다. ② [이동] 아이콘을 클릭합니다. <접근방법> 툴바 > [이동] 버튼 클릭합니다. ③ 사용자 그룹 이동 팝업이 노출됩니다. ④ 이동할 그룹을 선택합니다. ⑤ [적용] or [취소] 버튼을 클릭합니다. ✔ [적용] : 선택한 그룹에 사용자 추가 ✔ [취소] : 취소 | O59: RemoteView에서 이동은(는) 어떻게 하나요? | P59: RemoteView, ENT, 이동 | Q59: RV-MANUAL-ENT-058 | R59: Claude(Fable5) | S59: 상 | T59: 미검토
A60: 59 | B60: RV-MANUAL-ENT-059 | C60: Manual | D60: RemoteView Enterprise SaaS 사용자 가이드 | E60: 사용자/조직관리 > 사용자 조직 > 삭제 | F60: RemoteView | G60: 삭제 | H60: 관리자 | I60: 공개 | J60: 설정/사용 방법 문의 | K60: https://files.rsupport.com/ko/remoteview/guides/RemoteView_Enterprise_SaaS_User_Guide_kr.pdf | L60: chunk 40 / §사용자/조직관리 > 사용자 조직 / ● 삭제 | N60: ① [삭제] 아이콘을 클릭합니다. <접근방법> 툴바 > [삭제] 버튼 클릭합니다. ② “정말로 삭제하시겠습니까?” 메시지창 팝업이 노출됩니다. ⮚ 보안확인 설정 시 보안확인창 팝업이 노출됩니다. ③ [적용] or [취소] 버튼을 클릭합니다. ✔ [적용] : 선택한 사용자 삭제 ✔ [취소] : 취소 | O60: RemoteView에서 삭제은(는) 어떻게 하나요? | P60: RemoteView, ENT, 삭제 | Q60: RV-MANUAL-ENT-059 | R60: Claude(Fable5) | S60: 상 | T60: 미검토
A61: 60 | B61: RV-MANUAL-ENT-060 | C61: Manual | D61: RemoteView Enterprise SaaS 사용자 가이드 | E61: 사용자/조직관리 > 사용자 조직 > 등록정보 | F61: RemoteView | G61: 등록정보 | H61: 관리자 | I61: 공개 | J61: 설정/사용 방법 문의 | K61: https://files.rsupport.com/ko/remoteview/guides/RemoteView_Enterprise_SaaS_User_Guide_kr.pdf | L61: chunk 40 / §사용자/조직관리 > 사용자 조직 / ● 등록정보 | N61: ① [등록정보] 아이콘을 클릭합니다. <접근방법> 툴바 > [등록정보] 버튼 클릭합니다. ② 사용자 등록정보 팝업이 노출됩니다. ③ 데이터를 변경합니다. ④ 사용자/매니저 계정에 ‘에이전트 설치 허용’옵션 적용하여 에이전트 등록 권한을 설정할 수 있습니다. ⑤ [적용] or [취소] 버튼을 클릭합니다. ✔ [적용] : 사용자 등록정보 변경 ✔ [취소] : 기존 데이터가 유지 | O61: RemoteView에서 등록정보은(는) 어떻게 하나요? | P61: RemoteView, ENT, 등록정보 | Q61: RV-MANUAL-ENT-060 | R61: Claude(Fable5) | S61: 상 | T61: 미검토
A62: 61 | B62: RV-MANUAL-ENT-061 | C62: Manual | D62: RemoteView Enterprise SaaS 사용자 가이드 | E62: 사용자/조직관리 > 사용자 조직 > 소팅 | F62: RemoteView | G62: 소팅 | H62: 관리자 | I62: 공개 | J62: 기능/가능 여부 확인 | K62: https://files.rsupport.com/ko/remoteview/guides/RemoteView_Enterprise_SaaS_User_Guide_kr.pdf | L62: chunk 40 / §사용자/조직관리 > 사용자 조직 / ● 소팅 | N62: 선택한 옵션값 대로 목록이 소팅 됩니다. | O62: RemoteView의 소팅은(는) 무엇인가요? | P62: RemoteView, ENT, 소팅 | Q62: RV-MANUAL-ENT-061 | R62: Claude(Fable5) | S62: 하 | T62: 근거약함 | U62: 본문 25자 미만 — 원문 근거 짧음
A63: 62 | B63: RV-MANUAL-ENT-062 | C63: Manual | D63: RemoteView Enterprise SaaS 사용자 가이드 | E63: 사용자/조직관리 > 사용자 조직 > 검색 | F63: RemoteView | G63: 검색 | H63: 관리자 | I63: 공개 | J63: 기능/가능 여부 확인 | K63: https://files.rsupport.com/ko/remoteview/guides/RemoteView_Enterprise_SaaS_User_Guide_kr.pdf | L63: chunk 40 / §사용자/조직관리 > 사용자 조직 / ● 검색 | N63: 입력한 검색어와 일치하는 데이터가 검색됩니다. | O63: RemoteView의 검색은(는) 무엇인가요? | P63: RemoteView, ENT, 검색 | Q63: RV-MANUAL-ENT-062 | R63: Claude(Fable5) | S63: 중 | T63: 미검토
A64: 63 | B64: RV-MANUAL-ENT-063 | C64: Manual | D64: RemoteView Enterprise SaaS 사용자 가이드 | E64: 사용자/조직관리 > 사용자 조직 > 권한 할당 | F64: RemoteView | G64: 권한 할당 | H64: 관리자 | I64: 공개 | J64: 기능/가능 여부 확인 | K64: https://files.rsupport.com/ko/remoteview/guides/RemoteView_Enterprise_SaaS_User_Guide_kr.pdf | L64: chunk 40 / §사용자/조직관리 > 사용자 조직 / ● 권한 할당 | N64: ⑥ Drag & Drop으로 그룹에 속한 하위 그룹 또는 사용자에 권한을 할당합니다. ⮚ 다중 사용자 권한 부여가 가능합니다. ⑦ 권한 관리와 사용자의 권한 할당은 [사용자 관리] 페이지에서 가능합니다. 사용통계 | O64: RemoteView의 권한 할당은(는) 무엇인가요? | P64: RemoteView, ENT, 권한 할당 | Q64: RV-MANUAL-ENT-063 | R64: Claude(Fable5) | S64: 상 | T64: 미검토
A65: 64 | B65: RV-MANUAL-ENT-064 | C65: Manual | D65: RemoteView Enterprise SaaS 사용자 가이드 | E65: 사용자/조직관리 > 사용자 조직 > 새로고침 | F65: RemoteView | G65: 새로고침 | H65: 관리자 | I65: 공개 | J65: 설정/사용 방법 문의 | K65: https://files.rsupport.com/ko/remoteview/guides/RemoteView_Enterprise_SaaS_User_Guide_kr.pdf | L65: chunk 41 / §사용자/조직관리 > 사용자 조직 / ● 새로고침 | N65: ① [새로고침] 아이콘을 클릭합니다. ② 웹 페이지 화면의 데이터가 갱신됩니다. | O65: RemoteView에서 새로고침은(는) 어떻게 하나요? | P65: RemoteView, ENT, 새로고침 | Q65: RV-MANUAL-ENT-064 | R65: Claude(Fable5) | S65: 중 | T65: 미검토
A66: 65 | B66: RV-MANUAL-ENT-065 | C66: Manual | D66: RemoteView Enterprise SaaS 사용자 가이드 | E66: 사용자/조직관리 > 사용자 조직 > 통계타입 | F66: RemoteView | G66: 통계타입 | H66: 관리자 | I66: 공개 | J66: 설정/사용 방법 문의 | K66: https://files.rsupport.com/ko/remoteview/guides/RemoteView_Enterprise_SaaS_User_Guide_kr.pdf | L66: chunk 41 / §사용자/조직관리 > 사용자 조직 / ● 통계타입 | N66: ① [통계타입] 아이콘을 클릭합니다. <접근방법> 툴바 > [차트] [기록]버튼 클릭합니다. ② 차트, 기록, 선택한 타입에 맞는 데이터가 출력됩니다. | O66: RemoteView에서 통계타입은(는) 어떻게 하나요? | P66: RemoteView, ENT, 통계타입 | Q66: RV-MANUAL-ENT-065 | R66: Claude(Fable5) | S66: 상 | T66: 미검토
A67: 66 | B67: RV-MANUAL-ENT-066 | C67: Manual | D67: RemoteView Enterprise SaaS 사용자 가이드 | E67: 사용자/조직관리 > 사용자 조직 > 기간설정 | F67: RemoteView | G67: 기간설정 | H67: 관리자 | I67: 공개 | J67: 설정/사용 방법 문의 | K67: https://files.rsupport.com/ko/remoteview/guides/RemoteView_Enterprise_SaaS_User_Guide_kr.pdf | L67: chunk 41 / §사용자/조직관리 > 사용자 조직 / ● 기간설정 | N67: ① Input-box 마우스 클릭합니다. ② 캘린더가 팝업 됩니다. ③ 시작일, 마지막일을 선택합니다. ④ [검색] 버튼을 클릭합니다. 환경설정 <각각의 권한 별 사용자에 맞게 설정을 할 수 있습니다.> 권한에 따라 로그인 시 사용할 수 있는 메뉴가 다릅니다. 관리자 매니저 일반사용자 대표 정보 관리 ✔ - - 대표 옵션 설정 ✔ - - 회원 탈퇴 ✔ - - 내 정보 관리 ✔ ✔ ✔ 내 옵션 설정 ✔ ✔ ✔ 내 인증된 기기 관리 ✔ ✔ ✔ 비밀번호 변경 ✔ ✔ ✔ 내 비밀번호 변경 이력 ✔ ✔ ✔ 원격지원 이력 관리 ✔ - - 최근 로그인 이력 ✔ - - 로그인 실패 이력 ✔ - - 인증된 기기 관리 ✔ - - 비밀번호 변경 이력 ✔ - - 에이전트 목록 ✔ - - 라이선스 내역 및 구매 ✔ - - 온라인 구매 내역 ✔ - - 쿠폰 관리 ✔ - - RemoteView 정보 ✔ ✔ ✔ 다운로드 ✔ ✔ ✔ 옵션 설정 값 옵션 값 설정 방법 전체 사용 대표 옵션에서 설정한 옵션은 모든 계정에 적용 에이전트 설정 대표 옵션에서 에이전트 설정으로 설정된 옵션 값은 원격지 PC관리 탭> 원격지 PC 선택> 우 클 | O67: RemoteView에서 기간설정은(는) 어떻게 하나요? | P67: RemoteView, ENT, 기간설정 | Q67: RV-MANUAL-ENT-066 | R67: Claude(Fable5) | S67: 중 | T67: 사람확인 | U67: 복합 내용 의심(절차+표 혼재 또는 과대 본문) — 재절단 검토 필요
A68: 67 | B68: RV-MANUAL-ENT-067 | C68: Manual | D68: RemoteView Enterprise SaaS 사용자 가이드 | E68: 원격지원 이력 관리 > 모바일 접속 사용 | F68: RemoteView | G68: 모바일 접속 사용 | H68: 관리자 | I68: 공개 | J68: 설정 방법 문의 | K68: https://files.rsupport.com/ko/remoteview/guides/RemoteView_Enterprise_SaaS_User_Guide_kr.pdf | L68: chunk 42 / §원격지원 이력 관리 / ● 원격제어 기능 설정 / ■ 모바일 접속 사용 | N68: 모바일 접속 여부를 설정합니다. | O68: RemoteView의 모바일 접속 사용은(는) 무엇인가요? | P68: RemoteView, ENT, 모바일 접속 사용 | Q68: RV-MANUAL-ENT-067 | R68: Claude(Fable5) | S68: 하 | T68: 근거약함 | U68: 본문 25자 미만 — 원문 근거 짧음
A69: 68 | B69: RV-MANUAL-ENT-068 | C69: Manual | D69: RemoteView Enterprise SaaS 사용자 가이드 | E69: 원격지원 이력 관리 > 라이브뷰 사용 | F69: RemoteView | G69: 라이브뷰 사용 | H69: 관리자 | I69: 공개 | J69: 설정 방법 문의 | K69: https://files.rsupport.com/ko/remoteview/guides/RemoteView_Enterprise_SaaS_User_Guide_kr.pdf | L69: chunk 42 / §원격지원 이력 관리 / ● 원격제어 기능 설정 / ■ 라이브뷰 사용 | N69: 라이브뷰 기능 사용 여부를 설정합니다. ※ 원격지 PC의 실사용자가 다른 경우, 사전 안내와 실사용자의 동의가 필요합니다. | O69: RemoteView의 라이브뷰 사용은(는) 무엇인가요? | P69: RemoteView, ENT, 라이브뷰 사용 | Q69: RV-MANUAL-ENT-068 | R69: Claude(Fable5) | S69: 상 | T69: 미검토
A70: 69 | B70: RV-MANUAL-ENT-069 | C70: Manual | D70: RemoteView Enterprise SaaS 사용자 가이드 | E70: 원격지원 이력 관리 > 이메일 초대 | F70: RemoteView | G70: 이메일 초대 | H70: 관리자 | I70: 공개 | J70: 설정 방법 문의 | K70: https://files.rsupport.com/ko/remoteview/guides/RemoteView_Enterprise_SaaS_User_Guide_kr.pdf | L70: chunk 42 / §원격지원 이력 관리 / ● 원격제어 기능 설정 / ■ 이메일 초대 | N70: 이메일 초대 기능 사용 여부를 설정합니다. | O70: RemoteView의 이메일 초대은(는) 무엇인가요? | P70: RemoteView, ENT, 이메일 초대 | Q70: RV-MANUAL-ENT-069 | R70: Claude(Fable5) | S70: 하 | T70: 근거약함 | U70: 본문 25자 미만 — 원문 근거 짧음
A71: 70 | B71: RV-MANUAL-ENT-070 | C71: Manual | D71: RemoteView Enterprise SaaS 사용자 가이드 | E71: 원격지원 이력 관리 > 클립보드 자동 동기화 | F71: RemoteView | G71: 클립보드 자동 동기화 | H71: 관리자 | I71: 공개 | J71: 기능/가능 여부 확인 | K71: https://files.rsupport.com/ko/remoteview/guides/RemoteView_Enterprise_SaaS_User_Guide_kr.pdf | L71: chunk 42 / §원격지원 이력 관리 / ● 원격제어 기능 설정 / ■ 클립보드 자동 동기화 | N71: 뷰어 메뉴의 클립보드 기능을 거치지 않고 자동으로 클립보드 내용을 동기화 하여 교환하는 기능 사용 여부를 설 정합니다. | O71: RemoteView의 클립보드 자동 동기화은(는) 무엇인가요? | P71: RemoteView, ENT, 클립보드 자동 동기화 | Q71: RV-MANUAL-ENT-070 | R71: Claude(Fable5) | S71: 상 | T71: 미검토
A72: 71 | B72: RV-MANUAL-ENT-071 | C72: Manual | D72: RemoteView Enterprise SaaS 사용자 가이드 | E72: 원격지원 이력 관리 > 모바일 퀵 메뉴 설정 | F72: RemoteView | G72: 모바일 퀵 메뉴 설정 | H72: 관리자 | I72: 공개 | J72: 기능/가능 여부 확인 | K72: https://files.rsupport.com/ko/remoteview/guides/RemoteView_Enterprise_SaaS_User_Guide_kr.pdf | L72: chunk 42 / §원격지원 이력 관리 / ● 원격제어 기능 설정 / ■ 모바일 퀵 메뉴 설정 | N72: RemoteView 앱> 퀵 메뉴> [편집]> [추가 프로그램] 카테고리에 등록이 되며 프로그램 추가는 10개까지 가능 합니다. | O72: RemoteView의 모바일 퀵 메뉴 설정은(는) 무엇인가요? | P72: RemoteView, ENT, 모바일 퀵 메뉴 설정 | Q72: RV-MANUAL-ENT-071 | R72: Claude(Fable5) | S72: 상 | T72: 미검토
A73: 72 | B73: RV-MANUAL-ENT-072 | C73: Manual | D73: RemoteView Enterprise SaaS 사용자 가이드 | E73: 원격지원 이력 관리 > 자동녹화 사용 설정 | F73: RemoteView | G73: 자동녹화 사용 설정 | H73: 관리자 | I73: 공개 | J73: 설정 방법 문의 | K73: https://files.rsupport.com/ko/remoteview/guides/RemoteView_Enterprise_SaaS_User_Guide_kr.pdf | L73: chunk 42 / §원격지원 이력 관리 / ● 원격제어 기능 설정 / ■ 자동녹화 사용 설정 | N73: 원격제어 시작 시 자동으로 녹화 여부를 설정합니다. | O73: RemoteView의 자동녹화 사용 설정은(는) 무엇인가요? | P73: RemoteView, ENT, 자동녹화 사용 설정 | Q73: RV-MANUAL-ENT-072 | R73: Claude(Fable5) | S73: 중 | T73: 미검토
A74: 73 | B74: RV-MANUAL-ENT-073 | C74: Manual | D74: RemoteView Enterprise SaaS 사용자 가이드 | E74: 원격지원 이력 관리 > 웹뷰어 사용 설정 | F74: RemoteView | G74: 웹뷰어 사용 설정 | H74: 관리자 | I74: 공개 | J74: 설정 방법 문의 | K74: https://files.rsupport.com/ko/remoteview/guides/RemoteView_Enterprise_SaaS_User_Guide_kr.pdf | L74: chunk 42 / §원격지원 이력 관리 / ● 원격제어 기능 설정 / ■ 웹뷰어 사용 설정 | N74: 별도의 뷰어 설치 없이, 웹브라우저로 원격제어 할 수 있는 웹뷰어 사용 여부를 설정합니다. | O74: RemoteView의 웹뷰어 사용 설정은(는) 무엇인가요? | P74: RemoteView, ENT, 웹뷰어 사용 설정 | Q74: RV-MANUAL-ENT-073 | R74: Claude(Fable5) | S74: 중 | T74: 미검토
A75: 74 | B75: RV-MANUAL-ENT-074 | C75: Manual | D75: RemoteView Enterprise SaaS 사용자 가이드 | E75: 원격지원 이력 관리 > 소리공유 기본값 설정 | F75: RemoteView | G75: 소리공유 기본값 설정 | H75: 관리자 | I75: 공개 | J75: 설정 방법 문의 | K75: https://files.rsupport.com/ko/remoteview/guides/RemoteView_Enterprise_SaaS_User_Guide_kr.pdf | L75: chunk 42 / §원격지원 이력 관리 / ● 원격제어 기능 설정 / ■ 소리공유 기본값 설정 | N75: 제어 시작 시 소리공유 활성화 여부를 설정합니다. (*원격제어에만 적용됩니다.) | O75: RemoteView의 소리공유 기본값 설정은(는) 무엇인가요? | P75: RemoteView, ENT, 소리공유 기본값 설정 | Q75: RV-MANUAL-ENT-074 | R75: Claude(Fable5) | S75: 중 | T75: 미검토
A76: 75 | B76: RV-MANUAL-ENT-075 | C76: Manual | D76: RemoteView Enterprise SaaS 사용자 가이드 | E76: 원격지원 이력 관리 > 사용자 권한 기본값 설정 | F76: RemoteView | G76: 사용자 권한 기본값 설정 | H76: 관리자 | I76: 공개 | J76: 설정 방법 문의 | K76: https://files.rsupport.com/ko/remoteview/guides/RemoteView_Enterprise_SaaS_User_Guide_kr.pdf | L76: chunk 42 / §원격지원 이력 관리 / ● 원격제어 기능 설정 / ■ 사용자 권한 기본값 설정 | N76: 사용자를 에이전트에 권한 할당할 때, 어떤 권한을 부여할지 선택하여 기본값을 설정합니다. | O76: RemoteView의 사용자 권한 기본값 설정은(는) 무엇인가요? | P76: RemoteView, ENT, 사용자 권한 기본값 설정 | Q76: RV-MANUAL-ENT-075 | R76: Claude(Fable5) | S76: 중 | T76: 미검토
A77: 76 | B77: RV-MANUAL-ENT-076 | C77: Manual | D77: RemoteView Enterprise SaaS 사용자 가이드 | E77: 원격지원 이력 관리 > 다중접속 | F77: RemoteView | G77: 다중접속 | H77: 관리자 | I77: 공개 | J77: 기능/가능 여부 확인 | K77: https://files.rsupport.com/ko/remoteview/guides/RemoteView_Enterprise_SaaS_User_Guide_kr.pdf | L77: chunk 42 / §원격지원 이력 관리 / ● 원격제어 기능 설정 / ■ 다중접속 | N77: 1대의 원격지 PC에 여러 사용자가 동시에 접속하여 화면을 공유하고 제어할 수 있습니다. | O77: RemoteView의 다중접속은(는) 무엇인가요? | P77: RemoteView, ENT, 다중접속 | Q77: RV-MANUAL-ENT-076 | R77: Claude(Fable5) | S77: 중 | T77: 미검토
A78: 77 | B78: RV-MANUAL-ENT-077 | C78: Manual | D78: RemoteView Enterprise SaaS 사용자 가이드 | E78: 원격지원 이력 관리 > 제어 중 파일 전송 설정 | F78: RemoteView | G78: 제어 중 파일 전송 설정 | H78: 관리자 | I78: 공개 | J78: 설정 방법 문의 | K78: https://files.rsupport.com/ko/remoteview/guides/RemoteView_Enterprise_SaaS_User_Guide_kr.pdf | L78: chunk 42 / §원격지원 이력 관리 / ● 파일 전송 설정 / ■ 제어 중 파일 전송 설정 | N78: 원격제어 시 단말기 간에 파일 송수신(보내기, 가져오기) 여부를 설정합니다. | O78: RemoteView의 제어 중 파일 전송 설정은(는) 무엇인가요? | P78: RemoteView, ENT, 제어 중 파일 전송 설정 | Q78: RV-MANUAL-ENT-077 | R78: Claude(Fable5) | S78: 중 | T78: 미검토
A79: 78 | B79: RV-MANUAL-ENT-078 | C79: Manual | D79: RemoteView Enterprise SaaS 사용자 가이드 | E79: 원격지원 이력 관리 > 원격탐색기 사용 | F79: RemoteView | G79: 원격탐색기 사용 | H79: 관리자 | I79: 공개 | J79: 설정 방법 문의 | K79: https://files.rsupport.com/ko/remoteview/guides/RemoteView_Enterprise_SaaS_User_Guide_kr.pdf | L79: chunk 42 / §원격지원 이력 관리 / ● 파일 전송 설정 / ■ 원격탐색기 사용 | N79: 원격탐색기 사용 여부를 설정합니다. | O79: RemoteView의 원격탐색기 사용은(는) 무엇인가요? | P79: RemoteView, ENT, 원격탐색기 사용 | Q79: RV-MANUAL-ENT-078 | R79: Claude(Fable5) | S79: 하 | T79: 근거약함 | U79: 본문 25자 미만 — 원문 근거 짧음
A80: 79 | B80: RV-MANUAL-ENT-079 | C80: Manual | D80: RemoteView Enterprise SaaS 사용자 가이드 | E80: 원격지원 이력 관리 > 원격제어 뷰어 설정 | F80: RemoteView | G80: 원격제어 뷰어 설정 | H80: 관리자 | I80: 공개 | J80: 설정 방법 문의 | K80: https://files.rsupport.com/ko/remoteview/guides/RemoteView_Enterprise_SaaS_User_Guide_kr.pdf | L80: chunk 42 / §원격지원 이력 관리 / ● 원격제어 품질 설정 / ■ 원격제어 뷰어 설정 | N80: 에이전트를 클릭하여 접속 시 일반 뷰어/동영상 뷰어를 사용자 환경에 맞게 설정합니다. | O80: RemoteView의 원격제어 뷰어 설정은(는) 무엇인가요? | P80: RemoteView, ENT, 원격제어 뷰어 설정 | Q80: RV-MANUAL-ENT-079 | R80: Claude(Fable5) | S80: 중 | T80: 미검토
A81: 80 | B81: RV-MANUAL-ENT-080 | C81: Manual | D81: RemoteView Enterprise SaaS 사용자 가이드 | E81: 원격지원 이력 관리 > 제어 모드 | F81: RemoteView | G81: 제어 모드 | H81: 관리자 | I81: 공개 | J81: 설정 방법 문의 | K81: https://files.rsupport.com/ko/remoteview/guides/RemoteView_Enterprise_SaaS_User_Guide_kr.pdf | L81: chunk 42 / §원격지원 이력 관리 / ● 원격제어 품질 설정 / ■ 제어 모드 | N81: 원격제어 초기 접속 시 제어 모드(고속제어모드 or 그래픽제어모드)를 설정합니다. | O81: RemoteView의 제어 모드은(는) 무엇인가요? | P81: RemoteView, ENT, 제어 모드 | Q81: RV-MANUAL-ENT-080 | R81: Claude(Fable5) | S81: 중 | T81: 미검토
A82: 81 | B82: RV-MANUAL-ENT-081 | C82: Manual | D82: RemoteView Enterprise SaaS 사용자 가이드 | E82: 원격지원 이력 관리 > 화면 색상 | F82: RemoteView | G82: 화면 색상 | H82: 관리자 | I82: 공개 | J82: 설정 방법 문의 | K82: https://files.rsupport.com/ko/remoteview/guides/RemoteView_Enterprise_SaaS_User_Guide_kr.pdf | L82: chunk 42 / §원격지원 이력 관리 / ● 원격제어 품질 설정 / ■ 화면 색상 | N82: 뷰어의 화면 색상을 설정합니다. (색상수가 낮을수록 제어 속도가 빨라집니다.) | O82: RemoteView의 화면 색상은(는) 무엇인가요? | P82: RemoteView, ENT, 화면 색상 | Q82: RV-MANUAL-ENT-081 | R82: Claude(Fable5) | S82: 중 | T82: 미검토
A83: 82 | B83: RV-MANUAL-ENT-082 | C83: Manual | D83: RemoteView Enterprise SaaS 사용자 가이드 | E83: 원격지원 이력 관리 > 원격제어 시작 시 원격 화면 자동 잠금 | F83: RemoteView | G83: 원격제어 시작 시 원격 화면 자동 잠금 | H83: 관리자 | I83: 공개 | J83: 설정 방법 문의 | K83: https://files.rsupport.com/ko/remoteview/guides/RemoteView_Enterprise_SaaS_User_Guide_kr.pdf | L83: chunk 42 / §원격지원 이력 관리 / ● 화면 보안 설정 / ■ 원격제어 시작 시 원격 화면 자동 잠금 | N83: 원격제어 중 원격지 PC의 화면에 대한 잠금을 설정합니다. | O83: RemoteView의 원격제어 시작 시 원격 화면 자동 잠금은(는) 무엇인가요? | P83: RemoteView, ENT, 원격제어 시작 시 원격 화면 자동 잠 | Q83: RV-MANUAL-ENT-082 | R83: Claude(Fable5) | S83: 중 | T83: 미검토
A84: 83 | B84: RV-MANUAL-ENT-083 | C84: Manual | D84: RemoteView Enterprise SaaS 사용자 가이드 | E84: 원격지원 이력 관리 > 잠금 방식 선택 | F84: RemoteView | G84: 잠금 방식 선택 | H84: 관리자 | I84: 공개 | J84: 설정 방법 문의 | K84: https://files.rsupport.com/ko/remoteview/guides/RemoteView_Enterprise_SaaS_User_Guide_kr.pdf | L84: chunk 42 / §원격지원 이력 관리 / ● 화면 보안 설정 / ■ 잠금 방식 선택 | N84: 원격제어 시 원격지 PC의 화면 잠금 종류를 설정합니다. | O84: RemoteView의 잠금 방식 선택은(는) 무엇인가요? | P84: RemoteView, ENT, 잠금 방식 선택 | Q84: RV-MANUAL-ENT-083 | R84: Claude(Fable5) | S84: 중 | T84: 미검토
A85: 84 | B85: RV-MANUAL-ENT-084 | C85: Manual | D85: RemoteView Enterprise SaaS 사용자 가이드 | E85: 원격지원 이력 관리 > 원격제어 종료 시 원격 화면 설정 | F85: RemoteView | G85: 원격제어 종료 시 원격 화면 설정 | H85: 관리자 | I85: 공개 | J85: 설정 방법 문의 | K85: https://files.rsupport.com/ko/remoteview/guides/RemoteView_Enterprise_SaaS_User_Guide_kr.pdf | L85: chunk 42 / §원격지원 이력 관리 / ● 화면 보안 설정 / ■ 원격제어 종료 시 원격 화면 설정 | N85: 원격제어 종료 후 시스템 잠금, 로그오프 여부를 설정합니다. | O85: RemoteView의 원격제어 종료 시 원격 화면 설정은(는) 무엇인가요? | P85: RemoteView, ENT, 원격제어 종료 시 원격 화면 설정 | Q85: RV-MANUAL-ENT-084 | R85: Claude(Fable5) | S85: 중 | T85: 미검토
A86: 85 | B86: RV-MANUAL-ENT-085 | C86: Manual | D86: RemoteView Enterprise SaaS 사용자 가이드 | E86: 원격지원 이력 관리 > 원격제어 뷰어 미 사용 시 처리 | F86: RemoteView | G86: 원격제어 뷰어 미 사용 시 처리 | H86: 관리자 | I86: 공개 | J86: 설정 방법 문의 | K86: https://files.rsupport.com/ko/remoteview/guides/RemoteView_Enterprise_SaaS_User_Guide_kr.pdf | L86: chunk 42 / §원격지원 이력 관리 / ● 화면 보안 설정 / ■ 원격제어 뷰어 미 사용 시 처리 | N86: 정해진 시간 동안 뷰어를 사용하지 않을 경우 뷰어의 상태 여부를 설정합니다. | O86: RemoteView의 원격제어 뷰어 미 사용 시 처리은(는) 무엇인가요? | P86: RemoteView, ENT, 원격제어 뷰어 미 사용 시 처리 | Q86: RV-MANUAL-ENT-085 | R86: Claude(Fable5) | S86: 중 | T86: 미검토
A87: 86 | B87: RV-MANUAL-ENT-086 | C87: Manual | D87: RemoteView Enterprise SaaS 사용자 가이드 | E87: 원격지원 이력 관리 > 워터마크 기능 설정 | F87: RemoteView | G87: 워터마크 기능 설정 | H87: 관리자 | I87: 공개 | J87: 설정 방법 문의 | K87: https://files.rsupport.com/ko/remoteview/guides/RemoteView_Enterprise_SaaS_User_Guide_kr.pdf | L87: chunk 42 / §원격지원 이력 관리 / ● 워터마크 기능 설정 | N87: ■ 워터마크 사용 원격제어 중인 화면에 워터마크 기능을 설정할 수 있습니다. ⮚ 워터마크 상세 옵션으로는 워터마크 노출 항목 /색 /투명도 /크기 /레이아웃을 적용할 수 있습니다. | O87: RemoteView의 워터마크 기능 설정은(는) 무엇인가요? | P87: RemoteView, ENT, 워터마크 기능 설정 | Q87: RV-MANUAL-ENT-086 | R87: Claude(Fable5) | S87: 상 | T87: 미검토
A88: 87 | B88: RV-MANUAL-ENT-087 | C88: Manual | D88: RemoteView Enterprise SaaS 사용자 가이드 | E88: 원격지원 이력 관리 > 허용 IP 설정 | F88: RemoteView | G88: 허용 IP 설정 | H88: 관리자 | I88: 공개 | J88: 설정 방법 문의 | K88: https://files.rsupport.com/ko/remoteview/guides/RemoteView_Enterprise_SaaS_User_Guide_kr.pdf | L88: chunk 43 / §원격지원 이력 관리 / ● 허용 IP, MAC 설정 / ■ 허용 IP 설정 | N88: 특정 IP 대역에 대한 접근 여부를 설정합니다. ➢ 매니저/사용자 계정에서 에이전트 접근 시 허용된 IP만 가능합니다. ➢ 관리자 계정은 허용 IP 설정과 무관하게 에이전트 접근 가능합니다. ➢ 공인 IP 와 사설 IP 모두 적용됩니다. | O88: RemoteView의 허용 IP 설정은(는) 무엇인가요? | P88: RemoteView, ENT, 허용 IP 설정 | Q88: RV-MANUAL-ENT-087 | R88: Claude(Fable5) | S88: 상 | T88: 미검토
A89: 88 | B89: RV-MANUAL-ENT-088 | C89: Manual | D89: RemoteView Enterprise SaaS 사용자 가이드 | E89: 원격지원 이력 관리 > 허용 MAC 설정 | F89: RemoteView | G89: 허용 MAC 설정 | H89: 관리자 | I89: 공개 | J89: 설정 방법 문의 | K89: https://files.rsupport.com/ko/remoteview/guides/RemoteView_Enterprise_SaaS_User_Guide_kr.pdf | L89: chunk 43 / §원격지원 이력 관리 / ● 허용 IP, MAC 설정 / ■ 허용 MAC 설정 | N89: 특정 MAC주소에 대한 접근 여부를 설정합니다. ⮚ 회사 일괄 적용, 사용자 ID별 적용, 사용 안함 등 설정합니다. ⮚ 전체 사용일 경우, MAC 주소 추가 입력란에 MAC 주소를 Ctrl + c/v 하여 복사/붙여넣기 할 수 있습니다. ⮚ 사용자 설정일 경우, 사용자 관리/조직관리 Tab의 사용자 등록정보에서 허용 MAC 주소 설정 가능합니다. ⮚ 원격제어 연결 시 매니저/사용자 계정에서 에이전트 접근 시 허용 MAC 설정 옵션에 따라 접근 여부가 정해집 니다. 참고: 관리자 계정은 MAC 설정과 상관없이 에이전트 접근이 가능합니다. ⮚ 매니저/사용자 계정에서는 웹뷰어 연결 시 접근 계정 정보 입력 화면에서 10분 경과 시 보안으로 인해 접근이 차단되므로, 웹뷰어 제어를 재시도해야 합니다. 참고: Simple Launcher 버전이 자동 업데이트 되는 경우에는 최초1회 Simple Launcher 재실행 안내 팝업 이 노출됩니다. (세션만료 알림 팝업 이미지) | O89: RemoteView의 허용 MAC 설정은(는) 무엇인가요? | P89: RemoteView, ENT, 허용 MAC 설정 | Q89: RV-MANUAL-ENT-088 | R89: Claude(Fable5) | S89: 상 | T89: 미검토
A90: 89 | B90: RV-MANUAL-ENT-089 | C90: Manual | D90: RemoteView Enterprise SaaS 사용자 가이드 | E90: 원격지원 이력 관리 > 웹 사이트 인증 세션 만료 시간 | F90: RemoteView | G90: 웹 사이트 인증 세션 만료 시간 | H90: 관리자 | I90: 공개 | J90: 설정 방법 문의 | K90: https://files.rsupport.com/ko/remoteview/guides/RemoteView_Enterprise_SaaS_User_Guide_kr.pdf | L90: chunk 43 / §원격지원 이력 관리 / ● 보안 설정 / ■ 웹 사이트 인증 세션 만료 시간 | N90: 웹콘솔에 로그인 후 만료되기까지의 시간을 설정합니다. (기본값: 30분) | O90: RemoteView의 웹 사이트 인증 세션 만료 시간은(는) 무엇인가요? | P90: RemoteView, ENT, 웹 사이트 인증 세션 만료 시간 | Q90: RV-MANUAL-ENT-089 | R90: Claude(Fable5) | S90: 중 | T90: 미검토
A91: 90 | B91: RV-MANUAL-ENT-090 | C91: Manual | D91: RemoteView Enterprise SaaS 사용자 가이드 | E91: 원격지원 이력 관리 > 원격제어 만료 시간 설정 | F91: RemoteView | G91: 원격제어 만료 시간 설정 | H91: 관리자 | I91: 공개 | J91: 설정 방법 문의 | K91: https://files.rsupport.com/ko/remoteview/guides/RemoteView_Enterprise_SaaS_User_Guide_kr.pdf | L91: chunk 43 / §원격지원 이력 관리 / ● 보안 설정 / ■ 원격제어 만료 시간 설정 | N91: 원격제어시작 후 자동제어종료 시간을 설정합니다. (기본값: 60분) | O91: RemoteView의 원격제어 만료 시간 설정은(는) 무엇인가요? | P91: RemoteView, ENT, 원격제어 만료 시간 설정 | Q91: RV-MANUAL-ENT-090 | R91: Claude(Fable5) | S91: 중 | T91: 미검토
... A110: 109 | B110: RV-MANUAL-ENT-109 | C110: Manual | D110: RemoteView Enterprise SaaS 사용자 가이드 | E110: 회원탈퇴 > 탈퇴하기 버튼을 클릭하면 회원탈퇴 처리가 완료됩니다. | F110: RemoteView | G110: 탈퇴하기 버튼을 클릭하면 회원탈퇴 처리가 완료됩니다. | H110: 관리자 | I110: 공개 | J110: 기능/가능 여부 확인 | K110: https://files.rsupport.com/ko/remoteview/guides/RemoteView_Enterprise_SaaS_User_Guide_kr.pdf | L110: chunk 48 / §회원탈퇴 / ● 탈퇴하기 버튼을 클릭하면 회원탈퇴 처리가 완료됩니다. | N110: ⮚ 무료 데모 서비스나 유료 서비스를 사용 중일 경우에는 탈퇴가 되지 않으니 서비스 종료 후 회원 탈퇴가 가능합 니다. ⮚ 부정 가입을 방지하기 위해 탈퇴한 아이디와 이메일 정보로는 6개월 동안 재가입이 되지 않으며, 6개월이 경과 된 이후에는 탈퇴했던 동일한 아이디, 이메일 정보로 재가입을 할 수 있습니다. ⮚ 유료 결제한 내역이 남아 있을 경우 ‘문의하기’를 통해 환불 요청을 해야 환불을 받을 수 있습니다. | O110: RemoteView의 탈퇴하기 버튼을 클릭하면 회원탈퇴 처리가 완료됩니다.은(는) 무엇인가요? | P110: RemoteView, ENT, 탈퇴하기 버튼을 클릭하면 회원탈퇴 처 | Q110: RV-MANUAL-ENT-109 | R110: Claude(Fable5) | S110: 상 | T110: 미검토
A111: 110 | B111: RV-MANUAL-ENT-110 | C111: Manual | D111: RemoteView Enterprise SaaS 사용자 가이드 | E111: 내 옵션 설정 > 즐겨찾기 | F111: RemoteView | G111: 즐겨찾기 | H111: 관리자 | I111: 공개 | J111: 설정 방법 문의 | K111: https://files.rsupport.com/ko/remoteview/guides/RemoteView_Enterprise_SaaS_User_Guide_kr.pdf | L111: chunk 50 / §내 옵션 설정 / ● 일반 설정 / ■ 즐겨찾기 | N111: 즐겨찾기 영역 사용여부를 설정합니다. | O111: RemoteView의 즐겨찾기은(는) 무엇인가요? | P111: RemoteView, ENT, 즐겨찾기 | Q111: RV-MANUAL-ENT-110 | R111: Claude(Fable5) | S111: 하 | T111: 근거약함 | U111: 본문 25자 미만 — 원문 근거 짧음
A112: 111 | B112: RV-MANUAL-ENT-111 | C112: Manual | D112: RemoteView Enterprise SaaS 사용자 가이드 | E112: 내 옵션 설정 > 복수 선택 기능 | F112: RemoteView | G112: 복수 선택 기능 | H112: 관리자 | I112: 공개 | J112: 설정 방법 문의 | K112: https://files.rsupport.com/ko/remoteview/guides/RemoteView_Enterprise_SaaS_User_Guide_kr.pdf | L112: chunk 50 / §내 옵션 설정 / ● 일반 설정 / ■ 복수 선택 기능 | N112: 마우스와 키보드를 이용한 복수 선택 기능 사용여부를 설정합니다. | O112: RemoteView의 복수 선택 기능은(는) 무엇인가요? | P112: RemoteView, ENT, 복수 선택 기능 | Q112: RV-MANUAL-ENT-111 | R112: Claude(Fable5) | S112: 중 | T112: 미검토
A113: 112 | B113: RV-MANUAL-ENT-112 | C113: Manual | D113: RemoteView Enterprise SaaS 사용자 가이드 | E113: 내 옵션 설정 > 마우스 오른쪽 버튼 기능(Context Menu) | F113: RemoteView | G113: 마우스 오른쪽 버튼 기능(Context Menu) | H113: 관리자 | I113: 공개 | J113: 설정 방법 문의 | K113: https://files.rsupport.com/ko/remoteview/guides/RemoteView_Enterprise_SaaS_User_Guide_kr.pdf | L113: chunk 50 / §내 옵션 설정 / ● 일반 설정 / ■ 마우스 오른쪽 버튼 기능(Context Menu) | N113: 마우스 오른쪽 버튼 클릭을 이용한 서비스 메뉴 사용여부를 설정합니다. | O113: RemoteView의 마우스 오른쪽 버튼 기능(Context Menu)은(는) 무엇인가요? | P113: RemoteView, ENT, 마우스 오른쪽 버튼 기능(Contex | Q113: RV-MANUAL-ENT-112 | R113: Claude(Fable5) | S113: 중 | T113: 미검토
A114: 113 | B114: RV-MANUAL-ENT-113 | C114: Manual | D114: RemoteView Enterprise SaaS 사용자 가이드 | E114: 내 옵션 설정 > 설정 보존 기능 | F114: RemoteView | G114: 설정 보존 기능 | H114: 관리자 | I114: 공개 | J114: 설정 방법 문의 | K114: https://files.rsupport.com/ko/remoteview/guides/RemoteView_Enterprise_SaaS_User_Guide_kr.pdf | L114: chunk 50 / §내 옵션 설정 / ● 일반 설정 / ■ 설정 보존 기능 | N114: 마지막 작업 상태를 유지할지에 대해 설정합니다. | O114: RemoteView의 설정 보존 기능은(는) 무엇인가요? | P114: RemoteView, ENT, 설정 보존 기능 | Q114: RV-MANUAL-ENT-113 | R114: Claude(Fable5) | S114: 중 | T114: 미검토
A115: 114 | B115: RV-MANUAL-ENT-114 | C115: Manual | D115: RemoteView Enterprise SaaS 사용자 가이드 | E115: 내 옵션 설정 > 원격제어 뷰어 설정 | F115: RemoteView | G115: 원격제어 뷰어 설정 | H115: 관리자 | I115: 공개 | J115: 설정 방법 문의 | K115: https://files.rsupport.com/ko/remoteview/guides/RemoteView_Enterprise_SaaS_User_Guide_kr.pdf | L115: chunk 50 / §내 옵션 설정 / ● 원격제어 품질 설정 / ■ 원격제어 뷰어 설정 | N115: 에이전트를 클릭하여 접속 시 일반 뷰어/동영상 뷰어를 사용자 환경에 맞게 설정합니다. | O115: RemoteView의 원격제어 뷰어 설정은(는) 무엇인가요? | P115: RemoteView, ENT, 원격제어 뷰어 설정 | Q115: RV-MANUAL-ENT-114 | R115: Claude(Fable5) | S115: 중 | T115: 미검토
A116: 115 | B116: RV-MANUAL-ENT-115 | C116: Manual | D116: RemoteView Enterprise SaaS 사용자 가이드 | E116: 내 옵션 설정 > 제어모드 | F116: RemoteView | G116: 제어모드 | H116: 관리자 | I116: 공개 | J116: 설정 방법 문의 | K116: https://files.rsupport.com/ko/remoteview/guides/RemoteView_Enterprise_SaaS_User_Guide_kr.pdf | L116: chunk 50 / §내 옵션 설정 / ● 원격제어 품질 설정 / ■ 제어모드 | N116: 원격제어 초기 접속 시 제어모드(고속제어모드 or 그래픽제어모드)를 설정합니다. | O116: RemoteView의 제어모드은(는) 무엇인가요? | P116: RemoteView, ENT, 제어모드 | Q116: RV-MANUAL-ENT-115 | R116: Claude(Fable5) | S116: 중 | T116: 미검토
A117: 116 | B117: RV-MANUAL-ENT-116 | C117: Manual | D117: RemoteView Enterprise SaaS 사용자 가이드 | E117: 내 옵션 설정 > 화면색상 | F117: RemoteView | G117: 화면색상 | H117: 관리자 | I117: 공개 | J117: 설정 방법 문의 | K117: https://files.rsupport.com/ko/remoteview/guides/RemoteView_Enterprise_SaaS_User_Guide_kr.pdf | L117: chunk 50 / §내 옵션 설정 / ● 원격제어 품질 설정 / ■ 화면색상 | N117: 뷰어의 화면색상을 설정합니다. (색상수가 낮을수록 제어속도가 빨라집니다.) | O117: RemoteView의 화면색상은(는) 무엇인가요? | P117: RemoteView, ENT, 화면색상 | Q117: RV-MANUAL-ENT-116 | R117: Claude(Fable5) | S117: 중 | T117: 미검토
A118: 117 | B118: RV-MANUAL-ENT-117 | C118: Manual | D118: RemoteView Enterprise SaaS 사용자 가이드 | E118: 내 옵션 설정 > 원격제어 기능 설정 | F118: RemoteView | G118: 원격제어 기능 설정 | H118: 관리자 | I118: 공개 | J118: 설정 방법 문의 | K118: https://files.rsupport.com/ko/remoteview/guides/RemoteView_Enterprise_SaaS_User_Guide_kr.pdf | L118: chunk 50 / §내 옵션 설정 / ● 원격제어 기능 설정 | N118: ■ 클립보드 자동 동기화 뷰어 메뉴의 클립보드 기능을 자동으로 동기화를 설정합니다. | O118: RemoteView의 원격제어 기능 설정은(는) 무엇인가요? | P118: RemoteView, ENT, 원격제어 기능 설정 | Q118: RV-MANUAL-ENT-117 | R118: Claude(Fable5) | S118: 중 | T118: 미검토
A119: 118 | B119: RV-MANUAL-ENT-118 | C119: Manual | D119: RemoteView Enterprise SaaS 사용자 가이드 | E119: 내 옵션 설정 > 원격제어 시작 시 원격 화면 자동 잠금 | F119: RemoteView | G119: 원격제어 시작 시 원격 화면 자동 잠금 | H119: 관리자 | I119: 공개 | J119: 설정 방법 문의 | K119: https://files.rsupport.com/ko/remoteview/guides/RemoteView_Enterprise_SaaS_User_Guide_kr.pdf | L119: chunk 50 / §내 옵션 설정 / ● 화면 보안 설정 / ■ 원격제어 시작 시 원격 화면 자동 잠금 | N119: 원격제어 중 원격지 PC의 화면에 대한 잠금을 설정합니다. | O119: RemoteView의 원격제어 시작 시 원격 화면 자동 잠금은(는) 무엇인가요? | P119: RemoteView, ENT, 원격제어 시작 시 원격 화면 자동 잠 | Q119: RV-MANUAL-ENT-118 | R119: Claude(Fable5) | S119: 중 | T119: 미검토
A120: 119 | B120: RV-MANUAL-ENT-119 | C120: Manual | D120: RemoteView Enterprise SaaS 사용자 가이드 | E120: 내 옵션 설정 > 원격제어 종료 시 시스템 잠금 | F120: RemoteView | G120: 원격제어 종료 시 시스템 잠금 | H120: 관리자 | I120: 공개 | J120: 설정 방법 문의 | K120: https://files.rsupport.com/ko/remoteview/guides/RemoteView_Enterprise_SaaS_User_Guide_kr.pdf | L120: chunk 50 / §내 옵션 설정 / ● 화면 보안 설정 / ■ 원격제어 종료 시 시스템 잠금 | N120: 원격제어 종료 후 시스템 잠금 여부를 설정합니다. | O120: RemoteView의 원격제어 종료 시 시스템 잠금은(는) 무엇인가요? | P120: RemoteView, ENT, 원격제어 종료 시 시스템 잠금 | Q120: RV-MANUAL-ENT-119 | R120: Claude(Fable5) | S120: 중 | T120: 미검토
A121: 120 | B121: RV-MANUAL-ENT-120 | C121: Manual | D121: RemoteView Enterprise SaaS 사용자 가이드 | E121: 내 옵션 설정 > 원격제어 뷰어 미 사용 시 처리 | F121: RemoteView | G121: 원격제어 뷰어 미 사용 시 처리 | H121: 관리자 | I121: 공개 | J121: 설정 방법 문의 | K121: https://files.rsupport.com/ko/remoteview/guides/RemoteView_Enterprise_SaaS_User_Guide_kr.pdf | L121: chunk 50 / §내 옵션 설정 / ● 화면 보안 설정 / ■ 원격제어 뷰어 미 사용 시 처리 | N121: 정해진 시간 동안 뷰어를 사용하지 않을 경우 뷰어의 상태 여부를 설정합니다.  에이전트 접속 인증 사용이 OTP 또는 Email인 경우, 원격제어 중 뷰어 미 사용 시 처리를 뷰어 잠금으로 설정해 도 실제로 잠금 처리가 적용되지 않습니다. | O121: RemoteView의 원격제어 뷰어 미 사용 시 처리은(는) 무엇인가요? | P121: RemoteView, ENT, 원격제어 뷰어 미 사용 시 처리 | Q121: RV-MANUAL-ENT-120 | R121: Claude(Fable5) | S121: 상 | T121: 미검토
A122: 121 | B122: RV-MANUAL-ENT-121 | C122: Manual | D122: RemoteView Enterprise SaaS 사용자 가이드 | E122: RemoteView 정보 > 제품정보 | F122: RemoteView | G122: 제품정보 | H122: 관리자 | I122: 공개 | J122: 기능/가능 여부 확인 | K122: https://files.rsupport.com/ko/remoteview/guides/RemoteView_Enterprise_SaaS_User_Guide_kr.pdf | L122: chunk 51 / §RemoteView 정보 / ● 제품정보 | N122: 제품(서비스)명과 최신 버전정보, Copyright 정보를 볼 수 있습니다. | O122: RemoteView의 제품정보은(는) 무엇인가요? | P122: RemoteView, ENT, 제품정보 | Q122: RV-MANUAL-ENT-121 | R122: Claude(Fable5) | S122: 중 | T122: 미검토
A123: 122 | B123: RV-MANUAL-ENT-122 | C123: Manual | D123: RemoteView Enterprise SaaS 사용자 가이드 | E123: RemoteView 정보 > 문의 | F123: RemoteView | G123: 문의 | H123: 관리자 | I123: 공개 | J123: 기능/가능 여부 확인 | K123: https://files.rsupport.com/ko/remoteview/guides/RemoteView_Enterprise_SaaS_User_Guide_kr.pdf | L123: chunk 51 / §RemoteView 정보 / ● 문의 | N123: 제품문의와 홈페이지의 링크가 제공됩니다. | O123: RemoteView의 문의은(는) 무엇인가요? | P123: RemoteView, ENT, 문의 | Q123: RV-MANUAL-ENT-122 | R123: Claude(Fable5) | S123: 하 | T123: 근거약함 | U123: 본문 25자 미만 — 원문 근거 짧음
A124: 123 | B124: RV-MANUAL-ENT-123 | C124: Manual | D124: RemoteView Enterprise SaaS 사용자 가이드 | E124: 다운로드 > 매뉴얼 | F124: RemoteView | G124: 매뉴얼 | H124: 관리자 | I124: 공개 | J124: 기능/가능 여부 확인 | K124: https://files.rsupport.com/ko/remoteview/guides/RemoteView_Enterprise_SaaS_User_Guide_kr.pdf | L124: chunk 52 / §다운로드 / ● 매뉴얼 | N124: [다운로드] 링크 클릭 시 파일 다운로드 창이 팝업 되어 ‘열기’, ‘저장’, ‘취소’ 버튼을 통해 매뉴얼을 확인할 수 있습니 다. 분 류 설 명 SaaS Standard 매뉴얼 데스크탑 환경에서의 Standard 라이선스 제품 사용 매뉴얼 Enterprise 매뉴얼 데스크탑 환경에서의 Enterprise 라이선스 제품 사용 매뉴얼 모바일 iOS/iPad 아이폰/아이패드용 리모트뷰 제품 사용 매뉴얼 Android 안드로이드용 리모트뷰 제품 사용 매뉴얼 콘솔 macOS 사용자 매뉴얼 Mac용 리모트뷰 제품 사용 매뉴얼 macOS 설치 매뉴얼 Mac용 리모트뷰 제품 설치 매뉴얼 Linux 콘솔 리눅스 환경에서의 제품 사용 매뉴얼 BOX BOX 매뉴얼 BOX 제품 사용 매뉴얼 BOX2 매뉴얼 BOX2 제품 사용 매뉴얼 뷰어 뷰어 매뉴얼 원격제어 뷰어 사용 매뉴얼 | O124: RemoteView의 매뉴얼은(는) 무엇인가요? | P124: RemoteView, ENT, 매뉴얼 | Q124: RV-MANUAL-ENT-123 | R124: Claude(Fable5) | S124: 상 | T124: 미검토
A125: 124 | B125: RV-MANUAL-ENT-124 | C125: Manual | D125: RemoteView Enterprise SaaS 사용자 가이드 | E125: 다운로드 | F125: RemoteView | G125: 다운로드 | H125: 관리자 | I125: 공개 | J125: 기능/가능 여부 확인 | K125: https://files.rsupport.com/ko/remoteview/guides/RemoteView_Enterprise_SaaS_User_Guide_kr.pdf | L125: chunk 52 / ● 다운로드 | N125: ■ 수동설치 파일 Java, Linux, RsDoctor 설치 파일을 다운로드하여 수동으로 PC에 설치할 수 있습니다. ⮚ Java: Mac 환경의 원격제어 시 필요한 설치 파일 ⮚ Linux: Linux 환경의 에이전트 설치 파일 (지원 OS: CentOS, Red Hat, Ubuntu) ⮚ RsDoctor: 사용자 환경 정보 및 서비스 로그를 수집하여 장애를 진단하는 프로그램입니다. 6. 리모트뷰 에이전트 설치 사용자 페이지에서 설치 | O125: RemoteView의 다운로드은(는) 무엇인가요? | P125: RemoteView, ENT, 다운로드 | Q125: RV-MANUAL-ENT-124 | R125: Claude(Fable5) | S125: 상 | T125: 미검토
A126: 125 | B126: RV-MANUAL-ENT-125 | C126: Manual | D126: RemoteView Enterprise SaaS 사용자 가이드 | E126: 에이전트 삭제하기 > 사용자 페이지에서 삭제 | F126: RemoteView | G126: 사용자 페이지에서 삭제 | H126: 관리자 | I126: 공개 | J126: 설정/사용 방법 문의 | K126: https://files.rsupport.com/ko/remoteview/guides/RemoteView_Enterprise_SaaS_User_Guide_kr.pdf | L126: chunk 53 / §에이전트 삭제하기 / ● 사용자 페이지에서 삭제 | N126: ① 사용자 페이지에 로그인 합니다. ② 원격지 PC 관리에서 클릭 또는 제어판>프로그램 삭제에서 에이전트 프로그램을 선택 후 [제거] 버튼을 클릭 합니다. - 설치준비 과정을 통해 설치된 에이전트 유무를 체크합니다. (Vista 이상 환경에서 UAC가 ON으로 설정되어 있을 경우 권한 상승창 팝업) ③ RemoteView 에이전트 설치가 되었다는 메시지 팝업창이 노출됩니다. ④ 사용자 페이지 로그인 계정의 비밀번호를 입력합니다. ⑤ 설치된 에이전트 제거 프로세스가 진행됩니다. ⑥ 에이전트 삭제가 완료됩니다. ⑦ 에이전트 삭제가 완료되면 시작프로그램 트레이에서 리모트뷰 에이전트 아이콘이 사라집니다. | O126: RemoteView에서 사용자 페이지에서 삭제은(는) 어떻게 하나요? | P126: RemoteView, ENT, 사용자 페이지에서 삭제 | Q126: RV-MANUAL-ENT-125 | R126: Claude(Fable5) | S126: 상 | T126: 미검토
A127: 126 | B127: RV-MANUAL-ENT-126 | C127: Manual | D127: RemoteView Enterprise SaaS 사용자 가이드 | E127: 에이전트 삭제하기 > 제어판>프로그램 목록에서 삭제 | F127: RemoteView | G127: 제어판>프로그램 목록에서 삭제 | H127: 관리자 | I127: 공개 | J127: 설정/사용 방법 문의 | K127: https://files.rsupport.com/ko/remoteview/guides/RemoteView_Enterprise_SaaS_User_Guide_kr.pdf | L127: chunk 53 / §에이전트 삭제하기 / ● 제어판>프로그램 목록에서 삭제 | N127: ① 시작>제어판>제어판>프로그램 추가/삭제(윈도우 비스타 이하) or 프로그램 및 기능(윈도우 7 이상)을 엽니다. ② 프로그램 목록에서 ‘RemoteView Agent’를 선택합니다. ③ [제거]를 클릭합니다. ④ 이후 삭제 프로세스는 ‘사용자 페이지에서 삭제’의 ③부터 ⑦까지의 진행과 동일하게 삭제 프로세스가 동작됩니 다. 7. 원격지 PC 접속 및 제어 원격 접속 가능 PC 확인 및 접속 (아이콘 정렬) (리스트 정렬) 항목 설 명 에이전트가 로그인 되어 있는 상태입니다. 원격접속 가능합니다. 에이전트가 로그아웃 되어 있는 상태입니다. 원격접속 불가합니다. 라이선스 수가 초과되어 비활성화 되어 있는 상태입니다. ① 접속이 가능한 원격지 PC를 선택하고 PC 아이콘을 더블 클릭하거나, 마우스 오른쪽 클릭 후 Online Menu에서 [원격제어]를 선택합니다. ② 사용자 인증 정보(에이전트 로그인 계정)를 입력합니다. ③ 사용자 PC에 리모트뷰 뷰어가 실행되고 뷰어에 원격지 PC의 화면이 나타납니다. 원격지 PC에는 원격제어 안내창 과 화면 우측 하단에 원격 제어중임을 나타내는 문구를 확인할 수 있습니다. (사용자 PC) (원격지 PC) 8. 원격지 PC 관리 기능 설명 원격지 PC 관리 > 등록된 PC 아이콘에서 마우스 오른쪽 클릭 후 확인할 수 있습니다. (*참고 이미지: 아이콘별 실행 메뉴) 메 뉴 기 능 연결확인 원격지 PC의 에이전트의 최신 연결 상태(로그인 상태)를 확인합니다. 동영상 모드제어 리모트뷰 동영상 뷰어 모드를 이용하여 원격지 PC를 원격 접속 웹뷰어 제어 뷰어 프로그램 설치 없이 웹 브라우저에서 원격지 PC를 원격 접속 원격제어 리모트뷰 원격제어 뷰어 모드를 이용하여 원격지 PC를 원격 접속 원격탐색기 FTP 방식으로 원격지 PC와 파일을 송/수신 WOL로 전원 켜기 WOL 기능이 실행되고, 원격지 PC의 전원 켜기 가능 제어 도구 모음 시스템 종료 원격지 PC를 로그오프, 재시작 또는 종료 시스템정보 원격지 PC의 S/W, H/W 등의 시스템 정보 표시 원격화면캡처 원격지 PC가 동작 중일 경우 원격지 PC화면을 캡처하여 사용자 PC에서 확인 * 캡처 된 화면은 저장되지 않음 프로세스실행 원격지 PC에 특정 프로세스를 실행 프로세스목록 원격지 PC에 실행중인 프로세스 목록을 확인하거나 중지 서비스 재시작 원격지 PC의 에이전트를 재 시작 Agent 업데이트 원격지 PC의 에이전트를 업데이트 이메일 초대 등록된 사용자나 비 등록된 특정 사용자(일시적)에게 선택한 PC에 대하여 1회성으 로 원격제어 할 수 있는 웹 링크를 발송 즐겨찾기 즐겨찾기 카테고리에 PC를 추가 이동 선택한 PC를 다른 그룹으로 이동 삭제 선택한 PC를 삭제 계정 변경 원격접속 사용자 인증 ID와 비밀번호를 변경 사용자정보 에이전트에 할당된 사용자를 조회 등록정보 에이전트의 정보를 확인 및 변경 연결확인 에이전트의 최신 연결상태를 확인할 수 있습니다. (에이전트 로그인 상태) (에이전트 로그아웃 상태) 동영상 모드 제어 원격접속 사용자 인증 정보 정상입력 후 원격제어를 실행할 수 있습니다. 웹뷰어 제어 원격접속 사용자 인증 정보 정상 입력 후 브라우저를 이용한 웹 뷰어를 실행할 수 있습니다. 원격제어 원격접속 사용자 인증 정보 정상 입력 후 원격제어를 실행할 수 있습니다. ``` RemoteView | O127: RemoteView에서 제어판>프로그램 목록에서 삭제은(는) 어떻게 하나요? | P127: RemoteView, ENT, 제어판>프로그램 목록에서 삭제 | Q127: RV-MANUAL-ENT-126 | R127: Claude(Fable5) | S127: 상 | T127: 미검토
A128: 127 | B128: RV-MANUAL-ENT-127 | C128: Manual | D128: RemoteView Enterprise SaaS 사용자 가이드 | E128: WOL로 전원 켜기 노출 조건 > Agent: Windows 대상 (그 외 OS 미노출) | F128: RemoteView | G128: Agent: Windows 대상 (그 외 OS 미노출) | H128: 관리자 | I128: 공개 | J128: 기능/가능 여부 확인 | K128: https://files.rsupport.com/ko/remoteview/guides/RemoteView_Enterprise_SaaS_User_Guide_kr.pdf | L128: chunk 56 / §WOL로 전원 켜기 노출 조건 / ● Agent: Windows 대상 (그 외 OS 미노출) | N128: A B C | O128: RemoteView의 Agent: Windows 대상 (그 외 OS 미노출)은(는) 무엇인가요? | P128: RemoteView, ENT, Agent: Windows 대상 (그 | Q128: RV-MANUAL-ENT-127 | R128: Claude(Fable5) | S128: 하 | T128: 근거약함 | U128: 본문 25자 미만 — 원문 근거 짧음
A129: 128 | B129: RV-MANUAL-ENT-128 | C129: Manual | D129: RemoteView Enterprise SaaS 사용자 가이드 | E129: 등록정보 > 공유 폴더: 원격지 PC에서 전송받은 파일들이 저장되는 기본 폴더. 폴더의 | F129: RemoteView | G129: 공유 폴더: 원격지 PC에서 전송받은 파일들이 저장되는 기본 폴더. 폴더 | H129: 관리자 | I129: 공개 | J129: 기능/가능 여부 확인 | K129: https://files.rsupport.com/ko/remoteview/guides/RemoteView_Enterprise_SaaS_User_Guide_kr.pdf | L129: chunk 64 / §등록정보 / ● 공유 폴더: 원격지 PC에서 전송받은 파일들이 저장되는 기본 폴더. 폴더의 | N129: 위치는 변경이 가능합니다. | O129: RemoteView의 공유 폴더: 원격지 PC에서 전송받은 파일들이 저장되는 기본 폴더. 폴더의은(는) 무엇인가요? | P129: RemoteView, ENT, 공유 폴더: 원격지 PC에서 전송받은 | Q129: RV-MANUAL-ENT-128 | R129: Claude(Fable5) | S129: 하 | T129: 근거약함 | U129: 본문 25자 미만 — 원문 근거 짧음
A130: 129 | B130: RV-MANUAL-ENT-129 | C130: Manual | D130: RemoteView Enterprise SaaS 사용자 가이드 | E130: 등록정보 > SLEEP 해제: 시스템 절전모드 적용시 SLEEP 해제를 하여 절전모드로 빠 | F130: RemoteView | G130: SLEEP 해제: 시스템 절전모드 적용시 SLEEP 해제를 하여 절전모드 | H130: 관리자 | I130: 공개 | J130: 기능/가능 여부 확인 | K130: https://files.rsupport.com/ko/remoteview/guides/RemoteView_Enterprise_SaaS_User_Guide_kr.pdf | L130: chunk 64 / §등록정보 / ● SLEEP 해제: 시스템 절전모드 적용시 SLEEP 해제를 하여 절전모드로 빠 | N130: 지지 않게 합니다. 프록시 서버 설정 | O130: RemoteView의 SLEEP 해제: 시스템 절전모드 적용시 SLEEP 해제를 하여 절전모드로 빠은(는) 무엇인가요? | P130: RemoteView, ENT, SLEEP 해제: 시스템 절전모드 적 | Q130: RV-MANUAL-ENT-129 | R130: Claude(Fable5) | S130: 하 | T130: 근거약함 | U130: 본문 25자 미만 — 원문 근거 짧음
A131: 130 | B131: RV-MANUAL-ENT-130 | C131: Manual | D131: RemoteView Enterprise SaaS 사용자 가이드 | E131: 등록정보 > 원격지 PC의 네트워크 환경이 프록시 서버를 사용 시 “프록시 사용”에 체크 | F131: RemoteView | G131: 원격지 PC의 네트워크 환경이 프록시 서버를 사용 시 “프록시 사용”에 | H131: 관리자 | I131: 공개 | J131: 기능/가능 여부 확인 | K131: https://files.rsupport.com/ko/remoteview/guides/RemoteView_Enterprise_SaaS_User_Guide_kr.pdf | L131: chunk 64 / §등록정보 / ● 원격지 PC의 네트워크 환경이 프록시 서버를 사용 시 “프록시 사용”에 체크 | N131: 합니다. | O131: RemoteView의 원격지 PC의 네트워크 환경이 프록시 서버를 사용 시 “프록시 사용”에 체크은(는) 무엇인가요? | P131: RemoteView, ENT, 원격지 PC의 네트워크 환경이 프록시 | Q131: RV-MANUAL-ENT-130 | R131: Claude(Fable5) | S131: 하 | T131: 근거약함 | U131: 본문 25자 미만 — 원문 근거 짧음
A132: 131 | B132: RV-MANUAL-ENT-131 | C132: Manual | D132: RemoteView Enterprise SaaS 사용자 가이드 | E132: 등록정보 > 관리자는 프록시 서버 정보를 입력합니다. 인터넷에 직접 연결되어 있거나 | F132: RemoteView | G132: 관리자는 프록시 서버 정보를 입력합니다. 인터넷에 직접 연결되어 있거나 | H132: 관리자 | I132: 공개 | J132: 기능/가능 여부 확인 | K132: https://files.rsupport.com/ko/remoteview/guides/RemoteView_Enterprise_SaaS_User_Guide_kr.pdf | L132: chunk 64 / §등록정보 / ● 관리자는 프록시 서버 정보를 입력합니다. 인터넷에 직접 연결되어 있거나 | N132: 프록시 서버를 사용하지 않을 경우 설정하지 않아도 됩니다. [보안설정] Agent 접근 계정 설정 | O132: RemoteView의 관리자는 프록시 서버 정보를 입력합니다. 인터넷에 직접 연결되어 있거나은(는) 무엇인가요? | P132: RemoteView, ENT, 관리자는 프록시 서버 정보를 입력합니 | Q132: RV-MANUAL-ENT-131 | R132: Claude(Fable5) | S132: 중 | T132: 미검토
A133: 132 | B133: RV-MANUAL-ENT-132 | C133: Manual | D133: RemoteView Enterprise SaaS 사용자 가이드 | E133: 등록정보 > 원격지 PC에 접근 시 인증 받을 계정을 변경할 수 있습니다. | F133: RemoteView | G133: 원격지 PC에 접근 시 인증 받을 계정을 변경할 수 있습니다. | H133: 관리자 | I133: 공개 | J133: 기능/가능 여부 확인 | K133: https://files.rsupport.com/ko/remoteview/guides/RemoteView_Enterprise_SaaS_User_Guide_kr.pdf | L133: chunk 64 / §등록정보 / ● 원격지 PC에 접근 시 인증 받을 계정을 변경할 수 있습니다. | N133: 화면 잠금 설정 | O133: RemoteView의 원격지 PC에 접근 시 인증 받을 계정을 변경할 수 있습니다.은(는) 무엇인가요? | P133: RemoteView, ENT, 원격지 PC에 접근 시 인증 받을 계 | Q133: RV-MANUAL-ENT-132 | R133: Claude(Fable5) | S133: 하 | T133: 근거약함 | U133: 본문 25자 미만 — 원문 근거 짧음
...

Sheet B1_근거약함
A1: Unit ID | B1: title | C1: source_location | D1: 상태 | E1: 비고 | F1: 이 단위가 말하는 사실(앞 150자)
A2: RV-MANUAL-ENT-029 | B2: RemoteView Enterprise SaaS 사용자 가이드 | C2: chunk 34 / §사용자별 제어 권한 / ● 소팅 | D2: 근거약함 | E2: 본문 25자 미만 — 원문 근거 짧음 | F2: 선택한 옵션값대로 목록이 소팅 됩니다.
A3: RV-MANUAL-ENT-038 | B3: RemoteView Enterprise SaaS 사용자 가이드 | C3: chunk 36 / §사용자별 제어 권한 / ● 소팅 | D3: 근거약함 | E3: 본문 25자 미만 — 원문 근거 짧음 | F3: 선택한 옵션값 대로 목록이 소팅 됩니다.
A4: RV-MANUAL-ENT-051 | B4: RemoteView Enterprise SaaS 사용자 가이드 | C4: chunk 39 / §사용자 별 에이전트 설치 수 제한 기능 / ● 소팅 (2차) | D4: 근거약함 | E4: 본문 25자 미만 — 원문 근거 짧음 | F4: 선택한 옵션값대로 목록이 소팅 됩니다.
A5: RV-MANUAL-ENT-061 | B5: RemoteView Enterprise SaaS 사용자 가이드 | C5: chunk 40 / §사용자/조직관리 > 사용자 조직 / ● 소팅 | D5: 근거약함 | E5: 본문 25자 미만 — 원문 근거 짧음 | F5: 선택한 옵션값 대로 목록이 소팅 됩니다.
A6: RV-MANUAL-ENT-067 | B6: RemoteView Enterprise SaaS 사용자 가이드 | C6: chunk 42 / §원격지원 이력 관리 / ● 원격제어 기능 설정 / ■ 모바일 접속 사용 | D6: 근거약함 | E6: 본문 25자 미만 — 원문 근거 짧음 | F6: 모바일 접속 여부를 설정합니다.
A7: RV-MANUAL-ENT-069 | B7: RemoteView Enterprise SaaS 사용자 가이드 | C7: chunk 42 / §원격지원 이력 관리 / ● 원격제어 기능 설정 / ■ 이메일 초대 | D7: 근거약함 | E7: 본문 25자 미만 — 원문 근거 짧음 | F7: 이메일 초대 기능 사용 여부를 설정합니다.
A8: RV-MANUAL-ENT-078 | B8: RemoteView Enterprise SaaS 사용자 가이드 | C8: chunk 42 / §원격지원 이력 관리 / ● 파일 전송 설정 / ■ 원격탐색기 사용 | D8: 근거약함 | E8: 본문 25자 미만 — 원문 근거 짧음 | F8: 원격탐색기 사용 여부를 설정합니다.
A9: RV-MANUAL-ENT-110 | B9: RemoteView Enterprise SaaS 사용자 가이드 | C9: chunk 50 / §내 옵션 설정 / ● 일반 설정 / ■ 즐겨찾기 | D9: 근거약함 | E9: 본문 25자 미만 — 원문 근거 짧음 | F9: 즐겨찾기 영역 사용여부를 설정합니다.
A10: RV-MANUAL-ENT-122 | B10: RemoteView Enterprise SaaS 사용자 가이드 | C10: chunk 51 / §RemoteView 정보 / ● 문의 | D10: 근거약함 | E10: 본문 25자 미만 — 원문 근거 짧음 | F10: 제품문의와 홈페이지의 링크가 제공됩니다.
A11: RV-MANUAL-ENT-127 | B11: RemoteView Enterprise SaaS 사용자 가이드 | C11: chunk 56 / §WOL로 전원 켜기 노출 조건 / ● Agent: Windows 대상 (그 외 OS 미노출) | D11: 근거약함 | E11: 본문 25자 미만 — 원문 근거 짧음 | F11: A B C
A12: RV-MANUAL-ENT-128 | B12: RemoteView Enterprise SaaS 사용자 가이드 | C12: chunk 64 / §등록정보 / ● 공유 폴더: 원격지 PC에서 전송받은 파일들이 저장되는 기본 폴더. 폴더의 | D12: 근거약함 | E12: 본문 25자 미만 — 원문 근거 짧음 | F12: 위치는 변경이 가능합니다.
... A27: RV-DOC-LEAF-002 | B27: RemoteView SE 리플렛 | C27: chunk 0 / §리플렛 / 리플렛 문단 2 | D27: 근거약함 | E27: 브로슈어 단문·OCR 품질 불안 (DEC-009 홍보 수사 정답 소재 금지 유의) | F27: R:SUPPORT ```

Sheet B1_사람확인
A1: Unit ID | B1: title | C1: source_location | D1: 상태 | E1: 비고 | F1: 이 단위가 말하는 사실(앞 150자)
A2: RV-MANUAL-ENT-066 | B2: RemoteView Enterprise SaaS 사용자 가이드 | C2: chunk 41 / §사용자/조직관리 > 사용자 조직 / ● 기간설정 | D2: 사람확인 | E2: 복합 내용 의심(절차+표 혼재 또는 과대 본문) — 재절단 검토 필요 | F2: ① Input-box 마우스 클릭합니다. ② 캘린더가 팝업 됩니다. ③ 시작일, 마지막일을 선택합니다. ④ [검색] 버튼을 클릭합니다. 환경설정 <각각의 권한 별 사용자에 맞게 설정을 할 수 있습니다.> 권한에 따라 로그인 시 사용할 수 있는 메뉴가 다릅니다. 관리자
A3: RV-MANUAL-ENT-134 | B3: RemoteView Enterprise SaaS 사용자 가이드 | C3: chunk 64 / §등록정보 / ● 리모트뷰 에이전트는 세션연결에 관한 정보를 에이전트가 설치 되어있는 PC에 저장합니다. 윈도우 우측 하단의 | D3: 사람확인 | E3: 복합 내용 의심(절차+표 혼재 또는 과대 본문) — 재절단 검토 필요 | F3: 아이콘 마우스 오른쪽 클릭 후 “로그 보기” 메뉴를 선택하여 로그 뷰어를 실행시켜 확인할 수 있습니다. 9. 리모트뷰 뷰어 기능 설명 뷰어 기능 요약 설명 홈 제어 설정 원격 접속 및 제어 환경을 설정 환경설정 제어 품질/모드, 미디어 장치 설정, 드라이버 설치 등의
A4: RV-MANUAL-IOSM-012 | B4: RemoteView SaaS 매뉴얼 iOS | C4: chunk 10 / §고객 지원 / ● 문의하기 | D4: 사람확인 | E4: 복합 내용 의심(절차+표 혼재 또는 과대 본문) — 재절단 검토 필요 | F4: ‘문의하기’ 메뉴 터치 시 문의등록 화면이 노출 됩니다. 필수 입력항목 (*이메일 주소/ 성명/ 회사명/ 전화번호/ 회사/사용자 ID/ 내용설명)을 모두 입력 후 개인정보 처리방침을 동의를 선택한 뒤에 ‘제출’하면 됩니다. (*첨부파일 기능은 모바일 기기에서는 사용할
A5: RV-MANUAL-AND-045 | B5: RemoteView Android SaaS 사용자 가이드 | C5: chunk 22 / §9.2 / ● 에이전트 등록 | D5: 사람확인 | E5: 복합 내용 의심(절차+표 혼재 또는 과대 본문) — 재절단 검토 필요 | F5: ① 홈페이지(https://rview.com/)에서 회원가입 시 등록한 계정으로 로그인합니다. ② 등록하고자 하는 대표아이디/사용자 아이디/비밀번호 입력 후 에이전트 등록 버튼을 선택 시 권한설정 페이지로 이동합니다. ③ 허용이 필요한 권한 > 권한설정으로 이동합니다.
A6: RV-DOC-LEAF-003 | B6: RemoteView SE 리플렛 | C6: chunk 0 / §리플렛 / 리플렛 문단 3 | D6: 사람확인 | E6: OCR 문자 역전 훼손 — 원본 PDF 대조 필요 | F6: 원격 제어 중 고객의 디바이스 네트워크 연결방식이 바뀌어도 원격 연결이 끊기지 않고 재연결 됩니다. 멀티 세션기능을 통한 동시 제어를 지원 합니다. 유지보수 및 장애 발생 시 서울에 집중되어 있는 IT 협력 업체의 지원을 안전하고 빠르게 받을 수 있어 비용과 장애처리

Sheet B1_제외대장
A1: Unit ID | B1: 사유
A2: (해당 없음 — B1 제외 단위 0. TOC·표지 청크 88개는 단위 미절단(목차는 사실 단위 아님), 본 보고 §비고 기재)

Sheet B1_폴딩대장
A1: Unit ID | B1: 사유
A2: (해당 없음 — 단일 작업자·단일 패스, dedup 미발화 정상(지시서 v0.4 §7))

Sheet B1_계리
A1: 항목 | B1: 값 | C1: 수식/근거
A2: 총 절단 단위 | B2: =COUNTA(B1_커버리지맵!B:B)-1 | C2: 단위 시트 실측
A3: 미검토(유효) | B3: =COUNTIF(B1_커버리지맵!T:T,"미검토")
A4: 근거약함 | B4: =COUNTIF(B1_커버리지맵!T:T,"근거약함") | C4: 대장 일치 필수
A5: 사람확인 | B5: =COUNTIF(B1_커버리지맵!T:T,"사람확인") | C5: 대장 일치 필수
A6: 제외 | B6: =COUNTIF(B1_커버리지맵!T:T,"제외")
A7: 폴딩(중복) | B7: =COUNTIF(B1_커버리지맵!T:T,"중복")
A8: 등식 검증(합-총) | B8: =SUM(B3:B7)-B2 | C8: 0이어야 함

Sheet B2_커버리지맵
A1: # | B1: Unit ID | C1: type | D1: title | E1: description | F1: product | G1: feature | H1: user_type | I1: acl_level | J1: intent | K1: source/resource | L1: source_location | M1: related_units | N1: 이 단위가 말하는 사실 | O1: 답변 가능한 질문 | P1: tags | Q1: citation_id | R1: extracted_by | S1: confidence | T1: 상태 | U1: 비고
A2: 1 | B2: RV-WEB-HOME-001 | C2: WebPage | D2: RemoteView 웹 홈 페이지 | E2: 국내 1위 원격제어 | F2: RemoteView | G2: 국내 1위 원격제어 | H2: 공통 | I2: 공개 | J2: 기능/제품 정보 확인 | K2: https://content.rview.com/ko/ | L2: 본문 § 국내 1위 원격제어 | N2: 리모트뷰는 다릅니다 끊김 없는 60FPS 제어 품질, SSO 로그인, 강화된 IP 보안까지 쾌적하고 안전한 업무 환경을 경험하세요. 최근 한달 1978명 체험 중 | O2: RemoteView 국내 1위 원격제어에 대해 알려주세요 | P2: RemoteView, 홈, 국내 1위 원격제어 | Q2: RV-WEB-HOME-001 | R2: Claude(Fable5) | S2: 상 | T2: 미검토
A3: 2 | B3: RV-WEB-HOME-002 | C3: WebPage | D3: RemoteView 웹 홈 페이지 | E3: 25년 연속 1위, | F3: RemoteView | G3: 25년 연속 1위, | H3: 공통 | I3: 공개 | J3: 기능/제품 정보 확인 | K3: https://content.rview.com/ko/ | L3: 본문 § 25년 연속 1위, | N3: 30만 고객이 선택한 리모트뷰 - ![기상청](/wp-content/uploads/sites/2/image/main/main_ranking_l - ![율촌](/wp-content/uploads/sites/2/image/main/main_ranking_ .webp) | O3: RemoteView 25년 연속 1위,에 대해 알려주세요 | P3: RemoteView, 홈, 25년 연속 1위, | Q3: RV-WEB-HOME-002 | R3: Claude(Fable5) | S3: 상 | T3: 미검토
A4: 3 | B4: RV-WEB-HOME-003 | C4: WebPage | D4: RemoteView 웹 홈 페이지 | E4: 원격으로 해결 가능한데, | F4: RemoteView | G4: 원격으로 해결 가능한데, | H4: 공통 | I4: 공개 | J4: 기능/제품 정보 확인 | K4: https://content.rview.com/ko/ | L4: 본문 § 원격으로 해결 가능한데, | N4: 아직도 현장에 가고 있나요? - 01 | O4: RemoteView 원격으로 해결 가능한데,에 대해 알려주세요 | P4: RemoteView, 홈, 원격으로 해결 가능한데, | Q4: RV-WEB-HOME-003 | R4: Claude(Fable5) | S4: 하 | T4: 근거약함 | U4: 본문 25자 미만
A5: 4 | B5: RV-WEB-HOME-004 | C5: WebPage | D5: RemoteView 웹 홈 페이지 | E5: 비용의 낭비 | F5: RemoteView | G5: 비용의 낭비 | H5: 공통 | I5: 공개 | J5: 기능/제품 정보 확인 | K5: https://content.rview.com/ko/ | L5: 본문 § 비용의 낭비 | N5: “서버 하나 재부팅하려고 IDC까지 왕복 4시간이나 걸렸어요.” 현장 출동 한 번에 드는 시간·운영비를 연간으로 환산하면 큰 비용입니다. - 02 | O5: RemoteView 비용의 낭비에 대해 알려주세요 | P5: RemoteView, 홈, 비용의 낭비 | Q5: RV-WEB-HOME-004 | R5: Claude(Fable5) | S5: 상 | T5: 미검토
A6: 5 | B6: RV-WEB-HOME-005 | C6: WebPage | D6: RemoteView 웹 홈 페이지 | E6: 업무 중단 | F6: RemoteView | G6: 업무 중단 | H6: 공통 | I6: 공개 | J6: 기능/제품 정보 확인 | K6: https://content.rview.com/ko/ | L6: 본문 § 업무 중단 | N6: “담당자가 출장 중이라 오후까지 기다려 주세요.” 장비 장애는 기다려주지 않습니다. 대응이 늦어지면 매출이 멈춥니다. - 03 | O6: RemoteView 업무 중단에 대해 알려주세요 | P6: RemoteView, 홈, 업무 중단 | Q6: RV-WEB-HOME-005 | R6: Claude(Fable5) | S6: 상 | T6: 미검토
A7: 6 | B7: RV-WEB-HOME-006 | C7: WebPage | D7: RemoteView 웹 홈 페이지 | E7: 보안·통제 부재 | F7: RemoteView | G7: 보안·통제 부재 | H7: 공통 | I7: 공개 | J7: 기능/제품 정보 확인 | K7: https://content.rview.com/ko/ | L7: 본문 § 보안·통제 부재 | N7: “외주 업체가 우리 서버에 접속했는데, 무엇을 했는지 모릅니다.” 접속 기록·화면 녹화·권한 통제가 없는 원격은 보안 사고의 시작입니다. | O7: RemoteView 보안·통제 부재에 대해 알려주세요 | P7: RemoteView, 홈, 보안·통제 부재 | Q7: RV-WEB-HOME-006 | R7: Claude(Fable5) | S7: 상 | T7: 미검토
A8: 7 | B8: RV-WEB-HOME-007 | C8: WebPage | D8: RemoteView 웹 홈 페이지 | E8: 어떤 현장이든, | F8: RemoteView | G8: 어떤 현장이든, | H8: 공통 | I8: 공개 | J8: 기능/제품 정보 확인 | K8: https://content.rview.com/ko/ | L8: 본문 § 어떤 현장이든, | N8: 목적에 맞는 원격제어 리모트뷰가 있습니다 [ | O8: RemoteView 어떤 현장이든,에 대해 알려주세요 | P8: RemoteView, 홈, 어떤 현장이든, | Q8: RV-WEB-HOME-007 | R8: Claude(Fable5) | S8: 하 | T8: 근거약함 | U8: 본문 25자 미만
A9: 8 | B9: RV-WEB-HOME-008 | C9: WebPage | D9: RemoteView 웹 홈 페이지 | E9: 리모트뷰 | F9: RemoteView | G9: 리모트뷰 | H9: 공통 | I9: 공개 | J9: 기능/제품 정보 확인 | K9: https://content.rview.com/ko/ | L9: 본문 § 리모트뷰 | N9: 웹 브라우저 하나로 언제 어디서든 내 PC 제어 ](/ko/product/remoteview/)[ | O9: RemoteView 리모트뷰에 대해 알려주세요 | P9: RemoteView, 홈, 리모트뷰 | Q9: RV-WEB-HOME-008 | R9: Claude(Fable5) | S9: 중 | T9: 미검토
A10: 9 | B10: RV-WEB-HOME-009 | C10: WebPage | D10: RemoteView 웹 홈 페이지 | E10: 리모트뷰 SE | F10: RemoteView | G10: 리모트뷰 SE | H10: 공통 | I10: 공개 | J10: 기능/제품 정보 확인 | K10: https://content.rview.com/ko/ | L10: 본문 § 리모트뷰 SE | N10: 외부 인력 접속 기록·권한 통제· 화면 차단까지, 강화된 보안 솔루션 ](/ko/product/remoteview-se/) [ | O10: RemoteView 리모트뷰 SE에 대해 알려주세요 | P10: RemoteView, 홈, 리모트뷰 SE | Q10: RV-WEB-HOME-009 | R10: Claude(Fable5) | S10: 상 | T10: 미검토
A11: 10 | B11: RV-WEB-HOME-010 | C11: WebPage | D11: RemoteView 웹 홈 페이지 | E11: 리모트뷰 OT | F11: RemoteView | G11: 리모트뷰 OT | H11: 공통 | I11: 공개 | J11: 기능/제품 정보 확인 | K11: https://content.rview.com/ko/ | L11: 본문 § 리모트뷰 OT | N11: 제조·산업 설비의 실시간 모니터링 및 즉시 대응 ](/ko/product/remoteview-ot/)[ | O11: RemoteView 리모트뷰 OT에 대해 알려주세요 | P11: RemoteView, 홈, 리모트뷰 OT | Q11: RV-WEB-HOME-010 | R11: Claude(Fable5) | S11: 중 | T11: 미검토
A12: 11 | B12: RV-WEB-HOME-011 | C12: WebPage | D12: RemoteView 웹 홈 페이지 | E12: AI 온라인 용역통제 시스템 | F12: RemoteView | G12: AI 온라인 용역통제 시스템 | H12: 공통 | I12: 공개 | J12: 기능/제품 정보 확인 | K12: https://content.rview.com/ko/ | L12: 본문 § AI 온라인 용역통제 시스템 | N12: 공공·금융 보안 기준을 충족하는 원격 용역 관리 체계 ](/ko/product/control/) [ | O12: RemoteView AI 온라인 용역통제 시스템에 대해 알려주세요 | P12: RemoteView, 홈, AI 온라인 용역통제 시스템 | Q12: RV-WEB-HOME-011 | R12: Claude(Fable5) | S12: 중 | T12: 미검토
A13: 12 | B13: RV-WEB-HOME-012 | C13: WebPage | D13: RemoteView 웹 홈 페이지 | E13: 리모트뷰박스 | F13: RemoteView | G13: 리모트뷰박스 | H13: 공통 | I13: 공개 | J13: 기능/제품 정보 확인 | K13: https://content.rview.com/ko/ | L13: 본문 § 리모트뷰박스 | N13: 소프트웨어 설치가 안되는 장비도 케이블 연결로 원격 제어 ](/ko/product/remoteviewbox/)[ | O13: RemoteView 리모트뷰박스에 대해 알려주세요 | P13: RemoteView, 홈, 리모트뷰박스 | Q13: RV-WEB-HOME-012 | R13: Claude(Fable5) | S13: 상 | T13: 미검토
A14: 13 | B14: RV-WEB-HOME-013 | C14: WebPage | D14: RemoteView 웹 홈 페이지 | E14: RemoteWOL | F14: RemoteView | G14: RemoteWOL | H14: 공통 | I14: 공개 | J14: 기능/제품 정보 확인 | K14: https://content.rview.com/ko/ | L14: 본문 § RemoteWOL | N14: 퇴근 후에도 클릭 한 번으로 PC·서버 전원을 제어, 상시 가동 비용 절감 ](/ko/product/remotewol/) 나에게 맞는 리모트뷰 제품 찾기 나에게 맞는 리모트뷰 제품 찾기 ![](/wp-content/uploads/sites/2/image/main/main_popup_icon.webp) 리모트뷰 제품 라인업 한 눈에 비교하기 ➡️ 리모트뷰는 도입 방식과 기능에 따라 다양한 제품 라인업을 제공합니다. ✔️ 여러분의 비즈니스에 맞는 최적의 제품을 찾아보세요. 🔍 리모트뷰 제품 라인업 | 구분 | 구독형(SaaS) | 구축형(솔루션) | 하드웨어형 | | --- | --- | --- | --- | | 리모트뷰 제품 라인업 | - 리모트뷰 : 가장 범용적으로 사용하는 원격제어 솔루션 (원격제어, 재택근무 등) | - 리모트뷰SE : 보안강화형 - 리모트뷰OT : 제조업 특화형 - 온라인 용역 통제솔루션 : 공공기관 특화 용역 및 장비관리 | - RemoteViewBOX : 보안이슈 또는 노후장비로 에이전트 설치가 어려운 장치를 케이블로 연결 - RemoteWOL : PC와 서버의 전원 원격제어 | | 도입방식 | 온라인에서 구매 후 바로 사용 가능 | 상담 후 적용 / 기업이나 기관 환경에 맞는 다양한 솔루션 구축방식 제공 | 구매 후 설치하여 사용 가능 | | 기능 | - 모바일 원격제어 - 웹뷰어 - 다중접속 기능 - 멀티/듀얼모니터 - 원격PC 화면잠금 - 원격프린터 - 특정 프로세스 실행제한 - 특정도메인 차단 - OTP인증 등 - 원격제어 기능 제공 | 리모트뷰 기능 전체 + 보안 및 비즈니스 특화 / 보안 요구사항 및 비즈니스 요구사항 충족하여 커스텀 개발 | - RemoteViewBOX : 리모트뷰 기능 그대로 사용 / 노후기기·특수기기 등에 케이블로 연결하여 원격제어 가능 - RemoteWOL : 리모트뷰가 설치된 PC·서버 등 다수의 디바이스 전원을 원격으로 통제 | | 가격 | - 스탠다드 월 5,000원 - 엔터프라이즈 월 7,000원 \*연간 결제 시 할인적용[자세히보기](/ko/pricing/license/) | 서버 / 솔루션 / 어플라이언스 / 구축형 클라우 드 등 환경·사양에 따라 다양 [문의하기](/ko/contact/) | - RemoteViewBOX : 1,000,000원 / 1EA - RemoteWOL : 500,000원 / 1EA | 💡 리모트뷰, 직접 경험하며 선택해 보세요. ✅ 도움이 필요하시다면 편하게 상담을 신청해 주세요. [문의하기](/ko/contact/) ✅ 상담 전, 리모트뷰를 직접 체험해보시는 것 도 좋아요. [무료로 이용하기](/ko/trial/) | O14: RemoteView RemoteWOL에 대해 알려주세요 | P14: RemoteView, 홈, RemoteWOL | Q14: RV-WEB-HOME-013 | R14: Claude(Fable5) | S14: 상 | T14: 미검토
A15: 14 | B15: RV-WEB-HOME-014 | C15: WebPage | D15: RemoteView 웹 홈 페이지 | E15: PC 원격제어 | F15: RemoteView | G15: PC 원격제어 | H15: 공통 | I15: 공개 | J15: 기능/제품 정보 확인 | K15: https://content.rview.com/ko/ | L15: 본문 § PC 원격제어 | N15: 운영체제 상관없이 간편하게 PC를 원격제어 ](/ko/feature) | O15: RemoteView PC 원격제어에 대해 알려주세요 | P15: RemoteView, 홈, PC 원격제어 | Q15: RV-WEB-HOME-014 | R15: Claude(Fable5) | S15: 중 | T15: 미검토
A16: 15 | B16: RV-WEB-HOME-015 | C16: WebPage | D16: RemoteView 웹 홈 페이지 | E16: 모바일 원격제어 | F16: RemoteView | G16: 모바일 원격제어 | H16: 공통 | I16: 공개 | J16: 기능/제품 정보 확인 | K16: https://content.rview.com/ko/ | L16: 본문 § 모바일 원격제어 | N16: 리모트뷰 앱으로 스마트폰에서 PC 제어 ](/ko/feature/mobile/) | O16: RemoteView 모바일 원격제어에 대해 알려주세요 | P16: RemoteView, 홈, 모바일 원격제어 | Q16: RV-WEB-HOME-015 | R16: Claude(Fable5) | S16: 중 | T16: 미검토
A17: 16 | B17: RV-WEB-HOME-016 | C17: WebPage | D17: RemoteView 웹 홈 페이지 | E17: 웹뷰어 제어 | F17: RemoteView | G17: 웹뷰어 제어 | H17: 공통 | I17: 공개 | J17: 기능/제품 정보 확인 | K17: https://content.rview.com/ko/ | L17: 본문 § 웹뷰어 제어 | N17: 설치 없이 브라우저에서 바로 접속·제어 ](/ko/feature/webviewer/) | O17: RemoteView 웹뷰어 제어에 대해 알려주세요 | P17: RemoteView, 홈, 웹뷰어 제어 | Q17: RV-WEB-HOME-016 | R17: Claude(Fable5) | S17: 중 | T17: 미검토
A18: 17 | B18: RV-WEB-HOME-017 | C18: WebPage | D18: RemoteView 웹 홈 페이지 | E18: 다중접속 기능 | F18: RemoteView | G18: 다중접속 기능 | H18: 공통 | I18: 공개 | J18: 기능/제품 정보 확인 | K18: https://content.rview.com/ko/ | L18: 본문 § 다중접속 기능 | N18: 여러 사용자 동시 접속, 실시간 협업 ](/ko/feature/multiple-access/) | O18: RemoteView 다중접속 기능에 대해 알려주세요 | P18: RemoteView, 홈, 다중접속 기능 | Q18: RV-WEB-HOME-017 | R18: Claude(Fable5) | S18: 중 | T18: 미검토
A19: 18 | B19: RV-WEB-HOME-018 | C19: WebPage | D19: RemoteView 웹 홈 페이지 | E19: 멀티/듀얼모니터 | F19: RemoteView | G19: 멀티/듀얼모니터 | H19: 공통 | I19: 공개 | J19: 기능/제품 정보 확인 | K19: https://content.rview.com/ko/ | L19: 본문 § 멀티/듀얼모니터 | N19: 다중 모니터 자유 전환, 원격 멀티태스킹 ](/ko/feature/multiple-monitors/) | O19: RemoteView 멀티/듀얼모니터에 대해 알려주세요 | P19: RemoteView, 홈, 멀티/듀얼모니터 | Q19: RV-WEB-HOME-018 | R19: Claude(Fable5) | S19: 중 | T19: 미검토
A20: 19 | B20: RV-WEB-HOME-019 | C20: WebPage | D20: RemoteView 웹 홈 페이지 | E20: 실시간 모니터링(라이브뷰) | F20: RemoteView | G20: 실시간 모니터링(라이브뷰) | H20: 공통 | I20: 공개 | J20: 기능/제품 정보 확인 | K20: https://content.rview.com/ko/ | L20: 본문 § 실시간 모니터링(라이브뷰) | N20: 5초 단위 라이브뷰, 제어 없이 상태 확인 ](/ko/feature) | O20: RemoteView 실시간 모니터링(라이브뷰)에 대해 알려주세요 | P20: RemoteView, 홈, 실시간 모니터링(라이브뷰) | Q20: RV-WEB-HOME-019 | R20: Claude(Fable5) | S20: 중 | T20: 미검토
A21: 20 | B21: RV-WEB-HOME-020 | C21: WebPage | D21: RemoteView 웹 홈 페이지 | E21: 국가·국제 보안 인증 기준을 충족한 기술로 | F21: RemoteView | G21: 국가·국제 보안 인증 기준을 충족한 기술로 | H21: 공통 | I21: 공개 | J21: 기능/제품 정보 확인 | K21: https://content.rview.com/ko/ | L21: 본문 § 국가·국제 보안 인증 기준을 충족한 기술로 | N21: 안정적인 원격제어 환경을 제공합니다 안전한 원격제어를 위해 검증된 보안 체계를 제공합니다 브라우저가 video 태그를 지원하지 않습니다. | O21: RemoteView 국가·국제 보안 인증 기준을 충족한 기술로에 대해 알려주세요 | P21: RemoteView, 홈, 국가·국제 보안 인증 기준을 충족한 | Q21: RV-WEB-HOME-020 | R21: Claude(Fable5) | S21: 상 | T21: 미검토
A22: 21 | B22: RV-WEB-HOME-021 | C22: WebPage | D22: RemoteView 웹 홈 페이지 | E22: 국가 공인 | F22: RemoteView | G22: 국가 공인 | H22: 공통 | I22: 공개 | J22: 기능/제품 정보 확인 | K22: https://content.rview.com/ko/ | L22: 본문 § 국가 공인 | N22: 최고 등급 품질 인증 GS인증 1등급으로 제품의 품질, 기능성, 사용성을 공인된 기준으로 검증받았습니다. GS인증 1등급 한국정보통신기술협회 1등급 품질 인증 기능, 품질, 사용성을 공인 시험 기준으로 검증한 소프트웨어입니다. 공공 및 기업 환경에서 신뢰할 수 있 는 품질 수준을 제공합니다. 브라우저가 video 태그를 지원하지 않습니다. | O22: RemoteView 국가 공인에 대해 알려주세요 | P22: RemoteView, 홈, 국가 공인 | Q22: RV-WEB-HOME-021 | R22: Claude(Fable5) | S22: 상 | T22: 미검토 | U22: DEC-009 유의(홍보성 표현 포함) — 정답 소재 금지
A23: 22 | B23: RV-WEB-HOME-022 | C23: WebPage | D23: RemoteView 웹 홈 페이지 | E23: 국제 최고 수준 | F23: RemoteView | G23: 국제 최고 수준 | H23: 공통 | I23: 공개 | J23: 기능/제품 정보 확인 | K23: https://content.rview.com/ko/ | L23: 본문 § 국제 최고 수준 | N23: 정보보호 관리체계 인증 ISO/IEC 27001:2022, ISO/IEC 27017:2015 인증을 기반으로 국제 기준의 정보보호 관리체계를 준수하고 있습니다. ISO/IEC 27001:2022 ISO/IEC 27017:2015 정보보안 국제인증 국제 기준의 정보보호 관리체계를 준수하고 있습니다. 보안 정책부터 운영 관리까지 체계적인 보안 환경을 기반으로 서비스를 제공합니다. 브라우저가 video 태그를 지원하지 않습니다. | O23: RemoteView 국제 최고 수준에 대해 알려주세요 | P23: RemoteView, 홈, 국제 최고 수준 | Q23: RV-WEB-HOME-022 | R23: Claude(Fable5) | S23: 상 | T23: 미검토
A24: 23 | B24: RV-WEB-HOME-023 | C24: WebPage | D24: RemoteView 웹 홈 페이지 | E24: 공공 조달 등록으로 | F24: RemoteView | G24: 공공 조달 등록으로 | H24: 공통 | I24: 공개 | J24: 기능/제품 정보 확인 | K24: https://content.rview.com/ko/ | L24: 본문 § 공공 조달 등록으로 | N24: 검증된 제품 조달청 등록으로 공공기관 도입 기준을 충족한 검증된 제품입니다. 조달청 등록제품 국가정보원 국가정보보안기본지침 준수 공공기관이 요구하는 등록 기준과 절차를 충족한 제품입니다. 공공 도입 과정에서 요구되는 검증을 완료한 신뢰할 수 있는 제품입니다. 브라우저가 video 태그를 지원하지 않습니다. | O24: RemoteView 공공 조달 등록으로에 대해 알려주세요 | P24: RemoteView, 홈, 공공 조달 등록으로 | Q24: RV-WEB-HOME-023 | R24: Claude(Fable5) | S24: 상 | T24: 미검토
A25: 24 | B25: RV-WEB-HOME-024 | C25: WebPage | D25: RemoteView 웹 홈 페이지 | E25: 도입 기준에 대한 | F25: RemoteView | G25: 도입 기준에 대한 | H25: 공통 | I25: 공개 | J25: 기능/제품 정보 확인 | K25: https://content.rview.com/ko/ | L25: 본문 § 도입 기준에 대한 | N25: 신속한 검증 KISA 신속확인제를 통해 공공 및 기업의 도입 전 보안 검토를 신속하게 진행할 수 있습니다. KISA 신속확인제 공공기관 정보보호제품 도입 보안성 검증 공공기관 정보보호제품 도입 시 필요한 보안 적합성을 사전에 확인받았습니다. 도입 검토 과정에서 요구되는 보안 검토 부담을 줄일 수 있습니다. 브라우저가 video 태그를 지원하지 않습니다. | O25: RemoteView 도입 기준에 대한에 대해 알려주세요 | P25: RemoteView, 홈, 도입 기준에 대한 | Q25: RV-WEB-HOME-024 | R25: Claude(Fable5) | S25: 상 | T25: 미검토
A26: 25 | B26: RV-WEB-HOME-025 | C26: WebPage | D26: RemoteView 웹 홈 페이지 | E26: 국가 기준으로 검증된 | F26: RemoteView | G26: 국가 기준으로 검증된 | H26: 공통 | I26: 공개 | J26: 기능/제품 정보 확인 | K26: https://content.rview.com/ko/ | L26: 본문 § 국가 기준으로 검증된 | N26: 암호 안전성 국가정보원 KCMVP 인증을 통해 국가·공공기관 도입에 필요한 암호모듈 검증을 완료했습니다. 국가정보 KCMVP 국가·공공기관 도입 필수 암호모듈 안전성 확보 국가·공공 환경에서 요구되는 기준을 충족한 암호모듈을 적용했습니다. 검증된 암호모듈을 기반으로 강화된 보안 환경을 제공합니다. 안정적인 서비스 제공을 위해 명확한 서비스 수준협약(SLA)을 수립·준수하고 있습니다. 약속된 품질 기준을 확인해 보세요. | O26: RemoteView 국가 기준으로 검증된에 대해 알려주세요 | P26: RemoteView, 홈, 국가 기준으로 검증된 | Q26: RV-WEB-HOME-025 | R26: Claude(Fable5) | S26: 상 | T26: 미검토
A27: 26 | B27: RV-WEB-HOME-026 | C27: WebPage | D27: RemoteView 웹 홈 페이지 | E27: 이미 30만 기업이 리모트뷰로 | F27: RemoteView | G27: 이미 30만 기업이 리모트뷰로 | H27: 공통 | I27: 공개 | J27: 기능/제품 정보 확인 | K27: https://content.rview.com/ko/ | L27: 본문 § 이미 30만 기업이 리모트뷰로 | N27: 확실한 변화를 경험하고 있습니다 리모트뷰 고객사 평가기준 - ### 1위 25년 연속 원격 솔루션 1위 - ### 80% 시스템 유지보수 비용 절감 - ### 72% 인력 파견빈도 감소 - ### 83% 고객 만족도 (제품 사용편의성 포함) | O27: RemoteView 이미 30만 기업이 리모트뷰로에 대해 알려주세요 | P27: RemoteView, 홈, 이미 30만 기업이 리모트뷰로 | Q27: RV-WEB-HOME-026 | R27: Claude(Fable5) | S27: 상 | T27: 미검토 | U27: DEC-009 유의(홍보성 표현 포함) — 정답 소재 금지
A28: 27 | B28: RV-WEB-HOME-027 | C28: WebPage | D28: RemoteView 웹 홈 페이지 | E28: 운영비 30% 절감, | F28: RemoteView | G28: 운영비 30% 절감, | H28: 공통 | I28: 공개 | J28: 기능/제품 정보 확인 | K28: https://content.rview.com/ko/ | L28: 본문 § 운영비 30% 절감, | N28: 서비스 안정성은 강화 “리모트뷰 도입 후 무인매장 운영 비용이 기존 대비 30% 이상 절감되고, 안정적인 서비스 운영으로 점주와 고객 만족도가 높아졌습니다.” ![인생네컷](/wp-content/uploads/sites/2/image/main/main_ranking_review_02.webp) 무인기기 ](</ko/cases/equipment-03/ >)[![현장 대응 부담 절감, 원격 관리 체계 강화](/wp-content/uploads/sites/2/image/main/main_review_02.webp) | O28: RemoteView 운영비 30% 절감,에 대해 알려주세요 | P28: RemoteView, 홈, 운영비 30% 절감, | Q28: RV-WEB-HOME-027 | R28: Claude(Fable5) | S28: 상 | T28: 미검토
A29: 28 | B29: RV-WEB-HOME-028 | C29: WebPage | D29: RemoteView 웹 홈 페이지 | E29: 현장 대응 부담 절감, | F29: RemoteView | G29: 현장 대응 부담 절감, | H29: 공통 | I29: 공개 | J29: 기능/제품 정보 확인 | K29: https://content.rview.com/ko/ | L29: 본문 § 현장 대응 부담 절감, | N29: 원격 관리 체계 강화 “리모트뷰 솔루션 구축으로 전국 사업장과 외주 용역을 원격 관리하며, 대응과 관리 데이터를 혁신했습니다.” ![한국환경공단](/wp-content/uploads/sites/2/image/main/main_ranking_review_01.webp) 공공기관 ](/ko/cases/institution-03/) | O29: RemoteView 현장 대응 부담 절감,에 대해 알려주세요 | P29: RemoteView, 홈, 현장 대응 부담 절감, | Q29: RV-WEB-HOME-028 | R29: Claude(Fable5) | S29: 상 | T29: 미검토
A30: 29 | B30: RV-WEB-HOME-029 | C30: WebPage | D30: RemoteView 웹 홈 페이지 | E30: 리모트뷰의 다양한 소식을 | F30: RemoteView | G30: 리모트뷰의 다양한 소식을 | H30: 공통 | I30: 공개 | J30: 기능/제품 정보 확인 | K30: https://content.rview.com/ko/ | L30: 본문 § 리모트뷰의 다양한 소식을 | N30: 블로그로 만나보세요 인사이트 | O30: RemoteView 리모트뷰의 다양한 소식을에 대해 알려주세요 | P30: RemoteView, 홈, 리모트뷰의 다양한 소식을 | Q30: RV-WEB-HOME-029 | R30: Claude(Fable5) | S30: 하 | T30: 근거약함 | U30: 본문 25자 미만
A31: 30 | B31: RV-WEB-HOME-030 | C31: WebPage | D31: RemoteView 웹 홈 페이지 | E31: 13시간 주식 거래와 망분리 완화, 증권사 재택근무가 필수 인프라가 된 3가지 배경 | F31: RemoteView | G31: 13시간 주식 거래와 망분리 완화, 증권사 재택근무가 필수 인프라가 된 | H31: 공통 | I31: 공개 | J31: 기능/제품 정보 확인 | K31: https://content.rview.com/ko/ | L31: 본문 § 13시간 주식 거래와 망분리 완화, 증권사 재택근무가 필수 인프라가 된 | N31: ](https://content.rview.com/ko/blog/securities-firm-remote-work-compliance/) 활용팁 | O31: RemoteView 13시간 주식 거래와 망분리 완화, 증권사 재택근무가 에 대해 알려주세요 | P31: RemoteView, 홈, 13시간 주식 거래와 망분리 완화, | Q31: RV-WEB-HOME-030 | R31: Claude(Fable5) | S31: 상 | T31: 미검토
A32: 31 | B32: RV-WEB-HOME-031 | C32: WebPage | D32: RemoteView 웹 홈 페이지 | E32: 네이트온 원격제어: 리모트뷰를 찾는다면? 14일 무료 체험 및 퀵 사용 가이드 | F32: RemoteView | G32: 네이트온 원격제어: 리모트뷰를 찾는다면? 14일 무료 체험 및 퀵 사용 | H32: 공통 | I32: 공개 | J32: 기능/제품 정보 확인 | K32: https://content.rview.com/ko/ | L32: 본문 § 네이트온 원격제어: 리모트뷰를 찾는다면? 14일 무료 체험 및 퀵 사용 | N32: ](https://content.rview.com/ko/blog/nateon-remoteview-guide-and-free-trial/) 자료 | O32: RemoteView 네이트온 원격제어: 리모트뷰를 찾는다면? 14일 무료 에 대해 알려주세요 | P32: RemoteView, 홈, 네이트온 원격제어: 리모트뷰를 찾는다 | Q32: RV-WEB-HOME-031 | R32: Claude(Fable5) | S32: 상 | T32: 미검토
A33: 32 | B33: RV-WEB-HOME-032 | C33: WebPage | D33: RemoteView 웹 홈 페이지 | E33: RDP 원격 데스크톱 연결 및 VNC 사용법 완벽 가이드: | F33: RemoteView | G33: RDP 원격 데스크톱 연결 및 VNC 사용법 완벽 가이드: | H33: 공통 | I33: 공개 | J33: 기능/제품 정보 확인 | K33: https://content.rview.com/ko/ | L33: 본문 § RDP 원격 데스크톱 연결 및 VNC 사용법 완벽 가이드: | N33: 3389 포트 설정보다 중요한 실무 보안의 모든 것 ](https://content.rview.com/ko/blog/rdp-vnc-remote-desktop-security/) | O33: RemoteView RDP 원격 데스크톱 연결 및 VNC 사용법 완벽 가이에 대해 알려주세요 | P33: RemoteView, 홈, RDP 원격 데스크톱 연결 및 VNC | Q33: RV-WEB-HOME-032 | R33: Claude(Fable5) | S33: 상 | T33: 미검토
A34: 33 | B34: RV-WEB-HOME-033 | C34: WebPage | D34: RemoteView 웹 홈 페이지 | E34: 구독형 제품 | F34: RemoteView | G34: 구독형 제품 | H34: 공통 | I34: 공개 | J34: 기능/제품 정보 확인 | K34: https://content.rview.com/ko/ | L34: 본문 § 구독형 제품 | N34: 월 결제로 부담없이 시작 14일 무료체험으로 먼저 써보고, 도입 여부를 결정하세요. | O34: RemoteView 구독형 제품에 대해 알려주세요 | P34: RemoteView, 홈, 구독형 제품 | Q34: RV-WEB-HOME-033 | R34: Claude(Fable5) | S34: 중 | T34: 미검토
A35: 34 | B35: RV-WEB-HOME-034 | C35: WebPage | D35: RemoteView 웹 홈 페이지 | E35: 구축형 제품 | F35: RemoteView | G35: 구축형 제품 | H35: 공통 | I35: 공개 | J35: 기능/제품 정보 확인 | K35: https://content.rview.com/ko/ | L35: 본문 § 구축형 제품 | N35: 기업 환경에 맞춘 전용 시스템 구축 전문 컨설턴트가 환경에 맞는 구축 방법과 비용을 1:1로 안내해 드립니다. 브라우저가 video 태그를 지원하지 않습니다. | O35: RemoteView 구축형 제품에 대해 알려주세요 | P35: RemoteView, 홈, 구축형 제품 | Q35: RV-WEB-HOME-034 | R35: Claude(Fable5) | S35: 상 | T35: 미검토
A36: 35 | B36: RV-WEB-HOME-035 | C36: WebPage | D36: RemoteView 웹 홈 페이지 | E36: 업무에 도움이 되는 알짜레터를 받아보세요 | F36: RemoteView | G36: 업무에 도움이 되는 알짜레터를 받아보세요 | H36: 공통 | I36: 공개 | J36: 기능/제품 정보 확인 | K36: https://content.rview.com/ko/ | L36: 본문 § 업무에 도움이 되는 알짜레터를 받아보세요 | N36: \[필수\] 만 14세 이상이며, 개인정보 수집 및 이용에 동의합니다. \[선택\] 이벤트, 프로모션 등 마케팅 정보 수신에 동의합니다. 알짜레터 구독하기 개인정보 수집 및 이용 안내문 ∙ 수집하는 항목 : (필수)이메일 ∙ 수집 및 이용목적 : 알짜레터 발송 ∙ 보유 및 이용기간 : 구독해지 시 까지 - ※ 개인정보 수집 및 이용에 대한 동의를 거부할 권리가 있습니다. 그러나 동의를 거부할 경우, 알짜레터를 받아보실 수 없습니다. 닫기 마케팅 정보 수신 동의 안내문 - ※ 마케팅 정보 수신에 대한 동의를 거부할 수 있습니다. 그러나 동의하지 않을 경우 편의 제공 안내 등 이용 목적에 따른 혜택에 제한이 있을 수 있습니다. - ※ 마케팅 정보를 더 이상 받고 싶지 않으실 경우, 이메일 하단의 수신거부를 통해 철회요청 하시기 바랍니다. 닫기 Go to Top App DownLoad - Android App **알서포트(주)** 대표 : 서형수 주소 : (05203) 서울특별시 강동구 고덕비즈밸리로2가길 12 (고덕동) Windows® is a trademark of the Microsoft group of companies. iPhone® and iPad® are trademarks of Apple Inc., registered in the U.S. and other countries. Android™ is a trademark of Google Inc. © [RSUPPORT](https://www.rsupport.com/) CO., LTD. ALL RIGHTS RESERVED. [ 문의하기 ](https://help.rview.com/hc/ko/requests/new?ticket_form_id=360000030893)[ 시작가이드 ](/ko/support/tutorial/)[ 10분 체험 ](https://rview.com/ko/virtual_exp) | O36: RemoteView 업무에 도움이 되는 알짜레터를 받아보세요에 대해 알려주세요 | P36: RemoteView, 홈, 업무에 도움이 되는 알짜레터를 받아보 | Q36: RV-WEB-HOME-035 | R36: Claude(Fable5) | S36: 상 | T36: 미검토
A37: 36 | B37: RV-WEB-MISC-001 | C37: WebPage | D37: RemoteView 웹 B0편입 페이지 | E37: (도입부) | F37: RemoteView | G37: (도입부) | H37: 공통 | I37: 공개 | J37: 기능/제품 정보 확인 | K37: https://content.rview.com/ko/?p=13953 | L37: 본문 § (도입부) | N37: 리모트뷰 라이선스 구매 **구매를 위해 리모트뷰 로그인 페이지로 이동하세요.** 리모트뷰 계정으로 로그인하시면 즉시 라이선스 구매가 가능합니다. **리모트뷰 계정이 없으시다면? >** 지금 바로 [계정을 생성하고 2주간 무료로](/ko/trial/) 이용하세요!! **로그인전 리모트뷰 온라인 구매 가이드를 확인하세요!** 서비스 로그인 리모트뷰에 로그인 합니다. 리모트뷰 계정이 없다면, 가입하여 계정을 생성합니다. 결제 메뉴 클릭 서비스 페이지의 상단의 “결제” 메뉴로 이동합니다. 유료 전환 클릭 회원가입 시 발급된 데모 라이선스를 유료 전환합니다. 구매 정보 입력 후 결제 구매 기간/ 라이선스 종류/ PC수를 선택한 후 결제를 진행합니다. - ※상기의 구입 안내 절차는 표준 모드에서만 동작하는 화면입니다. - ※심플모드를 이용중인 분은 아래의 방법을 진행하신 후 표준화면으로 이동하여 위 2~4로 진행할 수 있습니다. 메뉴 아이콘 클릭 심플모드인 경우 메뉴아이콘을 클릭합니다. 메뉴\[환경설정\]을 선택 메뉴\[환경설정\]을 선택하여 환경설정페이지로 진입합니다. Go to Top App DownLoad - Android App **알서포트(주)** 대표 : 서형수 주소 : (05203) 서울특별시 강동구 고덕비즈밸리로2가길 12 (고덕동) Windows® is a trademark of the Microsoft group of companies. iPhone® and iPad® are trademarks of Apple Inc., registered in the U.S. and other countries. Android™ is a trademark of Google Inc. © [RSUPPORT](https://www.rsupport.com/) CO., LTD. ALL RIGHTS RESERVED. [ 문의하기 ](https://help.rview.com/hc/ko/requests/new?ticket_form_id=360000030893)[ 시작가이드 ](/ko/support/tutorial/)[ 10분 체험 ](https://rview.com/ko/virtual_exp) | O37: RemoteView (도입부)에 대해 알려주세요 | P37: RemoteView, B0편입, (도입부) | Q37: RV-WEB-MISC-001 | R37: Claude(Fable5) | S37: 상 | T37: 미검토
A38: 38 | B38: RV-WEB-CONTACT-001 | C38: WebPage | D38: RemoteView 웹 문의 페이지 | E38: (도입부) | F38: RemoteView | G38: (도입부) | H38: 공통 | I38: 공개 | J38: 기능/제품 정보 확인 | K38: https://content.rview.com/ko/contact/ | L38: 본문 § (도입부) | N38: 개인정보 수집/이용 안내문 ![](/wp-content/uploads/sites/2/image/sub/sms_close_icon.webp) 1. ∙ 수집하는 항목 : (필수)성명, 회사명, 휴대폰 번호, 이메일 2. ∙ 수집 및 이용목적 : 문의사항 확인 및 처리결과 회신 3. **∙ 보유 및 이용기간 : 문의 검토 완료 후, 1년간 보관** 1. **※ 개인정보 수집 및 이용에 대한 동의를 거부할 권리가 있습니다. 그러나 동의를 거부할 경우, 문의 등록을 하실 수 없습니다.** Go to Top App DownLoad - Android App **알서포트(주)** 대표 : 서형수 주소 : (05203) 서울특별시 강동구 고덕비즈밸리로2가길 12 (고덕동) Windows® is a trademark of the Microsoft group of companies. iPhone® and iPad® are trademarks of Apple Inc., registered in the U.S. and other countries. Android™ is a trademark of Google Inc. © [RSUPPORT](https://www.rsupport.com/) CO., LTD. ALL RIGHTS RESERVED. [ 문의하기 ](https://help.rview.com/hc/ko/requests/new?ticket_form_id=360000030893)[ 시작가이드 ](/ko/support/tutorial/)[ 10분 체험 ](https://rview.com/ko/virtual_exp) 개인정보 수집/이용 안내문 ![](/wp-content/uploads/sites/2/image/sub/sms_close_icon.webp) 1. ∙ 수집하는 항목 : (필수)성명, 회사명, 휴대폰 번호, 이메일 2. ∙ 수집 및 이용목적 : 문의사항 확인 및 처리결과 회신 3. **∙ 보유 및 이용기간 : 문의 검토 완료 후, 1년간 보관** 1. **※ 개인정보 수집 및 이용에 대한 동의를 거부할 권리가 있습니다. 그러나 동의를 거부할 경우, 문의 등록을 하실 수 없습니다.** Go to Top App DownLoad - Android App **알서포트(주)** 대표 : 서형수 주소 : (05203) 서울특별시 강동구 고덕비즈밸리로2가길 12 (고덕동) Windows® is a trademark of the Microsoft group of companies. iPhone® and iPad® are trademarks of Apple Inc., registered in the U.S. and other countries. Android™ is a trademark of Google Inc. © [RSUPPORT](https://www.rsupport.com/) CO., LTD. ALL RIGHTS RESERVED. [ 문의하기 ](https://help.rview.com/hc/ko/requests/new?ticket_form_id=360000030893)[ 시작가이드 ](/ko/support/tutorial/)[ 10분 체험 ](https://rview.com/ko/virtual_exp) | O38: RemoteView (도입부)에 대해 알려주세요 | P38: RemoteView, 문의, (도입부) | Q38: RV-WEB-CONTACT-001 | R38: Claude(Fable5) | S38: 상 | T38: 미검토
A39: 39 | B39: RV-WEB-FEAT-001 | C39: WebPage | D39: RemoteView 웹 기능 페이지 | E39: (도입부) | F39: RemoteView | G39: (도입부) | H39: 공통 | I39: 공개 | J39: 기능/제품 정보 확인 | K39: https://content.rview.com/ko/feature | L39: 본문 § (도입부) | N39: - 필요할 때마다, - 그 이상의 경험, 리모트뷰 ![리모트뷰의 모든 기능, 바로 써보세요](/wp-content/uploads/sites/2/image/sub/features_floating_icon.webp) 리모트뷰의 모든 기능, 바로 써보세요 다음에 - 보안 및 접근제어 - 원격제어 및 공유 - 운영 및 현황 관리 - 하드웨어 | O39: RemoteView (도입부)에 대해 알려주세요 | P39: RemoteView, 기능, (도입부) | Q39: RV-WEB-FEAT-001 | R39: Claude(Fable5) | S39: 상 | T39: 미검토
A40: 40 | B40: RV-WEB-FEAT-002 | C40: WebPage | D40: RemoteView 웹 기능 페이지 | E40: 원격 접속 환경을 안전하게 | F40: RemoteView | G40: 원격 접속 환경을 안전하게 | H40: 공통 | I40: 공개 | J40: 기능/제품 정보 확인 | K40: https://content.rview.com/ko/feature | L40: 본문 § 원격 접속 환경을 안전하게 | N40: 보호하고 권한을 체계적으로 관리할 수 있습니다 ![계정 및 접속 보안](/wp-content/uploads/sites/2/image/sub/feature_tit_icon04.webp)계정 및 접속 보안 | O40: RemoteView 원격 접속 환경을 안전하게에 대해 알려주세요 | P40: RemoteView, 기능, 원격 접속 환경을 안전하게 | Q40: RV-WEB-FEAT-002 | R40: Claude(Fable5) | S40: 상 | T40: 미검토
A41: 41 | B41: RV-WEB-FEAT-003 | C41: WebPage | D41: RemoteView 웹 기능 페이지 | E41: OTP 인증 가능 | F41: RemoteView | G41: OTP 인증 가능 | H41: 공통 | I41: 공개 | J41: 기능/제품 정보 확인 | K41: https://content.rview.com/ko/feature | L41: 본문 § OTP 인증 가능 | N41: 무작위로 생성되는 1회용 비밀번호(OTP)를 사용해 2단계 보안을 설정할 수 있습니다. 설정 후 사용자는 Google Authenticator 등 OTP 앱으로 인증키를 등록하고, 로그인 시 OTP 번호를 입력해 계정 보안을 강화합니다. | O41: RemoteView OTP 인증 가능에 대해 알려주세요 | P41: RemoteView, 기능, OTP 인증 가능 | Q41: RV-WEB-FEAT-003 | R41: Claude(Fable5) | S41: 상 | T41: 미검토
A42: 42 | B42: RV-WEB-FEAT-004 | C42: WebPage | D42: RemoteView 웹 기능 페이지 | E42: 해외 로그인(IP) 차단 설정 | F42: RemoteView | G42: 해외 로그인(IP) 차단 설정 | H42: 공통 | I42: 공개 | J42: 기능/제품 정보 확인 | K42: https://content.rview.com/ko/feature | L42: 본문 § 해외 로그인(IP) 차단 설정 | N42: 리모트뷰 계정을 생성한 국가 외 다른 국가에서의 로그인을 차단합니다. 외부 위협을 줄이고, 안전하게 원격 접속 환경을 관리할 수 있습니다. | O42: RemoteView 해외 로그인(IP) 차단 설정에 대해 알려주세요 | P42: RemoteView, 기능, 해외 로그인(IP) 차단 설정 | Q42: RV-WEB-FEAT-004 | R42: Claude(Fable5) | S42: 상 | T42: 미검토
... A82: 82 | B82: RV-WEB-FEAT-044 | C82: WebPage | D82: RemoteView 웹 기능 페이지 | E82: 어떤 안드로이드 기기도 > 에이전트 앱 | F82: RemoteView | G82: 어떤 안드로이드 기기도 > 에이전트 앱 | H82: 공통 | I82: 공개 | J82: 기능/제품 정보 확인 | K82: https://content.rview.com/ko/feature/android | L82: 본문 § 어떤 안드로이드 기기도 > 에이전트 앱 (2차) | N82: **에이전트 앱** ![구글플레이](/wp-content/uploads/sites/2/image/sub/controls_app_aos_icon.webp)구글플레이 화면 제어를 위한 플러그인 RSAssistant 모바일에서 안드로이드를 제어하기 위한 모바일 앱 모바일에서 안드로이드 제어를 위한 모바일 앱 ![구글플레이](/wp-content/uploads/sites/2/image/sub/controls_app_aos_icon.webp)구글플레이 ![앱스토어](/wp-content/uploads/sites/2/image/sub/controls_app_ios_icon.webp)앱스토어 산업별 담당자들의 진짜 후기 생산성과 효율을 높이기 위해, 지금 도입하세요! IT · 솔루션 ](/ko/uses/cases/?filter=it) 공공기관 ](/ko/uses/cases/?filter=public) 교육 · 문화 ](/ko/uses/cases/?filter=education) 금융 · 투자 ](/ko/uses/cases/?filter=financial) 무인기기 납품 ](/ko/uses/cases/?filter=equipment) 의료 ](/ko/uses/cases/?filter=medical) 제조 ](/ko/uses/cases/?filter=manufacture) 판매 · 서비스 ](/ko/uses/cases/?filter=sales) 30만 글로벌 기업이 선택한 원격제어 리모트뷰를 더 알고 싶으신가요? - 제품소개 - 전체기능 - 시작가이드 - 가상체험 개인정보 수집 및 이용 ![](/wp-content/uploads/sites/2/image/sub/sms_close_icon.webp) 1. ∙ 수집하는 항목 : (필수)성명, 회사명, 휴대폰 번호, 이메일 2. ∙ 수집 및 이용목적 : 문의사항 확인 및 처리결과 회신 3. ∙ 보유 및 이용기간 : 문의 검토 완료 후, 1년간 보관 1. **※ 개인정보 수집 및 이용에 대한 동의를 거부할 권리가 있습니다. 그러나 동의를 거부할 경우, 문의 등록을 하실 수 없습니다.** Go to Top App DownLoad - Android App **알서포트(주)** 대표 : 서형수 주소 : (05203) 서울특별시 강동구 고덕비즈밸리로2가길 12 (고덕동) Windows® is a trademark of the Microsoft group of companies. iPhone® and iPad® are trademarks of Apple Inc., registered in the U.S. and other countries. Android™ is a trademark of Google Inc. © [RSUPPORT](https://www.rsupport.com/) CO., LTD. ALL RIGHTS RESERVED. | O82: RemoteView 어떤 안드로이드 기기도 > 에이전트 앱에 대해 알려주세요 | P82: RemoteView, 기능, 어떤 안드로이드 기기도 > 에이전트 | Q82: RV-WEB-FEAT-044 | R82: Claude(Fable5) | S82: 상 | T82: 미검토
A83: 83 | B83: RV-WEB-FEAT-045 | C83: WebPage | D83: RemoteView 웹 기능 페이지 | E83: 용역업체 보안 관리, | F83: RemoteView | G83: 용역업체 보안 관리, | H83: 공통 | I83: 공개 | J83: 기능/제품 정보 확인 | K83: https://content.rview.com/ko/feature/control/ | L83: 본문 § 용역업체 보안 관리, | N83: 행정 효율까지 ‘AI 온라인 용역통제 시스템’으로 한 번에 국정원 가이드라인을 준수하고 AI 기반 지능형 관제로 보안 사각지대를 해소합니다. 전문가 상담받기 비교 자료 받기 ![온라인 용역통제 보안 기준을 확인하세요](/wp-content/uploads/sites/2/image/sub/controls_toast_icon_web.webp) 도입에 필요한 보안 기준을 확인해 보세요 다음에 도입 가이드 받기 ![arrow](/wp-content/uploads/sites/2/image/sub/controls_toast_mb.webp) 원격제어 1위, 알서포트가 만든 AI 온라인 용역통제 시스템은 믿을 수 있습니다 ISO/IEC 27001, ISO/IEC 27017 정보보안 국제인증 KISA 신속확인제 공공기관 정보보호제품 도입 보안성 검증 GS인증 1등급 한국정보통신기술협회 1등급 품질 인증 조달청 등록제품 국가정보원 국가정보보안기본 지침 준수 국가정보 KCMVP 국가·공공기관 도입 필수 암호모듈 안전성 확보 망 분리 환경에서 반복되는 외주 대응과 현장 방문 문제를 언제까지 감수하시겠습니까? 폐쇄망 환경의 업무 제약 보안을 위해 외부와 분리된 폐쇄망 환경에서도, 시스템 유지보수와 고도화를 위한 외부 인력 작업은 불가피합니다. 비효율적인 현장 출동 단순 유지보수나 장애 대응을 위해 반복되는 현장 출동은 시간과 예산 낭비로 이어집니다. 책임 소재 불분명에 따른 리스크 외부 인력 작업 중 보안 사고 발생 시, 작업 이력이 부족한 경우 담당자의 관리 책임이 문제될 수 있습니다. 원격 제어의 보안 사각지대 단순 유지보수나 장애 대응을 위해 반복되는 현장 출동은 시간과 예산 낭비로 이어집니다. prev next 리모트뷰 SE의 AI 온라인 용역통제로 망 분리 환경에서도 효율적인 외주 대응이 가능합니다 국가정보원 보안 감사 완벽 대응 국정원 보안 가이드라인을 모두 충족하는 기능으로, 도입 후 국가 기관의 정기적 보안 감사 시에도 문제없는 운영 환경을 제공합니다. 제로 트러스트 기반 보안 체계 인가 단말기·OTP 이중 검증, 승인된 자산에만 접속을 허용하는 권한 관리로 내부망 노출과 관리 사각지대를 원천적으로 차단합니다. 실시간 ‘CCTV급’ 작업 관제 외부 인력의 작업 화면을 실시간 라이브뷰로 감독하고, 이상 행위가 감지되면 즉시 접속을 차단할 수 있습니다. AI 지능형 행위 분석 및 리포트 AI가 원격 작업 이력을 분석해 관리자의 확인 부담을 줄입니다. 보안 위협이 의심되는 주요 장면을 포착하여 객관적인 보안 보고서를 생성합니다. 기관별 맞춤 보안 정책 적용으로 감사 대응 정확도와 행정 업무 효율성을 높입니다. 국내 유일 하드웨어 기반 원격 제어 RemoteViewBOX 거리와 기기의 제약 없이 자유로운 원격 작업 환경을 구축하세요. 복잡한 설정·설치없이 케이블만 연결하면, AI 온라인 용역통제로 외부 접속까지 안전하게 관리할 수 있습니다. 국정원의 엄격한 보안 기준을 완벽하게 구현하여 안심하고 사용할 수 있습니다 강력한 보안 통신 적용 국정원 검증필 암호모듈(KCMVP) 및 SSL VPN을 통해 공공기관 수준의 전송 보안을 보장합니다. AES/SSL 256bit 이중 암호화 통신 보안 통신을 전 구간에 이중으로 적용하여 데이터 가로채기 및 위변조 위험을 차단합니다. 인가 단말기 기반 제어 사전 등록된 IP/MAC 주소 식별과 OTP 2단계 인증을 거친 단말기만 접속을 허용합니다. 작업 전수 녹화 및 감사 모든 원격 작업 과정을 영상으로 기록하고, 위변조가 불가능한 로그를 1년 이상 보관합니다. - • 국가 정보보안 기본지침 제28조의2 (원격지에서의 온라인 개발) 준수 - • 전자금융감독규정 시행세칙 <별표7> 망분리 대체 정보보호통제 준수 알서포트 AI 온라인 용역통제 시스템과 타사 솔루션, 무엇이 다를까요? 알서포트 A사 H사 | 제어 | | --- | | 원격제어 중 모니터링 및 제어권 획득 | 가능 | 불가능 | 불가능 | | 창분리 멀티모니터 | 멀티 뷰어 지원 | 미지원 (개별 화면 전환 방식) | 미지원 (개별 화면 전환 방식) | | 보안 | | OS 장애 대응 | RemoteViewBOX로 BIOS/CMOS 진입 및 원격 부팅/전원 제어 가능 | 미지원 | 미지원 | | 상태 표시 | “원격제어 중” 표시 지원 | 지원 | 지원 | | 실시간 모니터링 | 라이브뷰(LiveView) 지원 | 미지원 | 미지원 | | 보안 인증 | ISO 27017/ISO 27001/ KISA 신속확인제/GS 1등급 국정원 검증필 암호화 | KISA 신속확인제/GS 1등급/ 국정원 검증필 암호화 | GS 1등급/보안 기능 확인서 | | 관리 | | 사용 신청/허가 절차 | 사용자가 관리자에게 신청 | 관리자가 사용자에게 호출 | 관리자가 사용자에게 호출 | 알서포트 AI 온라인 용역통제 시스템의 차별점을 상세 자료로 확인해 보세요. 비교 자료 받기 AI 온라인 용역통제 시스템은 안전은 기본, 사용자가 쉽고 편하게 쓸 수 있어야 합니다 사전 검증 및 권한 승인 외주 직원이 보안서약을 동의한 후 특정 일시와 대상을 신청하면, 보안 담당자가 검토 후 2단계 인증을 통해 일시적인 권한만 부여합니다. 실시간 모니터링 라이브뷰를 통해 모든 작업 과정을 5초 단위로 정밀 관제하며, 이상 행위 감지 시 즉시 세션을 강제 종료하여 사고를 예방합니다. 자동 기록 및 사후 추적 작업 종료와 동시에 로그와 녹화 파일을 기반으로 보안 결과 보고서를 자동 생성하여, 완벽한 감사 추적 환경을 제공합니다. 공공기관 운영 환경에서 이미 검증되었습니다 [![기상청](/wp-content/uploads/sites/2/image/sub/soc_ranking_review_01.webp) 공공기관 “전국 46개소 무인 관측장비의 실시간 장애 대응 체계를 구축하고 **리모트뷰박스 연동**으로 현장 출동 비용 72% 절감했어요”](/ko/cases/institution-04/) [![안동시](/wp-content/uploads/sites/2/image/sub/soc_ranking_review_02.webp) 공공기관 “기종에 상관없이 모든 CCTV 시스템을 원격 제어하고, **작업 이력**의 **100% 투명화**로 **보안 감사**를 무결점으로 **통과**했습니다.”](/ko/cases/institution-05/) - ![대한민국 국방부](/wp-content/uploads/sites/2/image/sub/soc_ranking_l p) - ![제천시](/wp-content/uploads/sites/2/image/sub/soc_ranking_log webp) 도입 전, 자주 묻는 질문을 확인하세요 - 타사 제품 대비 알서포트만의 하드웨어 제어 방식은 어떤 장점이 있나요? 알서포트는 소프트웨어 전용 방식의 경쟁사와 달리, **하드웨어(KVM)와 소프트웨어 이중화 제어를 지원합니다.** 리모트뷰박스를 도입하면 **OS를 넘어 BIOS·CMOS까지 원격으로 접근**할 수 있어, 일반 원격 솔루션으로는 불가능한 수준의 **장애 대응이 가능합니다**. - 원격 제어 중인 화면이 현장 PC에 그대로 노출되지는 않나요? 리모트뷰 SE는 강력한 원격지 화면 차단(Black Layer) 및 Lock 기능을 제공합니다. 모니터 전원 제어나 신호 차단 등 3가지 방식의 화면 잠금을 통해 현장에 있는 타인이 제어 내용을 절대 볼 수 없도록 물리적·소프트웨어적으로 완벽히 차단합니다. - 원격지 PC가 꺼져 있거나 전원이 차단된 경우에도 대응할 수 있나요? 리모트뷰박스에 내장된 기능으로 외부에서도 원격 부팅(WOL) 및 전원 제어가 가능합니다. 특히 하드웨어 제어 방식을 통해 PC가 꺼진 상태에서도 한 번의 클릭으로 전원을 켤 수 있어 업무 연속성을 완벽히 보장합니다. - 인가되지 않은 장소나 기기에서 관리자 페이지 접근을 차단할 수 있나요? 관리자 페이지 접속에 대한 IP 및 MAC 주소 제한 기능을 지원합니다. 허용된 특정 IP와 기기(MAC)에서만 관리자 권한을 행사할 수 있도록 이중 잠금 장치를 제공하여, 관리 계정 탈취나 외부 접근을 통한 보안 사고를 사전에 원천 봉쇄합니다. - 용역 인력이 다양한 OS를 사용하거나 멀티 모니터 환경이 필요한 경우에도 사용 가능한가요? 리모트뷰 SE는 Windows뿐만 아니라 macOS, iOS, Android 등 다수 OS를 완벽 지원하며, 모든 웹 브라우저에서 구동됩니다. 또한 멀티 뷰어 지원을 통한 창분리 멀티모니터 기능으로 실제 작업 환경과 동일한 듀얼 모니터 구성을 지원하여 업무 효율성을 극대화합니다. - AI 온라인 용역통제 시스템의 ‘AI 모니터링’은 기존 방식과 무엇이 다른가요? 기존에는 관리자가 녹화 영상을 일일이 돌려보며 직접 확인해야 했습니다. AI 모니터링은 원격 제어 종료 후 생성된 모든 작업 이력과 로그를 AI가 분석 하고, 보안 보고서까지 생성해 주므로 관리자의 확인 부담을 크게 줄여줍니다. 이를 통해 보안 감사에 필요한 증적 자료를 빠짐없이 확보하고, 관리 사각 지대를 해소할 수 있습니다. 단순 원격 프로그램으로는 국가 보안 기준을 충족할 수 없습니다 이제 보안 가이드라인에 최적화된 AI 온라인 용역통제 시스템 도입은 필수 단계입니다. 전문가 상담받기 비교 자료 받기 전문가 상담받기 공공기관 전문 컨설턴트가 최적의 온라인 용역통제 방안을 찾아드립니다. 비교 자료 다운받기 AI 온라인 용역통제 시스템 도입 전, 비교 자료를 통해 도입 환경을 진단해 보세요. 도입 가이드 다운받기 국가정보보안 기본지침의 심층 해석과 원격 보안 전략을 한눈에 확인해 보세요. 개인정보 수집 및 이용 ![](/wp-content/uploads/sites/2/image/sub/sms_close_icon.webp) 1. ∙ 수집하는 항목 : (필수)성명, 회사명, 휴대폰 번호, 이메일 2. ∙ 수집 및 이용목적 : 문의사항 확인 및 처리결과 회신 3. **∙ 보유 및 이용기간 : 문의 검토 완료 후, 1년간 보관** 1. **※ 개인정보 수집 및 이용에 대한 동의를 거부할 권리가 있습니다. 그러나 동의를 거부할 경우, 문의 등록을 하실 수 없습니다.** 개인정보 수집 및 이용 ![](/wp-content/uploads/sites/2/image/sub/sms_close_icon.webp) 1. ∙ 수집하는 항목 : (필수)성명, 회사명, 휴대폰 번호, 이메일 2. ∙ 수집 및 이용목적 : 알서포트 제품 소개서 발송, 제품·서비스 도입을 위한 영업 및 상담 활동, (마케팅 정보 수신 동의 시)알짜레터 소식 등 마케팅 정보 발송 3. **∙ 보유 및 이용기간 : 문의 검토 완료 후, 1년간 보관** 1. **※ 개인정보 수집 및 이용에 대한 동의를 거부할 권리가 있습니다. 그러나 동의를 거부할 경우, 자료를 다운받을 수 없습니다.** 마케팅 정보 수신 동의 안내문 ![](/wp-content/uploads/sites/2/image/sub/sms_close_icon.webp) 1. **※ 마케팅 정보 수신에 대한 동의를 거부할 수 있습니다. 단, 동의하지 않을 경우 편의 제공 안내 등 이용 목적에 따른 혜택에 제한이 있을 수 있습니다.** Go to Top App DownLoad - Android App **알서포트(주)** 대표 : 서형수 주소 : (05203) 서울특별시 강동구 고덕비즈밸리로2가길 12 (고덕동) Windows® is a trademark of the Microsoft group of companies. iPhone® and iPad® are trademarks of Apple Inc., registered in the U.S. and other countries. Android™ is a trademark of Google Inc. © [RSUPPORT](https://www.rsupport.com/) CO., LTD. ALL RIGHTS RESERVED. [ 문의하기 ](https://help.rview.com/hc/ko/requests/new?ticket_form_id=360000030893)[ 시작가이드 ](/ko/support/tutorial/)[ 10분 체험 ](https://rview.com/ko/virtual_exp) | O83: RemoteView 용역업체 보안 관리,에 대해 알려주세요 | P83: RemoteView, 기능, 용역업체 보안 관리, | Q83: RV-WEB-FEAT-045 | R83: Claude(Fable5) | S83: 하 | T83: 사람확인 | U83: 복합 내용 의심(장문 마케팅 섹션) — 재절단 검토 필요
A84: 84 | B84: RV-WEB-FEAT-046 | C84: WebPage | D84: RemoteView 웹 기능 페이지 | E84: 기업의 원격제어와 개인의 원격제어 | F84: RemoteView | G84: 기업의 원격제어와 개인의 원격제어 | H84: 공통 | I84: 공개 | J84: 기능/제품 정보 확인 | K84: https://content.rview.com/ko/feature/management | L84: 본문 § 기업의 원격제어와 개인의 원격제어 | N84: 무엇이 달라야 할까요? 재택근무 관리 등, 기업에서의 원격제어는 제공기능부터 달라야 합니다. 리모트뷰가 제공하는 관리자용 기능을 확인해보세요! | O84: RemoteView 기업의 원격제어와 개인의 원격제어에 대해 알려주세요 | P84: RemoteView, 기능, 기업의 원격제어와 개인의 원격제어 | Q84: RV-WEB-FEAT-046 | R84: Claude(Fable5) | S84: 상 | T84: 미검토
A85: 85 | B85: RV-WEB-FEAT-047 | C85: WebPage | D85: RemoteView 웹 기능 페이지 | E85: 재택근무 관리자를 위한 리모트뷰의 핵심기능 | F85: RemoteView | G85: 재택근무 관리자를 위한 리모트뷰의 핵심기능 | H85: 공통 | I85: 공개 | J85: 기능/제품 정보 확인 | K85: https://content.rview.com/ko/feature/management | L85: 본문 § 재택근무 관리자를 위한 리모트뷰의 핵심기능 | N85: PC·사용자 그룹관리 사용자 일괄 등록 사용자 권한 설정 프로세스, 서비스 제한 원격제어 사용 알림 설정 연결가능 시간 설정 | O85: RemoteView 재택근무 관리자를 위한 리모트뷰의 핵심기능에 대해 알려주세요 | P85: RemoteView, 기능, 재택근무 관리자를 위한 리모트뷰의 핵 | Q85: RV-WEB-FEAT-047 | R85: Claude(Fable5) | S85: 상 | T85: 미검토
A86: 86 | B86: RV-WEB-FEAT-048 | C86: WebPage | D86: RemoteView 웹 기능 페이지 | E86: 제어할 PC나 사용자들을 용도나 | F86: RemoteView | G86: 제어할 PC나 사용자들을 용도나 | H86: 공통 | I86: 공개 | J86: 기능/제품 정보 확인 | K86: https://content.rview.com/ko/feature/management | L86: 본문 § 제어할 PC나 사용자들을 용도나 | N86: 부서 별로 관리하는 기능이 있나요? 리모트뷰는 제어할 PC나 사용자들을 그룹으로 관리할 수 있는 기능을 제공합니다. 그룹관리 기능은 PC 또는 사용자들을 그룹(폴더)으로 묶어 지정된 사용자만 접근/ 제어할 수 있도록 설정하거나 그룹의 관리자 권한을 지정할 수있습니다. | O86: RemoteView 제어할 PC나 사용자들을 용도나에 대해 알려주세요 | P86: RemoteView, 기능, 제어할 PC나 사용자들을 용도나 | Q86: RV-WEB-FEAT-048 | R86: Claude(Fable5) | S86: 상 | T86: 미검토
A87: 87 | B87: RV-WEB-FEAT-049 | C87: WebPage | D87: RemoteView 웹 기능 페이지 | E87: 재택근무를 위해 1,000명이 넘는 | F87: RemoteView | G87: 재택근무를 위해 1,000명이 넘는 | H87: 공통 | I87: 공개 | J87: 기능/제품 정보 확인 | K87: https://content.rview.com/ko/feature/management | L87: 본문 § 재택근무를 위해 1,000명이 넘는 | N87: 인원을 한번에 등록하는 기능이 있나요? 리모트뷰는 원격 PC에 접근 할 수 있는 개인 사용자를 추가하거나 삭제하는 기능을 제공하며 엑셀 양식을 다운 받아 대규모의 사용자 정보를 입력하여 일괄적으로 등록하는 기능도 함께 제공합니다. | O87: RemoteView 재택근무를 위해 1,000명이 넘는에 대해 알려주세요 | P87: RemoteView, 기능, 재택근무를 위해 1,000명이 넘는 | Q87: RV-WEB-FEAT-049 | R87: Claude(Fable5) | S87: 상 | T87: 미검토
A88: 88 | B88: RV-WEB-FEAT-050 | C88: WebPage | D88: RemoteView 웹 기능 페이지 | E88: 사용자에 따라 제어할 PC의 | F88: RemoteView | G88: 사용자에 따라 제어할 PC의 | H88: 공통 | I88: 공개 | J88: 기능/제품 정보 확인 | K88: https://content.rview.com/ko/feature/management | L88: 본문 § 사용자에 따라 제어할 PC의 | N88: 사용 권한을 다르게 설정할 수 있나요? 사용자에 따라 제어할 PC의 사용 권한 (원격제어, 캡쳐, 프린트, 녹화, 파일 송수신, 클립보드 기능 등)을 허용하거나 차단할 수 있습니다. | O88: RemoteView 사용자에 따라 제어할 PC의에 대해 알려주세요 | P88: RemoteView, 기능, 사용자에 따라 제어할 PC의 | Q88: RV-WEB-FEAT-050 | R88: Claude(Fable5) | S88: 상 | T88: 미검토
A89: 89 | B89: RV-WEB-FEAT-051 | C89: WebPage | D89: RemoteView 웹 기능 페이지 | E89: 원격지 PC의 프로세스나 | F89: RemoteView | G89: 원격지 PC의 프로세스나 | H89: 공통 | I89: 공개 | J89: 기능/제품 정보 확인 | K89: https://content.rview.com/ko/feature/management | L89: 본문 § 원격지 PC의 프로세스나 | N89: 서비스 실행의 제한을 설정할 수 있나요? 리모트뷰는 사용자가 원격지 PC에서 특정 프로세스(exe)나 서비스를 실행하는 것을 제한하여, 재택근무 중에도 보안성을 유지할 수 있습니다. [프로세스 중지 설정](https://help.rview.com/hc/ko/articles/360047252074) [서비스 중지 설정](https://help.rview.com/hc/ko/articles/360047899454) | O89: RemoteView 원격지 PC의 프로세스나에 대해 알려주세요 | P89: RemoteView, 기능, 원격지 PC의 프로세스나 | Q89: RV-WEB-FEAT-051 | R89: Claude(Fable5) | S89: 상 | T89: 미검토
A90: 90 | B90: RV-WEB-FEAT-052 | C90: WebPage | D90: RemoteView 웹 기능 페이지 | E90: 사용자의 활동이나 보안 이벤트 | F90: RemoteView | G90: 사용자의 활동이나 보안 이벤트 | H90: 공통 | I90: 공개 | J90: 기능/제품 정보 확인 | K90: https://content.rview.com/ko/feature/management | L90: 본문 § 사용자의 활동이나 보안 이벤트 | N90: 발생 시, 관리자가 확인할 수 있나요? 리모트뷰는 사용자의 활동 및 보안 이벤트 발생 시, 관리자가 메일로 확인할 수 있도록 보안알림 메일기능을 제공합니다. 계정관리자의 설정에 따라 해외IP로그인이나 원격제어 사용시작, 비밀번호 변경, Agent 삭제 시 알림메일을 발송합니다. | O90: RemoteView 사용자의 활동이나 보안 이벤트에 대해 알려주세요 | P90: RemoteView, 기능, 사용자의 활동이나 보안 이벤트 | Q90: RV-WEB-FEAT-052 | R90: Claude(Fable5) | S90: 상 | T90: 미검토
A91: 91 | B91: RV-WEB-FEAT-053 | C91: WebPage | D91: RemoteView 웹 기능 페이지 | E91: 원격PC의 접근 가능 | F91: RemoteView | G91: 원격PC의 접근 가능 | H91: 공통 | I91: 공개 | J91: 기능/제품 정보 확인 | K91: https://content.rview.com/ko/feature/management | L91: 본문 § 원격PC의 접근 가능 | N91: 시간을 다르게 설정 할 수 있나요? 리모트뷰는 관리자의 관리 편의성을 위해 요일별로 사용자가 원격지 PC에 접근할 수 있는 접속시간을 설정할 수 있는 기능을 제공하고 있으며 사용자의 계정별로 연결 가능시간 설정을 예외시킬 수도 있습니다. [ 원격제어 시 보안이 걱정되시나요? 안심하고 원격제어할 수 있는 리모트뷰의 보안 기능을 확인해 보세요. ](/ko/feature/security) Go to Top App DownLoad - Android App **알서포트(주)** 대표 : 서형수 주소 : (05203) 서울특별시 강동구 고덕비즈밸리로2가길 12 (고덕동) Windows® is a trademark of the Microsoft group of companies. iPhone® and iPad® are trademarks of Apple Inc., registered in the U.S. and other countries. Android™ is a trademark of Google Inc. © [RSUPPORT](https://www.rsupport.com/) CO., LTD. ALL RIGHTS RESERVED. [ 문의하기 ](https://help.rview.com/hc/ko/requests/new?ticket_form_id=360000030893)[ 시작가이드 ](/ko/support/tutorial/)[ 10분 체험 ](https://rview.com/ko/virtual_exp) | O91: RemoteView 원격PC의 접근 가능에 대해 알려주세요 | P91: RemoteView, 기능, 원격PC의 접근 가능 | Q91: RV-WEB-FEAT-053 | R91: Claude(Fable5) | S91: 상 | T91: 미검토
A92: 92 | B92: RV-WEB-FEAT-054 | C92: WebPage | D92: RemoteView 웹 기능 페이지 | E92: 어디서든 필요할 때 | F92: RemoteView | G92: 어디서든 필요할 때 | H92: 공통 | I92: 공개 | J92: 기능/제품 정보 확인 | K92: https://content.rview.com/ko/feature/mobile | L92: 본문 § 어디서든 필요할 때 | N92: 리모트뷰 모바일 원격제어 스마트폰으로 PC를 제어하는 리모트뷰 모바일 원격제어를 지금 체험해보세요. ![](/wp-content/uploads/sites/2/image/sub/controls_toast_icon.webp) 리모트뷰, 무엇이든 물어보세요 다음에 시간과 공간 제약없이 일이 되게 하는 기능, 모바일 원격제어 내 PC를 어디서나 휴대폰으로 제어 “리모트뷰만 있으면 **내 PC**를 **휴대폰으로 제어**할 수 있어 정말 편리해요. 긴 연휴 중에도 **휴대폰으로 원 격 제어**가 가능해 안심이에요.” K 법무법인 팀장 회사에 있는 노트북을 휴대폰으로 제어 “퇴근 후 **급한 업무**도 **휴대폰으로 바로 처리**할 수 있어 좋아요. **버스 안**에서 리모트뷰로 **회사 PC를 제어**해 간편하게 끝냈죠. **맥북도 문제없이 제어**되어 정말 만족해요.” D 솔루션 매니저 태블릿으로도 그래픽·영상 작업을 끊김 없이 “리모트뷰는 **고해상도**를 **지원**하는데다 빨라서, 태블릿으로도 **외부에서 원활**하게 작업할 수 있어요.” G 에이전시 PD 관리 시스템 장애, 휴대폰으로 즉시 대응 “갑자기 **장애가 발생**해도 간단한 문제는 **휴대폰**으로 관리 시스템에 접속해 **바로 처리**할 수 있어요.” A 인프라서비스 개발자 리모트뷰의 강력한 모바일 제어 기능을 경험해 보세요 가상 마우스 · 터치 모두 지원 모바일에서도 가상 마우스로 정밀하게 조작하거나 터치 제스처로 스크롤·우클릭 등의 동작을 빠르게 컨트롤할 수 있어요. 퀵 메뉴 설정 자주쓰는 프로그램을 퀵메뉴로 추가하여 바로 실행할 수 있어요. 단축키 선택 자주쓰는 키보드 단축키를 메뉴에서 선택해 간편하게 쓸 수 있어요. 특수 키 선택 스마트폰에서 사용하지 못하는 PC 키보드의 특수키들을 터치로 간편하게 사용 가능해요. 안드로이드 기기 원격제어도 궁금하신가요? 스마트폰이나 PC로 편리하게 다양한 안드로이드 기기를 원격제어 해보세요. 브라우저가 video 태그를 지원하지 않습니다. 3분만에 세팅 완료! 지금 시작 하세요 1 2 3 리모트뷰 무료체험 신청 리모트뷰 계정을 생성하고 14일 무료체험을 시작해 보세요. 제어 받을 PC 준비 제어 받을 PC는 리모트뷰 에이전트를 설치해 주세요. 모바일 앱 설치 후, 원격제어 시작 모바일에서 리모트뷰 앱을 설치하고, 로그인하면 바로 원격제어할 수 있어요. 리모트뷰 모바일 앱으로 신속하고 간편하게 제어하세요. 모바일 제어의 완벽한 파트너 리모트뷰 모바일 앱 모바일 원격제어를 위한 리모트뷰 모바일 앱 ![](/wp-content/uploads/sites/2/image/sub/controls_app_aos_icon.webp)구글플레이 ![](/wp-content/uploads/sites/2/image/sub/controls_app_ios_icon.webp)앱스토어 30만 글로벌 기업이 선택한 원격제어 리모트뷰를 더 알고 싶으신가요? - 제품소개 - 전체기능 - 시작가이드 - 가상체험 개인정보 수집 및 이용 ![](/wp-content/uploads/sites/2/image/sub/sms_close_icon.webp) 1. ∙ 수집하는 항목 : (필수)성명, 회사명, 휴대폰 번호, 이메일 2. ∙ 수집 및 이용목적 : 문의사항 확인 및 처리결과 회신 3. ∙ 보유 및 이용기간 : 문의 검토 완료 후, 1년간 보관 1. **※ 개인정보 수집 및 이용에 대한 동의를 거부할 권리가 있습니다. 그러나 동의를 거부할 경우, 문의 등록을 하실 수 없습니다.** Go to Top App DownLoad - Android App **알서포트(주)** 대표 : 서형수 주소 : (05203) 서울특별시 강동구 고덕비즈밸리로2가길 12 (고덕동) Windows® is a trademark of the Microsoft group of companies. iPhone® and iPad® are trademarks of Apple Inc., registered in the U.S. and other countries. Android™ is a trademark of Google Inc. © [RSUPPORT](https://www.rsupport.com/) CO., LTD. ALL RIGHTS RESERVED. | O92: RemoteView 어디서든 필요할 때에 대해 알려주세요 | P92: RemoteView, 기능, 어디서든 필요할 때 | Q92: RV-WEB-FEAT-054 | R92: Claude(Fable5) | S92: 하 | T92: 사람확인 | U92: 복합 내용 의심(장문 마케팅 섹션) — 재절단 검토 필요
A93: 93 | B93: RV-WEB-FEAT-055 | C93: WebPage | D93: RemoteView 웹 기능 페이지 | E93: 원격지 화면 잠금 기능으로 원격 작업중에 | F93: RemoteView | G93: 원격지 화면 잠금 기능으로 원격 작업중에 | H93: 공통 | I93: 공개 | J93: 기능/제품 정보 확인 | K93: https://content.rview.com/ko/feature/monitor-lock/ | L93: 본문 § 원격지 화면 잠금 기능으로 원격 작업중에 | N93: 원격지 PC 화면을 보호하세요. 원격지 화면 잠금 기능을 사용하면 제어중인 원격지 컴퓨터 화면을 가려 다른 사용자에게 중요한 정보가 노출되는 것을 미연에 방지할 수 있습니다 | O93: RemoteView 원격지 화면 잠금 기능으로 원격 작업중에에 대해 알려주세요 | P93: RemoteView, 기능, 원격지 화면 잠금 기능으로 원격 작업 | Q93: RV-WEB-FEAT-055 | R93: Claude(Fable5) | S93: 상 | T93: 미검토
A94: 94 | B94: RV-WEB-FEAT-056 | C94: WebPage | D94: RemoteView 웹 기능 페이지 | E94: 원격지 화면 잠금은 3가지 방식으로 | F94: RemoteView | G94: 원격지 화면 잠금은 3가지 방식으로 | H94: 공통 | I94: 공개 | J94: 기능/제품 정보 확인 | K94: https://content.rview.com/ko/feature/monitor-lock/ | L94: 본문 § 원격지 화면 잠금은 3가지 방식으로 | N94: 원격지 PC 화면을 보호할 수 있습니다.** 모니터 전원 제어 방식 전원을 Off하여 화면잠금 Black Layer 방식 S/W로 화면을 덮어 화면잠금 모니터 신호 차단 방식 신호를 차단하여 화면잠금 * * * | O94: RemoteView 원격지 화면 잠금은 3가지 방식으로에 대해 알려주세요 | P94: RemoteView, 기능, 원격지 화면 잠금은 3가지 방식으로 | Q94: RV-WEB-FEAT-056 | R94: Claude(Fable5) | S94: 상 | T94: 미검토
A95: 95 | B95: RV-WEB-FEAT-057 | C95: WebPage | D95: RemoteView 웹 기능 페이지 | E95: NEW | F95: RemoteView | G95: NEW | H95: 공통 | I95: 공개 | J95: 기능/제품 정보 확인 | K95: https://content.rview.com/ko/feature/monitor-lock/ | L95: 본문 § NEW | N95: 모니터 전원 제어 방식 ‘모니터 전원 제어 방식’이란? Rsupport Remoteview Agent로 모니터 전원을 제어하여 모니터 화면을 잠그는 방식 1. Rsupport RemoteView Agent 2. 모니터 파워컨트롤 3. ![리모트뷰 모니터 전원 직접 제어 파워컨트롤](/wp-content/uploads/sites/2/image/sub/img_lock04.png) * * * | O95: RemoteView NEW에 대해 알려주세요 | P95: RemoteView, 기능, NEW | Q95: RV-WEB-FEAT-057 | R95: Claude(Fable5) | S95: 상 | T95: 미검토
A96: 96 | B96: RV-WEB-FEAT-058 | C96: WebPage | D96: RemoteView 웹 기능 페이지 | E96: NEW | F96: RemoteView | G96: NEW | H96: 공통 | I96: 공개 | J96: 기능/제품 정보 확인 | K96: https://content.rview.com/ko/feature/monitor-lock/ | L96: 본문 § NEW (2차) | N96: Black Layer 방식 ‘Black Layer 방식’이란? Rsupport RemoteView Agent로 모니터 화면 위에 Black Layer를 덮어 모니터 화면을 잠그는 방식 1. Rsupport RemoteView Agent 2. Black Layer 실행 3. ![리모트뷰 화면 노출 방지 Black Layer 기능](/wp-content/uploads/sites/2/image/sub/img_lock05.png) * * * | O96: RemoteView NEW에 대해 알려주세요 | P96: RemoteView, 기능, NEW | Q96: RV-WEB-FEAT-058 | R96: Claude(Fable5) | S96: 상 | T96: 미검토
A97: 97 | B97: RV-WEB-FEAT-059 | C97: WebPage | D97: RemoteView 웹 기능 페이지 | E97: 모니터 신호 차단 방식 | F97: RemoteView | G97: 모니터 신호 차단 방식 | H97: 공통 | I97: 공개 | J97: 기능/제품 정보 확인 | K97: https://content.rview.com/ko/feature/monitor-lock/ | L97: 본문 § 모니터 신호 차단 방식 | N97: ‘모니터 신호 차단 방식’이란? Rsupport Monitor Driver로 모니터로 들어가는 신호를 차단하여 모니터 화면을 잠그는 방식 1. Video Driver 2. Rsupport Monitor Driver 3. 모니터 신호 차단 4. ![리모트뷰 신호 차단 방식 모니터 화면잠금](/wp-content/uploads/image/sub/img_lock07.png) * * * | O97: RemoteView 모니터 신호 차단 방식에 대해 알려주세요 | P97: RemoteView, 기능, 모니터 신호 차단 방식 | Q97: RV-WEB-FEAT-059 | R97: Claude(Fable5) | S97: 상 | T97: 미검토
A98: 98 | B98: RV-WEB-FEAT-060 | C98: WebPage | D98: RemoteView 웹 기능 페이지 | E98: 모니터 화면잠금 방식 설정 마법사로 | F98: RemoteView | G98: 모니터 화면잠금 방식 설정 마법사로 | H98: 공통 | I98: 공개 | J98: 기능/제품 정보 확인 | K98: https://content.rview.com/ko/feature/monitor-lock/ | L98: 본문 § 모니터 화면잠금 방식 설정 마법사로 | N98: 간편하게 잠금 방법을 설정하세요 | O98: RemoteView 모니터 화면잠금 방식 설정 마법사로에 대해 알려주세요 | P98: RemoteView, 기능, 모니터 화면잠금 방식 설정 마법사로 | Q98: RV-WEB-FEAT-060 | R98: Claude(Fable5) | S98: 하 | T98: 근거약함 | U98: 본문 25자 미만
A99: 99 | B99: RV-WEB-FEAT-061 | C99: WebPage | D99: RemoteView 웹 기능 페이지 | E99: Step 01화면잠금 방식 설정하기 | F99: RemoteView | G99: Step 01화면잠금 방식 설정하기 | H99: 공통 | I99: 공개 | J99: 기능/제품 정보 확인 | K99: https://content.rview.com/ko/feature/monitor-lock/ | L99: 본문 § Step 01화면잠금 방식 설정하기 | N99: **환경설정 변경 시** RemoteView Agent 시스템 트레이 아이콘(일반적으로 화면 오른쪽 하단의 시계 옆에 있음) 을 마우스 오른쪽 버튼을 클릭하고, 환경설정 -> 보안설정 -> 화면잠금 설정변경을 클릭 실행하여 이 기능을 사용하도록 설정합니다. 화면잠금 방식 설정 마법사 진단 테스트 후 적용합니다. **에이전트 설치 시** 에이전트 설치 마지막 단계에서 화면 잠금 방법을 설정합니다. 화면잠금방식 설정 마법사 진단 테스트 후 적용합니다. * * * | O99: RemoteView Step 01화면잠금 방식 설정하기에 대해 알려주세요 | P99: RemoteView, 기능, Step 01화면잠금 방식 설정하기 | Q99: RV-WEB-FEAT-061 | R99: Claude(Fable5) | S99: 상 | T99: 미검토
A100: 100 | B100: RV-WEB-FEAT-062 | C100: WebPage | D100: RemoteView 웹 기능 페이지 | E100: Step 02화면잠금방식 설정 마법사로 적용하기 | F100: RemoteView | G100: Step 02화면잠금방식 설정 마법사로 적용하기 | H100: 공통 | I100: 공개 | J100: 기능/제품 정보 확인 | K100: https://content.rview.com/ko/feature/monitor-lock/ | L100: 본문 § Step 02화면잠금방식 설정 마법사로 적용하기 | N100: [ 더 많은 기능이 궁금하시나요? 리모트뷰가 제공하는 다양하고 유용한 기능들을 확인해 보세요. ](/ko/feature/) Go to Top App DownLoad - Android App **알서포트(주)** 대표 : 서형수 주소 : (05203) 서울특별시 강동구 고덕비즈밸리로2가길 12 (고덕동) Windows® is a trademark of the Microsoft group of companies. iPhone® and iPad® are trademarks of Apple Inc., registered in the U.S. and other countries. Android™ is a trademark of Google Inc. © [RSUPPORT](https://www.rsupport.com/) CO., LTD. ALL RIGHTS RESERVED. [ 문의하기 ](https://help.rview.com/hc/ko/requests/new?ticket_form_id=360000030893)[ 시작가이드 ](/ko/support/tutorial/)[ 10분 체험 ](https://rview.com/ko/virtual_exp) | O100: RemoteView Step 02화면잠금방식 설정 마법사로 적용하기에 대해 알려주세요 | P100: RemoteView, 기능, Step 02화면잠금방식 설정 마법사 | Q100: RV-WEB-FEAT-062 | R100: Claude(Fable5) | S100: 상 | T100: 미검토
A101: 101 | B101: RV-WEB-FEAT-063 | C101: WebPage | D101: RemoteView 웹 기능 페이지 | E101: 1분 만에 모여 한번에 해결 | F101: RemoteView | G101: 1분 만에 모여 한번에 해결 | H101: 공통 | I101: 공개 | J101: 기능/제품 정보 확인 | K101: https://content.rview.com/ko/feature/multiple-access | L101: 본문 § 1분 만에 모여 한번에 해결 | N101: 리모트뷰 다중 접속 여러 사용자가 한 PC에 동시 접속! 지연 없는 협업으로 복잡한 문제도 단번에 해결하세요. 다중 접속 기능으로 협업 효율을 높이세요 최대 5명 동시 접속으로, 한자리에 모이지 않아도 문제 해결 팀원들은 각자의 자리에서 즉시 원격으로 접속해 문제를 함께 해결하고, 효율적으로 협업할 수 있습니다. 여러명이 동시에 접속해도 혼선 없이 제어 가능 호스트는 제어가 필요한 접속자에게 언제든지 제어권을 부여하고 관리할 수 있어, 모든 접속자가 문제 해결에 온전히 집중할 수 있습니다. 협업 중 추가로 필요한 인원이 있다면 이메일로 즉시 초대 호스트는 접속자 목록을 실시간으로 확인하고, 필요한 인원을 이메일로 즉시 초대해 함께 협업할 수 있습니다. 다중 접속 기능, 이렇게 활용하세요 IT 관리자 복잡한 시스템 장애 발생 시, 여러 분야의 전문가들이 하나의 PC에 동시 접속해 문제를 진단하고 해결합니다. 디자인 및 엔지니어링 팀 고성능 워크스테이션의 전문 솔루션 (CAD, 3D 프로그램 등)을 여러 팀원이 함께 보며 즉각적인 피드백을 주고 받습니다. 금융 및 보안 담당자 보안이 중요한 시스템에 여러 담당자가 동시 접속하여 실시간으로 상황을 감시하고 위협에 공동 대응합니다. 3분만에 세팅 완료! 지금 시작 하세요 1 2 3 리모트뷰 무료체험 신청 리모트뷰 계정을 생성하고 14일 무료체험을 시작해 보세요. 리모트뷰 로그인 후 다중 접속 설정 환경설정 ![](/wp-content/uploads/sites/2/image/sub/multiple_setting_arrow.webp) 대표 옵션 설정에서 다중 접속 사용을 활성화하면 바로 준비가 완료됩니다. ※ 다중 접속 기능은 Windows 에이전트가 설치된 PC에 Windows 뷰어로 접속 시에만 사용 가능합니다. 원격 PC 접속하면, 원격제어 시작 뷰어로 원격 PC에 접속하면, 원격제어는 물론 다중 접속 기능도 함께 이용할 수 있습니다. 다른 제품과 차이를 확인하세요 리모트뷰는 최대 5명까지 동시에 접속할 수 있어, 2~3명으로는 부족했던 복잡한 상황에도 유연하게 대응합 니다. 또한 호스트 중심의 제어권 관리 방식을 적용해, 여러 명이 함께 작업할 때 생길 수 있는 혼선을 막고 안정적인 협업 환경을 보장합니다. 다중 접속 지원 동시 접속 인원 최대 5명 최대 3명 Corporate 요금제 기준이며, 세부 조건에 따라 달라질 수 있습니다. 최대 2명 – \* 팀뷰어는 Corporate 요금제 기준이며, 세부 조건에 따라 달라질 수 있습니다. 개인정보 수집 및 이용 ![](/wp-content/uploads/sites/2/image/sub/sms_close_icon.webp) 1. ∙ 수집하는 항목 : (필수)성명, 회사명, 휴대폰 번호, 이메일 2. ∙ 수집 및 이용목적 : 문의사항 확인 및 처리결과 회신 3. ∙ 보유 및 이용기간 : 문의 검토 완료 후, 1년간 보관 1. **※ 개인정보 수집 및 이용에 대한 동의를 거부할 권리가 있습니다. 그러나 동의를 거부할 경우, 문의 등록을 하실 수 없습니다.** Go to Top App DownLoad - Android App **알서포트(주)** 대표 : 서형수 주소 : (05203) 서울특별시 강동구 고덕비즈밸리로2가길 12 (고덕동) Windows® is a trademark of the Microsoft group of companies. iPhone® and iPad® are trademarks of Apple Inc., registered in the U.S. and other countries. Android™ is a trademark of Google Inc. © [RSUPPORT](https://www.rsupport.com/) CO., LTD. ALL RIGHTS RESERVED. [ 문의하기 ](https://help.rview.com/hc/ko/requests/new?ticket_form_id=360000030893)[ 시작가이드 ](/ko/support/tutorial/)[ 10분 체험 ](https://rview.com/ko/virtual_exp) | O101: RemoteView 1분 만에 모여 한번에 해결에 대해 알려주세요 | P101: RemoteView, 기능, 1분 만에 모여 한번에 해결 | Q101: RV-WEB-FEAT-063 | R101: Claude(Fable5) | S101: 하 | T101: 사람확인 | U101: 복합 내용 의심(장문 마케팅 섹션) — 재절단 검토 필요
A102: 102 | B102: RV-WEB-FEAT-064 | C102: WebPage | D102: RemoteView 웹 기능 페이지 | E102: 멀티 / 듀얼모니터 제어 | F102: RemoteView | G102: 멀티 / 듀얼모니터 제어 | H102: 공통 | I102: 공개 | J102: 기능/제품 정보 확인 | K102: https://content.rview.com/ko/feature/multiple-monitors/ | L102: 본문 § 멀티 / 듀얼모니터 제어 | N102: 듀얼모니터 원격제어를 위한 최적의 솔루션, 역시 리모트뷰입니다. 여러 대의 모니터를 쉽고 간편하게 제어할 수 있습니다. | O102: RemoteView 멀티 / 듀얼모니터 제어에 대해 알려주세요 | P102: RemoteView, 기능, 멀티 / 듀얼모니터 제어 | Q102: RV-WEB-FEAT-064 | R102: Claude(Fable5) | S102: 상 | T102: 미검토
A103: 103 | B103: RV-WEB-FEAT-065 | C103: WebPage | D103: RemoteView 웹 기능 페이지 | E103: 멀티/ 듀얼모니터를 사용하시나요? | F103: RemoteView | G103: 멀티/ 듀얼모니터를 사용하시나요? | H103: 공통 | I103: 공개 | J103: 기능/제품 정보 확인 | K103: https://content.rview.com/ko/feature/multiple-monitors/ | L103: 본문 § 멀티/ 듀얼모니터를 사용하시나요? | N103: 리모트뷰의 듀얼모니터 디스플레이 옵션을 이용하여 원하는 대로 화면을 세팅하세요. 작업별로 화면을 분리하거나, 연결된 모든 화면을 모아보는 등 편리한 원격제어가 가능합니다. | O103: RemoteView 멀티/ 듀얼모니터를 사용하시나요?에 대해 알려주세요 | P103: RemoteView, 기능, 멀티/ 듀얼모니터를 사용하시나요? | Q103: RV-WEB-FEAT-065 | R103: Claude(Fable5) | S103: 상 | T103: 미검토
A104: 104 | B104: RV-WEB-FEAT-066 | C104: WebPage | D104: RemoteView 웹 기능 페이지 | E104: 듀얼모니터 제어, 이렇게 사용해 보세요! | F104: RemoteView | G104: 듀얼모니터 제어, 이렇게 사용해 보세요! | H104: 공통 | I104: 공개 | J104: 기능/제품 정보 확인 | K104: https://content.rview.com/ko/feature/multiple-monitors/ | L104: 본문 § 듀얼모니터 제어, 이렇게 사용해 보세요! | N104: 사용자 맞춤형 멀티모니터 옵션을 제공합니다. 쉬워지는 멀티 태스킹, 향상되는 업무 능률을 직접 경험해보세요. | O104: RemoteView 듀얼모니터 제어, 이렇게 사용해 보세요!에 대해 알려주세요 | P104: RemoteView, 기능, 듀얼모니터 제어, 이렇게 사용해 보세 | Q104: RV-WEB-FEAT-066 | R104: Claude(Fable5) | S104: 상 | T104: 미검토
A105: 105 | B105: RV-WEB-FEAT-067 | C105: WebPage | D105: RemoteView 웹 기능 페이지 | E105: 한 화면에 여러 대의 | F105: RemoteView | G105: 한 화면에 여러 대의 | H105: 공통 | I105: 공개 | J105: 기능/제품 정보 확인 | K105: https://content.rview.com/ko/feature/multiple-monitors/ | L105: 본문 § 한 화면에 여러 대의 | N105: 모니터 모아 보기 ](#m2) | O105: RemoteView 한 화면에 여러 대의에 대해 알려주세요 | P105: RemoteView, 기능, 한 화면에 여러 대의 | Q105: RV-WEB-FEAT-067 | R105: Claude(Fable5) | S105: 하 | T105: 근거약함 | U105: 본문 25자 미만
A106: 106 | B106: RV-WEB-FEAT-068 | C106: WebPage | D106: RemoteView 웹 기능 페이지 | E106: 여러 대의 모니터를 | F106: RemoteView | G106: 여러 대의 모니터를 | H106: 공통 | I106: 공개 | J106: 기능/제품 정보 확인 | K106: https://content.rview.com/ko/feature/multiple-monitors/ | L106: 본문 § 여러 대의 모니터를 | N106: 개별 창으로 나누어 보기 ](#m3) | O106: RemoteView 여러 대의 모니터를에 대해 알려주세요 | P106: RemoteView, 기능, 여러 대의 모니터를 | Q106: RV-WEB-FEAT-068 | R106: Claude(Fable5) | S106: 하 | T106: 근거약함 | U106: 본문 25자 미만
A107: 107 | B107: RV-WEB-FEAT-069 | C107: WebPage | D107: RemoteView 웹 기능 페이지 | E107: 리모트뷰 멀티모니터, 영상으로 확인하세요. | F107: RemoteView | G107: 리모트뷰 멀티모니터, 영상으로 확인하세요. | H107: 공통 | I107: 공개 | J107: 기능/제품 정보 확인 | K107: https://content.rview.com/ko/feature/multiple-monitors/ | L107: 본문 § 리모트뷰 멀티모니터, 영상으로 확인하세요. | N107: 몇 대의 모니터든 부드럽고 끊김 없이 제어가 가능합니다. 다중모니터로 연결된 원격지 환경을 그대로 반영하여 업무 연속성을 유지할 수 있습니다. | O107: RemoteView 리모트뷰 멀티모니터, 영상으로 확인하세요.에 대해 알려주세요 | P107: RemoteView, 기능, 리모트뷰 멀티모니터, 영상으로 확인하 | Q107: RV-WEB-FEAT-069 | R107: Claude(Fable5) | S107: 상 | T107: 미검토
A108: 108 | B108: RV-WEB-FEAT-070 | C108: WebPage | D108: RemoteView 웹 기능 페이지 | E108: 01 | F108: RemoteView | G108: 01 | H108: 공통 | I108: 공개 | J108: 기능/제품 정보 확인 | K108: https://content.rview.com/ko/feature/multiple-monitors/ | L108: 본문 § 01 | N108: 한 번에 한 대의 모니터 보기 여러 대의 모니터 중 원하는 모니터를 한 번에 하나씩 노출합니다. - 모니터 전환 버튼으로 자유롭게 모니터를 변경하거나, - 화면 – 모니터 선택으로 원하는 모니터를 지정하여 확인할 수 있습니다. | O108: RemoteView 01에 대해 알려주세요 | P108: RemoteView, 기능, 01 | Q108: RV-WEB-FEAT-070 | R108: Claude(Fable5) | S108: 상 | T108: 미검토
A109: 109 | B109: RV-WEB-FEAT-071 | C109: WebPage | D109: RemoteView 웹 기능 페이지 | E109: 02 | F109: RemoteView | G109: 02 | H109: 공통 | I109: 공개 | J109: 기능/제품 정보 확인 | K109: https://content.rview.com/ko/feature/multiple-monitors/ | L109: 본문 § 02 | N109: 한 화면에 여러 대의 모니터 모아 보기 연결된 모니터들을 분할하여 한 화면에 표시합니다. 여러 대의 모니터를 한 화면에 모아 한 눈에 확인할 수 있습니다. - 화면 - 모니터 선택 – 전체 모니터 보기 | O109: RemoteView 02에 대해 알려주세요 | P109: RemoteView, 기능, 02 | Q109: RV-WEB-FEAT-071 | R109: Claude(Fable5) | S109: 상 | T109: 미검토
A110: 110 | B110: RV-WEB-FEAT-072 | C110: WebPage | D110: RemoteView 웹 기능 페이지 | E110: 03 | F110: RemoteView | G110: 03 | H110: 공통 | I110: 공개 | J110: 기능/제품 정보 확인 | K110: https://content.rview.com/ko/feature/multiple-monitors/ | L110: 본문 § 03 | N110: 여러 대의 모니터를 개별 창으로 나누어 보기 여러 모니터의 화면을 독립된 각각의 창으로 나누어 제어할 수 있습니다. 윈도우 창처럼 자유롭게 드래그하거나 이동이 가능합니다. - 화면 - 멀티 뷰어 실행 **자주 묻는 질문** - 01 | O110: RemoteView 03에 대해 알려주세요 | P110: RemoteView, 기능, 03 | Q110: RV-WEB-FEAT-072 | R110: Claude(Fable5) | S110: 상 | T110: 미검토
A111: 111 | B111: RV-WEB-FEAT-073 | C111: WebPage | D111: RemoteView 웹 기능 페이지 | E111: 최대 몇 대의 멀티모니터를 지원하나요? | F111: RemoteView | G111: 최대 몇 대의 멀티모니터를 지원하나요? | H111: 공통 | I111: 공개 | J111: 기능/제품 정보 확인 | K111: https://content.rview.com/ko/feature/multiple-monitors/ | L111: 본문 § 최대 몇 대의 멀티모니터를 지원하나요? | N111: 4대까지 지원합니다. 확장 지원이 필요하신 경우, 고객센터로 문의해주세요. - 02 | O111: RemoteView 최대 몇 대의 멀티모니터를 지원하나요?에 대해 알려주세요 | P111: RemoteView, 기능, 최대 몇 대의 멀티모니터를 지원하나요 | Q111: RV-WEB-FEAT-073 | R111: Claude(Fable5) | S111: 중 | T111: 미검토
A112: 112 | B112: RV-WEB-FEAT-074 | C112: WebPage | D112: RemoteView 웹 기능 페이지 | E112: 별도의 설정이 필요한가요? | F112: RemoteView | G112: 별도의 설정이 필요한가요? | H112: 공통 | I112: 공개 | J112: 기능/제품 정보 확인 | K112: https://content.rview.com/ko/feature/multiple-monitors/ | L112: 본문 § 별도의 설정이 필요한가요? | N112: 2대 이상의 모니터를 연결하면 자동으로 기능이 활성화됩니다. - 03 | O112: RemoteView 별도의 설정이 필요한가요?에 대해 알려주세요 | P112: RemoteView, 기능, 별도의 설정이 필요한가요? | Q112: RV-WEB-FEAT-074 | R112: Claude(Fable5) | S112: 중 | T112: 미검토
A113: 113 | B113: RV-WEB-FEAT-075 | C113: WebPage | D113: RemoteView 웹 기능 페이지 | E113: 웹뷰어에서 해당 기능을 이용할 수 있나요? | F113: RemoteView | G113: 웹뷰어에서 해당 기능을 이용할 수 있나요? | H113: 공통 | I113: 공개 | J113: 기능/제품 정보 확인 | K113: https://content.rview.com/ko/feature/multiple-monitors/ | L113: 본문 § 웹뷰어에서 해당 기능을 이용할 수 있나요? | N113: New 원격제어 모드에서만 이용 가능합니다. - 04 | O113: RemoteView 웹뷰어에서 해당 기능을 이용할 수 있나요?에 대해 알려주세요 | P113: RemoteView, 기능, 웹뷰어에서 해당 기능을 이용할 수 있 | Q113: RV-WEB-FEAT-075 | R113: Claude(Fable5) | S113: 중 | T113: 미검토
A114: 114 | B114: RV-WEB-FEAT-076 | C114: WebPage | D114: RemoteView 웹 기능 페이지 | E114: 스탠다드/엔터프라이즈 라이선스 모두 지원하나요? | F114: RemoteView | G114: 스탠다드/엔터프라이즈 라이선스 모두 지원하나요? | H114: 공통 | I114: 공개 | J114: 기능/제품 정보 확인 | K114: https://content.rview.com/ko/feature/multiple-monitors/ | L114: 본문 § 스탠다드/엔터프라이즈 라이선스 모두 지원하나요? | N114: 모든 라이선스에 지원되는 기능입니다. [ 멀티 모니터를 제어하는 가장 효율적인 방법 New 원격제어 모드 살펴보기 ](/ko/feature/newviewer/) Go to Top App DownLoad - Android App **알서포트(주)** 대표 : 서형수 주소 : (05203) 서울특별시 강동구 고덕비즈밸리로2가길 12 (고덕동) Windows® is a trademark of the Microsoft group of companies. iPhone® and iPad® are trademarks of Apple Inc., registered in the U.S. and other countries. Android™ is a trademark of Google Inc. © [RSUPPORT](https://www.rsupport.com/) CO., LTD. ALL RIGHTS RESERVED. [ 문의하기 ](https://help.rview.com/hc/ko/requests/new?ticket_form_id=360000030893)[ 시작가이드 ](/ko/support/tutorial/)[ 10분 체험 ](https://rview.com/ko/virtual_exp) | O114: RemoteView 스탠다드/엔터프라이즈 라이선스 모두 지원하나요?에 대해 알려주세요 | P114: RemoteView, 기능, 스탠다드/엔터프라이즈 라이선스 모두 | Q114: RV-WEB-FEAT-076 | R114: Claude(Fable5) | S114: 상 | T114: 미검토
A115: 115 | B115: RV-WEB-FEAT-077 | C115: WebPage | D115: RemoteView 웹 기능 페이지 | E115: (도입부) | F115: RemoteView | G115: (도입부) | H115: 공통 | I115: 공개 | J115: 기능/제품 정보 확인 | K115: https://content.rview.com/ko/feature/newviewer/ | L115: 본문 § (도입부) | N115: 더 완벽히 진화한 리모트뷰! | O115: RemoteView (도입부)에 대해 알려주세요 | P115: RemoteView, 기능, (도입부) | Q115: RV-WEB-FEAT-077 | R115: Claude(Fable5) | S115: 하 | T115: 근거약함 | U115: 본문 25자 미만
A116: 116 | B116: RV-WEB-FEAT-078 | C116: WebPage | D116: RemoteView 웹 기능 페이지 | E116: New 원격제어 모드 | F116: RemoteView | G116: New 원격제어 모드 | H116: 공통 | I116: 공개 | J116: 기능/제품 정보 확인 | K116: https://content.rview.com/ko/feature/newviewer/ | L116: 본문 § New 원격제어 모드 | N116: 독자적인 기술과 노하우로 완성된 New 원격제어 모드로 확 달라진 리모트뷰를 경험해 보세요. | O116: RemoteView New 원격제어 모드에 대해 알려주세요 | P116: RemoteView, 기능, New 원격제어 모드 | Q116: RV-WEB-FEAT-078 | R116: Claude(Fable5) | S116: 중 | T116: 미검토
A117: 117 | B117: RV-WEB-FEAT-079 | C117: WebPage | D117: RemoteView 웹 기능 페이지 | E117: New 원격제어 어떻게 진화했을까요? | F117: RemoteView | G117: New 원격제어 어떻게 진화했을까요? | H117: 공통 | I117: 공개 | J117: 기능/제품 정보 확인 | K117: https://content.rview.com/ko/feature/newviewer/ | L117: 본문 § New 원격제어 어떻게 진화했을까요? | N117: 쾌적한 UI/UX 멀티 모니터 확장 지원 간편한 환경설정 화상 키보드 Your browser does not support the video tag. | O117: RemoteView New 원격제어 어떻게 진화했을까요?에 대해 알려주세요 | P117: RemoteView, 기능, New 원격제어 어떻게 진화했을까요? | Q117: RV-WEB-FEAT-079 | R117: Claude(Fable5) | S117: 상 | T117: 미검토
A118: 118 | B118: RV-WEB-FEAT-080 | C118: WebPage | D118: RemoteView 웹 기능 페이지 | E118: 깔끔하고 넓어진 화면 구성과 간결하고 직관적인 기능 배열로 | F118: RemoteView | G118: 깔끔하고 넓어진 화면 구성과 간결하고 직관적인 기능 배열로 | H118: 공통 | I118: 공개 | J118: 기능/제품 정보 확인 | K118: https://content.rview.com/ko/feature/newviewer/ | L118: 본문 § 깔끔하고 넓어진 화면 구성과 간결하고 직관적인 기능 배열로 | N118: 더 쉽고 쾌적해진 사용 환경에서 원격제어가 가능합니다. Your browser does not support the video tag. | O118: RemoteView 깔끔하고 넓어진 화면 구성과 간결하고 직관적인 기능 배에 대해 알려주세요 | P118: RemoteView, 기능, 깔끔하고 넓어진 화면 구성과 간결하고 | Q118: RV-WEB-FEAT-080 | R118: Claude(Fable5) | S118: 상 | T118: 미검토
A119: 119 | B119: RV-WEB-FEAT-081 | C119: WebPage | D119: RemoteView 웹 기능 페이지 | E119: 최대 4대의 모니터를 지원하는 멀티 뷰어 기능으로 | F119: RemoteView | G119: 최대 4대의 모니터를 지원하는 멀티 뷰어 기능으로 | H119: 공통 | I119: 공개 | J119: 기능/제품 정보 확인 | K119: https://content.rview.com/ko/feature/newviewer/ | L119: 본문 § 최대 4대의 모니터를 지원하는 멀티 뷰어 기능으로 | N119: 여러 대의 모니터를 독립적인 개별 창으로 제어하거나 한눈에 모아보는 화면분할로 자유롭게 활용할 수 있습니다. Your browser does not support the video tag. | O119: RemoteView 최대 4대의 모니터를 지원하는 멀티 뷰어 기능으로에 대해 알려주세요 | P119: RemoteView, 기능, 최대 4대의 모니터를 지원하는 멀티 | Q119: RV-WEB-FEAT-081 | R119: Claude(Fable5) | S119: 상 | T119: 미검토
A120: 120 | B120: RV-WEB-FEAT-082 | C120: WebPage | D120: RemoteView 웹 기능 페이지 | E120: 나에게 최적화된 원격제어 환경을 한 번에 쉽게 설정하고 | F120: RemoteView | G120: 나에게 최적화된 원격제어 환경을 한 번에 쉽게 설정하고 | H120: 공통 | I120: 공개 | J120: 기능/제품 정보 확인 | K120: https://content.rview.com/ko/feature/newviewer/ | L120: 본문 § 나에게 최적화된 원격제어 환경을 한 번에 쉽게 설정하고 | N120: 저장하여 더욱 간편하게 [환경설정](https://help.rview.com/hc/ko/articles/14857321903891)을 이용할 수 있습니다. Your browser does not support the video tag. | O120: RemoteView 나에게 최적화된 원격제어 환경을 한 번에 쉽게 설정하고에 대해 알려주세요 | P120: RemoteView, 기능, 나에게 최적화된 원격제어 환경을 한 | Q120: RV-WEB-FEAT-082 | R120: Claude(Fable5) | S120: 상 | T120: 미검토
A121: 121 | B121: RV-WEB-FEAT-083 | C121: WebPage | D121: RemoteView 웹 기능 페이지 | E121: ![리모트뷰 New 원격제어 모드 화상 키보드 지원](/wp-content/uploads/image/sub/icon-newviewer04.png | F121: RemoteView | G121: ![리모트뷰 New 원격제어 모드 화상 키보드 지원](/wp-conten | H121: 공통 | I121: 공개 | J121: 기능/제품 정보 확인 | K121: https://content.rview.com/ko/feature/newviewer/ | L121: 본문 § ![리모트뷰 New 원격제어 모드 화상 키보드 지원](/wp-conten | N121: 가상 키보드 활성화 기능으로 키보드가 없는 업무 환경에서도 제약 없이 원격제어를 활용하고 생산성을 높일 수 있습니다. | O121: RemoteView ![리모트뷰 New 원격제어 모드 화상 키보드 지원](에 대해 알려주세요 | P121: RemoteView, 기능, ![리모트뷰 New 원격제어 모드 화 | Q121: RV-WEB-FEAT-083 | R121: Claude(Fable5) | S121: 상 | T121: 미검토
A122: 122 | B122: RV-WEB-FEAT-084 | C122: WebPage | D122: RemoteView 웹 기능 페이지 | E122: 지원 사양 | F122: RemoteView | G122: 지원 사양 | H122: 공통 | I122: 공개 | J122: 기능/제품 정보 확인 | K122: https://content.rview.com/ko/feature/newviewer/ | L122: 본문 § 지원 사양 | N122: | 운영체제 | | --- | | Windows | Windows 10이상, Windows Server 2012 이상 | | MacOS | MacOS 11 – 14 | | Android | Android 7 – 13 | | Linux | CentOS(64bit) 7.0 – 7.7 | | Red Hat(64bit) 7.0 – 7.7 | | Ubunto(64bit) 14.4 – 18.4 | [ 설치 없이 간편한 리모트뷰 웹뷰어를 알고 계시나요?쉽고 간편한 웹뷰어를 지금 체험해보세요 ](/ko/feature/webviewer/) Go to Top App DownLoad - Android App **알서포트(주)** 대표 : 서형수 주소 : (05203) 서울특별시 강동구 고덕비즈밸리로2가길 12 (고덕동) Windows® is a trademark of the Microsoft group of companies. iPhone® and iPad® are trademarks of Apple Inc., registered in the U.S. and other countries. Android™ is a trademark of Google Inc. © [RSUPPORT](https://www.rsupport.com/) CO., LTD. ALL RIGHTS RESERVED. [ 문의하기 ](https://help.rview.com/hc/ko/requests/new?ticket_form_id=360000030893)[ 시작가이드 ](/ko/support/tutorial/)[ 10분 체험 ](https://rview.com/ko/virtual_exp) 더 완벽히 진화한 리모트뷰! | O122: RemoteView 지원 사양에 대해 알려주세요 | P122: RemoteView, 기능, 지원 사양 | Q122: RV-WEB-FEAT-084 | R122: Claude(Fable5) | S122: 상 | T122: 미검토
A123: 123 | B123: RV-WEB-FEAT-085 | C123: WebPage | D123: RemoteView 웹 기능 페이지 | E123: 지원 사양 | F123: RemoteView | G123: 지원 사양 | H123: 공통 | I123: 공개 | J123: 기능/제품 정보 확인 | K123: https://content.rview.com/ko/feature/newviewer/ | L123: 본문 § 지원 사양 (2차) | N123: | 운영체제 | | --- | | Windows | Windows 10이상, Windows Server 2012 이상 | | MacOS | MacOS 11 – 14 | | Android | Android 7 – 13 | | Linux | CentOS(64bit) 7.0 – 7.7 | | Red Hat(64bit) 7.0 – 7.7 | | Ubunto(64bit) 14.4 – 18.4 | [ 설치 없이 간편한 리모트뷰 웹뷰어를 알고 계시나요?쉽고 간편한 웹뷰어를 지금 체험해보세요 ](/ko/feature/webviewer/) Go to Top App DownLoad - Android App **알서포트(주)** 대표 : 서형수 주소 : (05203) 서울특별시 강동구 고덕비즈밸리로2가길 12 (고덕동) Windows® is a trademark of the Microsoft group of companies. iPhone® and iPad® are trademarks of Apple Inc., registered in the U.S. and other countries. Android™ is a trademark of Google Inc. © [RSUPPORT](https://www.rsupport.com/) CO., LTD. ALL RIGHTS RESERVED. [ 문의하기 ](https://help.rview.com/hc/ko/requests/new?ticket_form_id=360000030893)[ 시작가이드 ](/ko/support/tutorial/)[ 10분 체험 ](https://rview.com/ko/virtual_exp) | O123: RemoteView 지원 사양에 대해 알려주세요 | P123: RemoteView, 기능, 지원 사양 | Q123: RV-WEB-FEAT-085 | R123: Claude(Fable5) | S123: 상 | T123: 미검토
A124: 124 | B124: RV-WEB-FEAT-086 | C124: WebPage | D124: RemoteView 웹 기능 페이지 | E124: 현장 제어가 필요한 순간, | F124: RemoteView | G124: 현장 제어가 필요한 순간, | H124: 공통 | I124: 공개 | J124: 기능/제품 정보 확인 | K124: https://content.rview.com/ko/feature/rvbox-advanced/ | L124: 본문 § 현장 제어가 필요한 순간, | N124: 리모트뷰박스로 실시간 원격제어 현장에 가지 않아도 리모트뷰박스만 있다면, 언제 어디서든 정밀한 제어가 가능합니다. 현장 대응을 더 빠르고 정확하게, 원격제어 하드웨어 리모트뷰박스 단 1픽셀의 오차도 허용하지 않는 정밀한 마우스 제어 현장 장비의 마우스 좌표를 원격에서도 정확하게 일치시켜, 마우스 제어 사각지대(Dead Zone) 없이 안정적으로 조작 할 수 있습니다. - 단일 커서 옵션으로 정합성 향상 - 마우스 제어 사각지대(Dead Zone) 원천 차단 - 듀얼 모니터 간 커서 이동 시 튐 현상 방지 브라우저가 video 태그를 지원하지 않습니다. 1인은 제어하고, 2인은 관제하는 안전한 협업 구조 제어와 모니터링을 분리해 오조작을 방지하고, 장비 추가 연결 을 통해 최대 3명이 동시에 안정적으로 접속할 수 있습 니다. - 기기 추가 구성 시 최대 3인 동시 접속 지원 - 제어와 모니터링 역할을 명확하게 분리 - 마우스 신호 물리적 차단으로 조작 권한 제어 브라우저가 video 태그를 지원하지 않습니다. 비표준 해상도부터 초광각 화면까지 왜곡 없는 원격 관리 초광각·대형 디스플레이에서도 별도 설정 없이 왜곡 없는 화면을 실시간으로 모니터링할 수 있습니다. - 다양한 화면 비율에도 찌그러짐 없는 선명함 - 클릭 한 번으로 모니터 해상도 설정 최적화 - 특수 규격의 관제 시스템도 완벽하게 호환 브라우저가 video 태그를 지원하지 않습니다. 검증된 보안 채널로 완성하는 빈틈없는 현장 물리 보안 보안이 검증된 리모트뷰 채널을 통해 제어 화면과 현장 상황을 함께 전난희여 안전한 원격 관제가 가능합니다. - 제어 화면과 실시간 현장을 동시 모니터링 - 리모트뷰 보안 기반의 안전한 영상 전송 - 저가형 CCTV와 차별화된 강력한 보안 브라우저가 video 태그를 지원하지 않습니다. 리모트뷰박스로 어디서든 바로 제어하세요 연결만으로 다양한 장비를 안정적으로 원격 제어할 수 있습니다. 개인정보 수집 및 이용 ![](/wp-content/uploads/sites/2/image/sub/sms_close_icon.webp) 1. ∙ 수집하는 항목 : (필수)성명, 회사명, 휴대폰 번호, 이메일 2. ∙ 수집 및 이용목적 : 문의사항 확인 및 처리결과 회신 3. ∙ 보유 및 이용기간 : 문의 검토 완료 후, 1년간 보관 1. **※ 개인정보 수집 및 이용에 대한 동의를 거부할 권리가 있습니다. 그러나 동의를 거부할 경우, 문의 등록을 하실 수 없습니다.** Go to Top App DownLoad - Android App **알서포트(주)** 대표 : 서형수 주소 : (05203) 서울특별시 강동구 고덕비즈밸리로2가길 12 (고덕동) Windows® is a trademark of the Microsoft group of companies. iPhone® and iPad® are trademarks of Apple Inc., registered in the U.S. and other countries. Android™ is a trademark of Google Inc. © [RSUPPORT](https://www.rsupport.com/) CO., LTD. ALL RIGHTS RESERVED. [ 문의하기 ](https://help.rview.com/hc/ko/requests/new?ticket_form_id=360000030893)[ 시작가이드 ](/ko/support/tutorial/)[ 10분 체험 ](https://rview.com/ko/virtual_exp) | O124: RemoteView 현장 제어가 필요한 순간,에 대해 알려주세요 | P124: RemoteView, 기능, 현장 제어가 필요한 순간, | Q124: RV-WEB-FEAT-086 | R124: Claude(Fable5) | S124: 상 | T124: 미검토 | U124: / URL 변형 앵커: https://content.rview.com/ko/?p=24107 (동일 포스트 — 채점 시 정답 문서로 접힘)
A125: 125 | B125: RV-WEB-FEAT-087 | C125: WebPage | D125: RemoteView 웹 기능 페이지 | E125: 모니터 없이도, 소프트웨어 | F125: RemoteView | G125: 모니터 없이도, 소프트웨어 | H125: 공통 | I125: 공개 | J125: 기능/제품 정보 확인 | K125: https://content.rview.com/ko/feature/rvbox/ | L125: 본문 § 모니터 없이도, 소프트웨어 | N125: 설치 없이도 가능한 원격 제어 BIOS 화면 제어부터 소프트웨어 무설치, 4K 고화질 출력까지 제약 많은 환경에서도 안정적으로 제어할 수 있습니다. | O125: RemoteView 모니터 없이도, 소프트웨어에 대해 알려주세요 | P125: RemoteView, 기능, 모니터 없이도, 소프트웨어 | Q125: RV-WEB-FEAT-087 | R125: Claude(Fable5) | S125: 상 | T125: 미검토
A126: 126 | B126: RV-WEB-FEAT-088 | C126: WebPage | D126: RemoteView 웹 기능 페이지 | E126: 산업용 기기제어를 위한 리모트뷰박스의 핵심 기능 | F126: RemoteView | G126: 산업용 기기제어를 위한 리모트뷰박스의 핵심 기능 | H126: 공통 | I126: 공개 | J126: 기능/제품 정보 확인 | K126: https://content.rview.com/ko/feature/rvbox/ | L126: 본문 § 산업용 기기제어를 위한 리모트뷰박스의 핵심 기능 | N126: S/W 무설치 카메라 연동 Ethernet 지원 특수/구형OS 제어 BIOS 화면제어 원격 전원제어 4K 고화질 | O126: RemoteView 산업용 기기제어를 위한 리모트뷰박스의 핵심 기능에 대해 알려주세요 | P126: RemoteView, 기능, 산업용 기기제어를 위한 리모트뷰박스의 | Q126: RV-WEB-FEAT-088 | R126: Claude(Fable5) | S126: 상 | T126: 미검토
A127: 127 | B127: RV-WEB-FEAT-089 | C127: WebPage | D127: RemoteView 웹 기능 페이지 | E127: 제어할 기기에 소프트웨어 설치없이 제어가 | F127: RemoteView | G127: 제어할 기기에 소프트웨어 설치없이 제어가 | H127: 공통 | I127: 공개 | J127: 기능/제품 정보 확인 | K127: https://content.rview.com/ko/feature/rvbox/ | L127: 본문 § 제어할 기기에 소프트웨어 설치없이 제어가 | N127: 가능한가요? 리모트뷰박스는 제어할 기기에 S/W 설치 없이 하드웨어 리소스만을 이용하여 HDMI 연결을 통해 화면을 송출하고 제어하기 때문에 보안사고나, 외부 S/W 설치금지 정책에 완벽대응이 가능합니다. 또한 S/W가 내장되어 제어기기의 OS를 업데이트 하거나, 리모트뷰박스 업데이 트에도 제어할 기기에는 영향없이 업데이트가 가능합니다. | O127: RemoteView 제어할 기기에 소프트웨어 설치없이 제어가에 대해 알려주세요 | P127: RemoteView, 기능, 제어할 기기에 소프트웨어 설치없이 제 | Q127: RV-WEB-FEAT-089 | R127: Claude(Fable5) | S127: 상 | T127: 미검토
A128: 128 | B128: RV-WEB-FEAT-090 | C128: WebPage | D128: RemoteView 웹 기능 페이지 | E128: 모니터연결이 어려운 산업용 기기나, 오래된 PC도 제어 | F128: RemoteView | G128: 모니터연결이 어려운 산업용 기기나, 오래된 PC도 제어 | H128: 공통 | I128: 공개 | J128: 기능/제품 정보 확인 | K128: https://content.rview.com/ko/feature/rvbox/ | L128: 본문 § 모니터연결이 어려운 산업용 기기나, 오래된 PC도 제어 | N128: 할 수 있을까요? 리모트뷰박스의 카메라 연동 기능을 이용하면 모니터 연결이 어려운 산업용 기기 도 제어가 가능합니다. 리모트뷰박스는 KVM 기술을 기반으로 제작되어 키보드/ 비디오/마우스가 각각 독립적으로 동작합니다. 때문에 제어할 기기 대신 카메라 를 연결하여 모니터 역할을 함으로써 별도의 비디오 연결 포트가 없어도 제어가 가능합니다. | O128: RemoteView 모니터연결이 어려운 산업용 기기나, 오래된 PC도 제어에 대해 알려주세요 | P128: RemoteView, 기능, 모니터연결이 어려운 산업용 기기나, | Q128: RV-WEB-FEAT-090 | R128: Claude(Fable5) | S128: 상 | T128: 미검토
A129: 129 | B129: RV-WEB-FEAT-091 | C129: WebPage | D129: RemoteView 웹 기능 페이지 | E129: 보안 때문에 인터넷 연결을 할 수 없는 기기도 원격제어 | F129: RemoteView | G129: 보안 때문에 인터넷 연결을 할 수 없는 기기도 원격제어 | H129: 공통 | I129: 공개 | J129: 기능/제품 정보 확인 | K129: https://content.rview.com/ko/feature/rvbox/ | L129: 본문 § 보안 때문에 인터넷 연결을 할 수 없는 기기도 원격제어 | N129: 가능할까요? 리모트뷰박스라면 이더넷 지원이 안되는 기기도 문제없이 원격제어가 가능합니 다. 리모트뷰박스는 자체로 이더넷을 지원하여 내부망, 외부망, 유선 환경을 모두 지원합니다. 따라서 기기의 보안 문제와 안정성 문제 뿐만 아니라 호환이슈로 인 해서 인터넷 연결을 제한하거나 직접적으로 연결을 하지 못하는 장비도 안전하게 제어가 가능합니다. | O129: RemoteView 보안 때문에 인터넷 연결을 할 수 없는 기기도 원격제어에 대해 알려주세요 | P129: RemoteView, 기능, 보안 때문에 인터넷 연결을 할 수 없 | Q129: RV-WEB-FEAT-091 | R129: Claude(Fable5) | S129: 상 | T129: 미검토
A130: 130 | B130: RV-WEB-FEAT-092 | C130: WebPage | D130: RemoteView 웹 기능 페이지 | E130: 더이상 지원하지 않는 OS나 특수OS도 | F130: RemoteView | G130: 더이상 지원하지 않는 OS나 특수OS도 | H130: 공통 | I130: 공개 | J130: 기능/제품 정보 확인 | K130: https://content.rview.com/ko/feature/rvbox/ | L130: 본문 § 더이상 지원하지 않는 OS나 특수OS도 | N130: 제어 가능할까요? 리모트뷰박스는 운영체제(OS)에 관계없이 원격제어가 가능합니다. 리모트뷰박 스는 운영체제 위에서 동작하는 소프트웨어가 아니라 하드웨어 자체의 신호를 제 어하는 방식이기 때문에 구형 윈도우, 리눅스, 맥, 심지어 커스텀 SO나 임베디드 OS같은 특수한 시스템이 탑재된 장비도 동일하게 제어가 가능합니다. | O130: RemoteView 더이상 지원하지 않는 OS나 특수OS도에 대해 알려주세요 | P130: RemoteView, 기능, 더이상 지원하지 않는 OS나 특수OS | Q130: RV-WEB-FEAT-092 | R130: Claude(Fable5) | S130: 상 | T130: 미검토
A131: 131 | B131: RV-WEB-FEAT-093 | C131: WebPage | D131: RemoteView 웹 기능 페이지 | E131: 부팅할 때 나오는 BIOS 화면도 제어할 수 있을까요? | F131: RemoteView | G131: 부팅할 때 나오는 BIOS 화면도 제어할 수 있을까요? | H131: 공통 | I131: 공개 | J131: 기능/제품 정보 확인 | K131: https://content.rview.com/ko/feature/rvbox/ | L131: 본문 § 부팅할 때 나오는 BIOS 화면도 제어할 수 있을까요? | N131: 리모트뷰박스는 부팅 시 노출되는 BIOS 화면도 제어가 가능합니다. 리모트뷰박스는 KVM over IP 기술을 기반으로 운영체제에 의존하지 않기 때문 에 HDMI케이블을 통해 송출된 화면으로 CMOS 셋업이 가능하며, 장애 시 부팅화 면을 체크하여 장애를 지원한다거나, 멀티 부팅화면에 원격 접속하여 제어하는 것 이 가능합니다. | O131: RemoteView 부팅할 때 나오는 BIOS 화면도 제어할 수 있을까요?에 대해 알려주세요 | P131: RemoteView, 기능, 부팅할 때 나오는 BIOS 화면도 제 | Q131: RV-WEB-FEAT-093 | R131: Claude(Fable5) | S131: 상 | T131: 미검토
A132: 132 | B132: RV-WEB-FEAT-094 | C132: WebPage | D132: RemoteView 웹 기능 페이지 | E132: 원격지에 있는 기기의 전원도 제어할 수 있을까요? | F132: RemoteView | G132: 원격지에 있는 기기의 전원도 제어할 수 있을까요? | H132: 공통 | I132: 공개 | J132: 기능/제품 정보 확인 | K132: https://content.rview.com/ko/feature/rvbox/ | L132: 본문 § 원격지에 있는 기기의 전원도 제어할 수 있을까요? | N132: 리모트뷰박스에는 WOL(Wake On Lan)기능이 함께 탑재되어 있어 제어할 기기 의 전원 On/OFF 제어가 가능합니다. 원격지 기기의 전원상태를 관리자 화면을 통해 모니터링이 가능하며 긴급상황에 실시간으로 전원을 켤 수 있습니다. 또한 전원 OFF 상태를 유지하여 전기 사용량 절감, 장비의 수명 연장, 보안 강화가 가능합니다. | O132: RemoteView 원격지에 있는 기기의 전원도 제어할 수 있을까요?에 대해 알려주세요 | P132: RemoteView, 기능, 원격지에 있는 기기의 전원도 제어할 | Q132: RV-WEB-FEAT-094 | R132: Claude(Fable5) | S132: 상 | T132: 미검토
A133: 133 | B133: RV-WEB-FEAT-095 | C133: WebPage | D133: RemoteView 웹 기능 페이지 | E133: 고해상도의 작업이 필요한데 원격제어로 끊기지 | F133: RemoteView | G133: 고해상도의 작업이 필요한데 원격제어로 끊기지 | H133: 공통 | I133: 공개 | J133: 기능/제품 정보 확인 | K133: https://content.rview.com/ko/feature/rvbox/ | L133: 본문 § 고해상도의 작업이 필요한데 원격제어로 끊기지 | N133: 않을까요? 리모트뷰박스는 원격제어 동작을 실행하는 S/W가 원격지 기기에 설치되어 동작 하는 것이 아니라 기기 내부에 설치된 S/W를 하드웨어 자체 리소스만을 이용하여 동작하기 때문에 제어할 기기의 리소스를 최소화할 수 있습니다. 따라서 원격제어 를 통한 기기의 리소스 부하없이 보다 안정적으로 제어가 가능합니다. 개인정보 수집 및 이용 ![](/wp-content/uploads/sites/2/image/sub/sms_close_icon.webp) 1. ∙ 수집하는 항목 : (필수)성명, 회사명, 휴대폰 번호, 이메일 2. ∙ 수집 및 이용목적 : 문의사항 확인 및 처리결과 회신 3. ∙ 보유 및 이용기간 : 문의 검토 완료 후, 1년간 보관 1. **※ 개인정보 수집 및 이용에 대한 동의를 거부할 권리가 있습니다. 그러나 동의를 거부할 경우, 문의 등록을 하실 수 없습니다.** Go to Top App DownLoad - Android App **알서포트(주)** 대표 : 서형수 주소 : (05203) 서울특별시 강동구 고덕비즈밸리로2가길 12 (고덕동) Windows® is a trademark of the Microsoft group of companies. iPhone® and iPad® are trademarks of Apple Inc., registered in the U.S. and other countries. Android™ is a trademark of Google Inc. © [RSUPPORT](https://www.rsupport.com/) CO., LTD. ALL RIGHTS RESERVED. [ 문의하기 ](https://help.rview.com/hc/ko/requests/new?ticket_form_id=360000030893)[ 시작가이드 ](/ko/support/tutorial/)[ 10분 체험 ](https://rview.com/ko/virtual_exp) | O133: RemoteView 고해상도의 작업이 필요한데 원격제어로 끊기지에 대해 알려주세요 | P133: RemoteView, 기능, 고해상도의 작업이 필요한데 원격제어로 | Q133: RV-WEB-FEAT-095 | R133: Claude(Fable5) | S133: 상 | T133: 미검토
A134: 134 | B134: RV-WEB-FEAT-096 | C134: WebPage | D134: RemoteView 웹 기능 페이지 | E134: 빈틈없는 원격 보안 으로 언제 어디서나 | F134: RemoteView | G134: 빈틈없는 원격 보안 으로 언제 어디서나 | H134: 공통 | I134: 공개 | J134: 기능/제품 정보 확인 | K134: https://content.rview.com/ko/feature/security | L134: 본문 § 빈틈없는 원격 보안 으로 언제 어디서나 | N134: 안심하고 사용할 수 있는 리모트뷰 원격제어 솔루션 선택 시 최우선적인 고려 사항은 얼마나 안전하게 사용할 수 있는가입니다. 격이 다른 리모트뷰의 원격 보안 환경에서 걱정 없이 원격제어하세요! | O134: RemoteView 빈틈없는 원격 보안 으로 언제 어디서나에 대해 알려주세요 | P134: RemoteView, 기능, 빈틈없는 원격 보안 으로 언제 어디서 | Q134: RV-WEB-FEAT-096 | R134: Claude(Fable5) | S134: 상 | T134: 미검토
A135: 135 | B135: RV-WEB-FEAT-097 | C135: WebPage | D135: RemoteView 웹 기능 페이지 | E135: 안심하고 원격제어할 수 있는 리모트뷰의 보안 기능 | F135: RemoteView | G135: 안심하고 원격제어할 수 있는 리모트뷰의 보안 기능 | H135: 공통 | I135: 공개 | J135: 기능/제품 정보 확인 | K135: https://content.rview.com/ko/feature/security | L135: 본문 § 안심하고 원격제어할 수 있는 리모트뷰의 보안 기능 | N135: 원격지 화면 잠금 비밀번호 보안 로그인 2중 인증 허용 IP/MAC 설정 해외 로그인 차단 | O135: RemoteView 안심하고 원격제어할 수 있는 리모트뷰의 보안 기능에 대해 알려주세요 | P135: RemoteView, 기능, 안심하고 원격제어할 수 있는 리모트뷰 | Q135: RV-WEB-FEAT-097 | R135: Claude(Fable5) | S135: 중 | T135: 미검토
A136: 136 | B136: RV-WEB-FEAT-098 | C136: WebPage | D136: RemoteView 웹 기능 페이지 | E136: 모니터 화면 잠금으로 | F136: RemoteView | G136: 모니터 화면 잠금으로 | H136: 공통 | I136: 공개 | J136: 기능/제품 정보 확인 | K136: https://content.rview.com/ko/feature/security | L136: 본문 § 모니터 화면 잠금으로 | N136: 원격지 화면 유출 방지 원격지의 기기화면도 보안대상입니다. 원격제어 되고 있는 기기의 화면을 완벽하게 가려 중요한 정보를 타인에게 보이지 않도록 할 수 있습니다. | O136: RemoteView 모니터 화면 잠금으로에 대해 알려주세요 | P136: RemoteView, 기능, 모니터 화면 잠금으로 | Q136: RV-WEB-FEAT-098 | R136: Claude(Fable5) | S136: 상 | T136: 미검토
A137: 137 | B137: RV-WEB-FEAT-099 | C137: WebPage | D137: RemoteView 웹 기능 페이지 | E137: 디테일한 비밀번호 보안 설정으로 | F137: RemoteView | G137: 디테일한 비밀번호 보안 설정으로 | H137: 공통 | I137: 공개 | J137: 기능/제품 정보 확인 | K137: https://content.rview.com/ko/feature/security | L137: 본문 § 디테일한 비밀번호 보안 설정으로 | N137: 더 안전하게 계정을 보호 더욱 완벽한 보안 설정을 위해 계정의 비밀번호 수준과 사용 기간을 설정 하고, 로그인 시 비밀번호 입력 횟수 제한으로 더욱 안전하게 계정을 보호할 수 있습니다. | O137: RemoteView 디테일한 비밀번호 보안 설정으로에 대해 알려주세요 | P137: RemoteView, 기능, 디테일한 비밀번호 보안 설정으로 | Q137: RV-WEB-FEAT-099 | R137: Claude(Fable5) | S137: 상 | T137: 미검토 | U137: DEC-009 유의(홍보성 표현 포함) — 정답 소재 금지
A138: 138 | B138: RV-WEB-FEAT-100 | C138: WebPage | D138: RemoteView 웹 기능 페이지 | E138: 로그인 2단계 인증으로 | F138: RemoteView | G138: 로그인 2단계 인증으로 | H138: 공통 | I138: 공개 | J138: 기능/제품 정보 확인 | K138: https://content.rview.com/ko/feature/security | L138: 본문 § 로그인 2단계 인증으로 | N138: 계정 도용을 철저히 방지 로그인 시 OTP 또는 이메일을 통한 추가 인증으로 리모트뷰 계정의 보안을 한층 더 강화할 수 있습니다. 2단계 인증으로 강화된 보안 기능을 이용해 보세요. | O138: RemoteView 로그인 2단계 인증으로에 대해 알려주세요 | P138: RemoteView, 기능, 로그인 2단계 인증으로 | Q138: RV-WEB-FEAT-100 | R138: Claude(Fable5) | S138: 상 | T138: 미검토
A139: 139 | B139: RV-WEB-FEAT-101 | C139: WebPage | D139: RemoteView 웹 기능 페이지 | E139: 허용 IP와 MAC 설정으로 | F139: RemoteView | G139: 허용 IP와 MAC 설정으로 | H139: 공통 | I139: 공개 | J139: 기능/제품 정보 확인 | K139: https://content.rview.com/ko/feature/security | L139: 본문 § 허용 IP와 MAC 설정으로 | N139: 안전한 장소와 기기에서만 접속 원격 접속을 허용할 장소와 기기를 등록하여 그 외 접속을 차단하고 중요 자료의 유출을 막을 수 있습니다. 장소와 기기의 제한으로 보다 안전한 원격제어를 이용해보세요. | O139: RemoteView 허용 IP와 MAC 설정으로에 대해 알려주세요 | P139: RemoteView, 기능, 허용 IP와 MAC 설정으로 | Q139: RV-WEB-FEAT-101 | R139: Claude(Fable5) | S139: 상 | T139: 미검토
...

Sheet B2_폴딩대장
A1: # | B1: 구분 | C1: source/resource | D1: source_location | E1: 폴딩 사유 | F1: 대표 Unit ID
A2: 1 | B2: (폴딩) | C2: https://content.rview.com/ko/feature | D2: 본문 § 원격 접속 환경을 안전하게 | E2: 동일 문서 내 완전 동일 섹션 반복(크롤 레이아웃 이중화 추정) — 대표 RV-WEB-FEAT-002로 폴딩 | F2: RV-WEB-FEAT-002
A3: 2 | B3: (폴딩) | C3: https://content.rview.com/ko/feature | D3: 본문 § OTP 인증 가능 | E3: 동일 문서 내 완전 동일 섹션 반복(크롤 레이아웃 이중화 추정) — 대표 RV-WEB-FEAT-003로 폴딩 | F3: RV-WEB-FEAT-003
A4: 3 | B4: (폴딩) | C4: https://content.rview.com/ko/feature | D4: 본문 § 해외 로그인(IP) 차단 설정 | E4: 동일 문서 내 완전 동일 섹션 반복(크롤 레이아웃 이중화 추정) — 대표 RV-WEB-FEAT-004로 폴딩 | F4: RV-WEB-FEAT-004
A5: 4 | B5: (폴딩) | C5: https://content.rview.com/ko/feature | D5: 본문 § 원격제어 동의 | E5: 동일 문서 내 완전 동일 섹션 반복(크롤 레이아웃 이중화 추정) — 대표 RV-WEB-FEAT-005로 폴딩 | F5: RV-WEB-FEAT-005
A6: 5 | B6: (폴딩) | C6: https://content.rview.com/ko/feature | D6: 본문 § 허용 IP/MAC 관리 | E6: 동일 문서 내 완전 동일 섹션 반복(크롤 레이아웃 이중화 추정) — 대표 RV-WEB-FEAT-006로 폴딩 | F6: RV-WEB-FEAT-006
A7: 6 | B7: (폴딩) | C7: https://content.rview.com/ko/feature | D7: 본문 § 특정 프로세스(exe) 실행제한 | E7: 동일 문서 내 완전 동일 섹션 반복(크롤 레이아웃 이중화 추정) — 대표 RV-WEB-FEAT-007로 폴딩 | F7: RV-WEB-FEAT-007
A8: 7 | B8: (폴딩) | C8: https://content.rview.com/ko/feature | D8: 본문 § 원격PC 화면 잠금 | E8: 동일 문서 내 완전 동일 섹션 반복(크롤 레이아웃 이중화 추정) — 대표 RV-WEB-FEAT-008로 폴딩 | F8: RV-WEB-FEAT-008
A9: 8 | B9: (폴딩) | C9: https://content.rview.com/ko/feature | D9: 본문 § 마우스/키보드 입력 잠금 | E9: 동일 문서 내 완전 동일 섹션 반복(크롤 레이아웃 이중화 추정) — 대표 RV-WEB-FEAT-009로 폴딩 | F9: RV-WEB-FEAT-009
A10: 9 | B10: (폴딩) | C10: https://content.rview.com/ko/feature | D10: 본문 § 보안 상태 사전 점검 | E10: 동일 문서 내 완전 동일 섹션 반복(크롤 레이아웃 이중화 추정) — 대표 RV-WEB-FEAT-010로 폴딩 | F10: RV-WEB-FEAT-010
A11: 10 | B11: (폴딩) | C11: https://content.rview.com/ko/feature | D11: 본문 § 워터마크 | E11: 동일 문서 내 완전 동일 섹션 반복(크롤 레이아웃 이중화 추정) — 대표 RV-WEB-FEAT-011로 폴딩 | F11: RV-WEB-FEAT-011
A12: 11 | B12: (폴딩) | C12: https://content.rview.com/ko/feature | D12: 본문 § 언제 어디서나 기기에 접속해 | E12: 동일 문서 내 완전 동일 섹션 반복(크롤 레이아웃 이중화 추정) — 대표 RV-WEB-FEAT-012로 폴딩 | F12: RV-WEB-FEAT-012
A13: 12 | B13: (폴딩) | C13: https://content.rview.com/ko/feature | D13: 본문 § 멀티/듀얼 모니터 지원 | E13: 동일 문서 내 완전 동일 섹션 반복(크롤 레이아웃 이중화 추정) — 대표 RV-WEB-FEAT-013로 폴딩 | F13: RV-WEB-FEAT-013
... A248: 247 | B248: (폴딩·소급) | C248: https://content.rview.com/ko/?p=24107 | D248: 본문 § 현장 제어가 필요한 순간, | E248: [소급 정정 2026-07-13] URL 변형 이중 인입 — feature/rvbox-advanced/와 제목·본문 완전 일치 실측 (B6 사전 대조 중 발견). 당초 B2에서 신규 절단(오류) | F248: RV-WEB-FEAT-086

Sheet B2_근거약함
A1: Unit ID | B1: description | C1: source_location | D1: 상태 | E1: 비고 | F1: 사실(앞 150자)
A2: RV-WEB-HOME-003 | B2: 원격으로 해결 가능한데, | C2: 본문 § 원격으로 해결 가능한데, | D2: 근거약함 | E2: 본문 25자 미만 | F2: 아직도 현장에 가고 있나요? - 01
A3: RV-WEB-HOME-007 | B3: 어떤 현장이든, | C3: 본문 § 어떤 현장이든, | D3: 근거약함 | E3: 본문 25자 미만 | F3: 목적에 맞는 원격제어 리모트뷰가 있습니다 [
A4: RV-WEB-HOME-029 | B4: 리모트뷰의 다양한 소식을 | C4: 본문 § 리모트뷰의 다양한 소식을 | D4: 근거약함 | E4: 본문 25자 미만 | F4: 블로그로 만나보세요 인사이트
A5: RV-WEB-FEAT-060 | B5: 모니터 화면잠금 방식 설정 마법사로 | C5: 본문 § 모니터 화면잠금 방식 설정 마법사로 | D5: 근거약함 | E5: 본문 25자 미만 | F5: 간편하게 잠금 방법을 설정하세요
A6: RV-WEB-FEAT-067 | B6: 한 화면에 여러 대의 | C6: 본문 § 한 화면에 여러 대의 | D6: 근거약함 | E6: 본문 25자 미만 | F6: 모니터 모아 보기 ](#m2)
A7: RV-WEB-FEAT-068 | B7: 여러 대의 모니터를 | C7: 본문 § 여러 대의 모니터를 | D7: 근거약함 | E7: 본문 25자 미만 | F7: 개별 창으로 나누어 보기 ](#m3)
A8: RV-WEB-FEAT-077 | B8: (도입부) | C8: 본문 § (도입부) | D8: 근거약함 | E8: 본문 25자 미만 | F8: 더 완벽히 진화한 리모트뷰!
A9: RV-WEB-USES-001 | B9: "국내 8백만 다운로드, 네이트온 내PC제어 | C9: 본문 § "국내 8백만 다운로드, 네이트온 내PC제어 | D9: 근거약함 | E9: 사례 목록 페이지 — 개별 사실 단위 아님(개별 사례는 B5에서 절단) | F9: RemoteView가 제공하는 서비스인 것 알고 계셨나요?" 유수의 기업에 성공적으로 도입된 리모트뷰 생산성 증대와 효율적인 관리 · 운영 사례를 지금 바로 확인해보세요. 전체 IT·솔루션 공공기관 교육·문화 금융·투자 무인 기기 의료 제조 판매·서비스 [![](htt
A10: RV-WEB-USES-002 | B10: "국내 8백만 다운로드, 네이트온 내PC제어 | C10: 본문 § "국내 8백만 다운로드, 네이트온 내PC제어 | D10: 근거약함 | E10: 사례 목록 페이지 — 개별 사실 단위 아님(개별 사례는 B5에서 절단) | F10: RemoteView가 제공하는 서비스인 것 알고 계셨나요?" 유수의 기업에 성공적으로 도입된 리모트뷰 생산성 증대와 효율적인 관리 · 운영 사례를 지금 바로 확인해보세요. 전체 IT·솔루션 공공기관 교육·문화 금융·투자 무인 기기 의료 제조 판매·서비스 [![](htt

Sheet B2_사람확인
A1: Unit ID | B1: description | C1: source_location | D1: 상태 | E1: 비고 | F1: 사실(앞 150자)
A2: RV-WEB-FEAT-045 | B2: 용역업체 보안 관리, | C2: 본문 § 용역업체 보안 관리, | D2: 사람확인 | E2: 복합 내용 의심(장문 마케팅 섹션) — 재절단 검토 필요 | F2: 행정 효율까지 ‘AI 온라인 용역통제 시스템’으로 한 번에 국정원 가이드라인을 준수하고 AI 기반 지능형 관제로 보안 사각지대를 해소합니다. 전문가 상담받기 비교 자료 받기 ![온라인 용역통제 보안 기준을 확인하세요](/wp-content/uploads/sites/2/
A3: RV-WEB-FEAT-054 | B3: 어디서든 필요할 때 | C3: 본문 § 어디서든 필요할 때 | D3: 사람확인 | E3: 복합 내용 의심(장문 마케팅 섹션) — 재절단 검토 필요 | F3: 리모트뷰 모바일 원격제어 스마트폰으로 PC를 제어하는 리모트뷰 모바일 원격제어를 지금 체험해보세요. ![](/wp-content/uploads/sites/2/image/sub/controls_toast_icon.webp) 리모트뷰, 무엇이든 물어보세요 다음에 시간과 공
A4: RV-WEB-FEAT-063 | B4: 1분 만에 모여 한번에 해결 | C4: 본문 § 1분 만에 모여 한번에 해결 | D4: 사람확인 | E4: 복합 내용 의심(장문 마케팅 섹션) — 재절단 검토 필요 | F4: 리모트뷰 다중 접속 여러 사용자가 한 PC에 동시 접속! 지연 없는 협업으로 복잡한 문제도 단번에 해결하세요. 다중 접속 기능으로 협업 효율을 높이세요 최대 5명 동시 접속으로, 한자리에 모이지 않아도 문제 해결 팀원들은 각자의 자리에서 즉시 원격으로 접속해 문제를 함
A5: RV-WEB-FEAT-103 | B5: 설치 없이 브라우저로 | C5: 본문 § 설치 없이 브라우저로 | D5: 사람확인 | E5: 복합 내용 의심(장문 마케팅 섹션) — 재절단 검토 필요 | F5: 원격제어, 리모트뷰 웹뷰어 가장 쉽게, 익숙한 웹 브라우저로 원격 PC를 제어하세요. OS 제약이나 설치 없이, 3초 만에 안정적으로 연결됩니다. 편리함과 호환성, 속도 다 갖춘 웹뷰어 써보면 알아요. 사용자들이 왜 선호하는지 브라우저로 즉시 접속, 설치 없이 3초 만
A6: RV-WEB-PRICE-004 | B6: 패키지 | C6: 본문 § 패키지 | D6: 사람확인 | E6: 복합 내용 의심(장문 마케팅 섹션) — 재절단 검토 필요 / 가격 변동성 — 시점 앵커 필수, 정본 개정 시 재검토 대상 | F6: [시점 앵커: 2026-07-02 인덱싱 기준] - 100 - 300 - 무제한 대규모 기기 관리를 위한 고급형 상품 모바일 기기 지원 **35,000원** / 월 연간 결제 시 할인 혜택이 적용됩니다. 월 요금은 연 결제 기준으로 계산된 참고 금액입니다.
A7: RV-WEB-PRICE-005 | B7: 안정적인 원격 제어를 위한 | C7: 본문 § 안정적인 원격 제어를 위한 | D7: 사람확인 | E7: 복합 내용 의심(장문 마케팅 섹션) — 재절단 검토 필요 / 가격 변동성 — 시점 앵커 필수, 정본 개정 시 재검토 대상 | F7: [시점 앵커: 2026-07-02 인덱싱 기준] 리모트뷰 하드웨어 - ### RemoteViewBOX (KVM) 소프트웨어 설치없는 원격제어 하드웨어 3,000,000원50% 할인 1,500,000원 (부가세 별도) - OS 제약없이 4K 고화질 제어 가능 -
A8: RV-WEB-PROD-001 | B8: 용역업체 보안 관리, | C8: 본문 § 용역업체 보안 관리, | D8: 사람확인 | E8: 복합 내용 의심(장문 마케팅 섹션) — 재절단 검토 필요 | F8: 행정 효율까지 ‘AI 온라인 용역통제 시스템’으로 한 번에 국정원 가이드라인을 준수하고 AI 기반 지능형 관제로 보안 사각지대를 해소합니다. 전문가 상담받기 비교 자료 받기 ![온라인 용역통제 보안 기준을 확인하세요](/wp-content/uploads/sites/2/
A9: RV-WEB-PROD-002 | B9: 어디서든 필요할 때 | C9: 본문 § 어디서든 필요할 때 | D9: 사람확인 | E9: 복합 내용 의심(장문 마케팅 섹션) — 재절단 검토 필요 | F9: 리모트뷰 모바일 원격제어 스마트폰으로 PC를 제어하는 리모트뷰 모바일 원격제어를 지금 체험해보세요. ![](/wp-content/uploads/sites/2/image/sub/controls_toast_icon.webp) 리모트뷰, 무엇이든 물어보세요 다음에 시간과 공
A10: RV-WEB-PROD-037 | B10: 원격으로 | C10: 본문 § 원격으로 | D10: 사람확인 | E10: 복합 내용 의심(장문 마케팅 섹션) — 재절단 검토 필요 | F10: 서버·컴퓨터 전원을 켜는 가장 간단한 방법 RemoteWOL로 PC와 서버 전원을 제어해, 업무 효율성과 전력 비용 절감을 동시에 실현하세요. 원격으로 PC와 서버 전원을 제어해, 업무 효율성과 전력 비용 절감을 동시에 실현하세요. 원격 전원 관리가 필요한 순간 재택근
A11: RV-WEB-PROD-038 | B11: 원격으로 | C11: 본문 § 원격으로 (2차) | D11: 사람확인 | E11: 복합 내용 의심(장문 마케팅 섹션) — 재절단 검토 필요 | F11: 서버·컴퓨터 전원을 켜는 가장 간단한 방법 RemoteWOL로 PC와 서버 전원을 제어해, 업무 효율성과 전력 비용 절감을 동시에 실현하세요. 원격으로 PC와 서버 전원을 제어해, 업무 효율성과 전력 비용 절감을 동시에 실현하세요. 원격 전원 관리가 필요한 순간 재택근
A12: RV-WEB-PROD-039 | B12: 경쟁솔루션(VDI) 비교 | C12: 본문 § 경쟁솔루션(VDI) 비교 | D12: 사람확인 | E12: 복합 내용 의심(장문 마케팅 섹션) — 재절단 검토 필요 | F12: - RemoteView 란? 값비싼 데스크톱 가상화(VDI)? 가성비 높은 리모트뷰로 원격제어 하세요! 관련 콘텐츠 - [ 키오스크 설치 전, 이거 놓치면 진짜 낭패 봅니다! l 원격제어 리모트뷰 RemoteView 란? ](https://content.rvie
A13: RV-WEB-PROD-040 | B13: 설치 없이 브라우저로 | C13: 본문 § 설치 없이 브라우저로 | D13: 사람확인 | E13: 복합 내용 의심(장문 마케팅 섹션) — 재절단 검토 필요 | F13: 원격제어, 리모트뷰 웹뷰어 가장 쉽게, 익숙한 웹 브라우저로 원격 PC를 제어하세요. OS 제약이나 설치 없이, 3초 만에 안정적으로 연결됩니다. 편리함과 호환성, 속도 다 갖춘 웹뷰어 써보면 알아요. 사용자들이 왜 선호하는지 브라우저로 즉시 접속, 설치 없이 3초 만

Sheet B2_제외대장
A1: Unit ID | B1: 사유
A2: (해당 없음 — B2 제외 단위 0)

Sheet B2_계리
A1: 항목 | B1: 값 | C1: 수식/근거
A2: 총 절단(유지+폴딩) | B2: =B3+B8 | C2: 450이어야 함
A3: 본체 유지 | B3: =COUNTA(B2_커버리지맵!B:B)-1
A4: 미검토(유효) | B4: =COUNTIF(B2_커버리지맵!T:T,"미검토")
A5: 근거약함 | B5: =COUNTIF(B2_커버리지맵!T:T,"근거약함") | C5: 대장 일치
A6: 사람확인 | B6: =COUNTIF(B2_커버리지맵!T:T,"사람확인") | C6: 대장 일치
A7: 제외 | B7: =COUNTIF(B2_커버리지맵!T:T,"제외")
A8: 폴딩 | B8: =COUNTA(B2_폴딩대장!A:A)-1 | C8: 전량 대장 기재
A9: 본체 등식 검증 | B9: =SUM(B4:B7)-B3 | C9: 0이어야 함
A10: 소급 정정(2026-07-13) | C10: p=24107 단위 이관: 본체 −(위 폴딩 이관분), 폴딩 +. B6 사전 대조에서 rvbox-advanced 변형으로 판명. 총 절단 450 불변(유지분과 폴딩분 재배분)

Sheet B3_커버리지맵
A1: # | B1: Unit ID | C1: type | D1: title | E1: description | F1: product | G1: feature | H1: user_type | I1: acl_level | J1: intent | K1: source/resource | L1: source_location | M1: related_units | N1: 이 단위가 말하는 사실 | O1: 답변 가능한 질문 | P1: tags | Q1: citation_id | R1: extracted_by | S1: confidence | T1: 상태 | U1: 비고
A2: 1 | B2: RV-POLICY-TNC-001 | C2: Policy | D2: RemoteView 서비스 이용약관 | E2: 제1조(목적) 전문 | F2: RemoteView | G2: 약관 제1조 목적 | H2: 공통 | I2: 공개 | J2: 정책·계약 조건 확인 | K2: https://content.rview.com/ko/terms-and-conditions/ | L2: 본문 § 제1조(목적) / 전문 | N2: [시행 기준: 2021-02-16] 본 약관은 알서포트주식회사(이하 ‘회사’라 한다.)가 제공하는 서비스(회원 또는 이용고객이 PC, 휴대형 단말기 등 각종 유무선 기기와 인터넷을 통하여 원격제어 관련 서비스를 이용할 수 있도록 회사가 제공하는 인터넷 기반 원격 관련 서비스를 의미합니다.)와 관련하여, 회사와 회원간에 서비스의 이용조건 및 절차, 회사와 회원간의 권리와 의무사항 및 기타 필요한 제반사항의 규정을 목적으로 합니다. | O2: RemoteView 이용약관 제1조(목적)의 내용은 무엇인가요? | P2: RemoteView, 약관, 목적 | Q2: RV-POLICY-TNC-001 | R2: Claude(Fable5) | S2: 상 | T2: 미검토 | U2: F형 소재 후보(권한·책임 경계)
A3: 2 | B3: RV-POLICY-TNC-002 | C3: Policy | D3: RemoteView 서비스 이용약관 | E3: 제2조(용어의 정의) 0항 | F3: RemoteView | G3: 약관 제2조 용어의 정의 | H3: 공통 | I3: 공개 | J3: 정책·계약 조건 확인 | K3: https://content.rview.com/ko/terms-and-conditions/ | L3: 본문 § 제2조(용어의 정의) / 0항 | N3: [시행 기준: 2021-02-16] 본 약관에서 사용하는 용어는 다음과 같습니다. | O3: RemoteView 이용약관 제2조(용어의 정의)의 내용은 무엇인가요? | P3: RemoteView, 약관, 용어의 정의 | Q3: RV-POLICY-TNC-002 | R3: Claude(Fable5) | S3: 상 | T3: 미검토
A4: 3 | B4: RV-POLICY-TNC-003 | C4: Policy | D4: RemoteView 서비스 이용약관 | E4: 제2조(용어의 정의) 1항 | F4: RemoteView | G4: 약관 제2조 용어의 정의 | H4: 공통 | I4: 공개 | J4: 정책·계약 조건 확인 | K4: https://content.rview.com/ko/terms-and-conditions/ | L4: 본문 § 제2조(용어의 정의) / 1항 | N4: [시행 기준: 2021-02-16] 회원 : 회사가 운영하는 사이트에 접속하여 이 약관에 동의하고, 아이디와 비밀번호를 발급받아 회사가 제공하는 서비스를 이용하는 자를 말하며, 정회원과 일반회원으로 구분됩니다. 1. 정회원 : 유료서비스 이용계약의 당사로 회사에 서비스 가입신청서를 제출하고, 회사가 승인한 자로서 이용요금의 납입의무를 가진 법인이나 개인 2. 일반회원 : 회사가 운영하는 사이트의 이용약관에 동의하고, ‘이용신청 및 승낙’ 절차에 의하여 회원 등록된 자 | O4: RemoteView 이용약관 제2조(용어의 정의)의 내용은 무엇인가요? | P4: RemoteView, 약관, 용어의 정의 | Q4: RV-POLICY-TNC-003 | R4: Claude(Fable5) | S4: 상 | T4: 미검토 | U4: F형 소재 후보(권한·책임 경계)
A5: 4 | B5: RV-POLICY-TNC-004 | C5: Policy | D5: RemoteView 서비스 이용약관 | E5: 제2조(용어의 정의) 2항 | F5: RemoteView | G5: 약관 제2조 용어의 정의 | H5: 공통 | I5: 공개 | J5: 정책·계약 조건 확인 | K5: https://content.rview.com/ko/terms-and-conditions/ | L5: 본문 § 제2조(용어의 정의) / 2항 | N5: [시행 기준: 2021-02-16] 아이디 : 회원 식별과 서비스 이용을 위하여 회원이 선정하고 회사가 승인하는 고유번호로 문자와 숫자의 조합, 또는 경우에 따라 회원의 이메일주소 | O5: RemoteView 이용약관 제2조(용어의 정의)의 내용은 무엇인가요? | P5: RemoteView, 약관, 용어의 정의 | Q5: RV-POLICY-TNC-004 | R5: Claude(Fable5) | S5: 상 | T5: 미검토
A6: 5 | B6: RV-POLICY-TNC-005 | C6: Policy | D6: RemoteView 서비스 이용약관 | E6: 제2조(용어의 정의) 3항 | F6: RemoteView | G6: 약관 제2조 용어의 정의 | H6: 공통 | I6: 공개 | J6: 정책·계약 조건 확인 | K6: https://content.rview.com/ko/terms-and-conditions/ | L6: 본문 § 제2조(용어의 정의) / 3항 | N6: [시행 기준: 2021-02-16] 비밀번호(패스워드) : 회원이 부여 받은 아이디에 대하여 회원이 통신상에서 자신의 비밀 보호를 위하여 선정한 문자와 숫자, 특수문자의 조합 | O6: RemoteView 이용약관 제2조(용어의 정의)의 내용은 무엇인가요? | P6: RemoteView, 약관, 용어의 정의 | Q6: RV-POLICY-TNC-005 | R6: Claude(Fable5) | S6: 상 | T6: 미검토
A7: 6 | B7: RV-POLICY-TNC-006 | C7: Policy | D7: RemoteView 서비스 이용약관 | E7: 제2조(용어의 정의) 4항 | F7: RemoteView | G7: 약관 제2조 용어의 정의 | H7: 공통 | I7: 공개 | J7: 정책·계약 조건 확인 | K7: https://content.rview.com/ko/terms-and-conditions/ | L7: 본문 § 제2조(용어의 정의) / 4항 | N7: [시행 기준: 2021-02-16] 이용계약 : 서비스 이용과 관련하여 회사와 회원 간에 체결하는 계약 | O7: RemoteView 이용약관 제2조(용어의 정의)의 내용은 무엇인가요? | P7: RemoteView, 약관, 용어의 정의 | Q7: RV-POLICY-TNC-006 | R7: Claude(Fable5) | S7: 상 | T7: 미검토
A8: 7 | B8: RV-POLICY-TNC-007 | C8: Policy | D8: RemoteView 서비스 이용약관 | E8: 제2조(용어의 정의) 5항 | F8: RemoteView | G8: 약관 제2조 용어의 정의 | H8: 공통 | I8: 공개 | J8: 정책·계약 조건 확인 | K8: https://content.rview.com/ko/terms-and-conditions/ | L8: 본문 § 제2조(용어의 정의) / 5항 | N8: [시행 기준: 2021-02-16] 서비스 : 회원 또는 이용자가 PC, 휴대형 단말기 등 각종 유무선 기기와 인터넷을 통하여 원거리의 내 PC를 안전하게 실시간으로 제어할 수 있는 서비스를 이용할 수 있도록 회사가 제공하는 인터넷 기반 제반 서비스 | O8: RemoteView 이용약관 제2조(용어의 정의)의 내용은 무엇인가요? | P8: RemoteView, 약관, 용어의 정의 | Q8: RV-POLICY-TNC-007 | R8: Claude(Fable5) | S8: 상 | T8: 미검토
A9: 8 | B9: RV-POLICY-TNC-008 | C9: Policy | D9: RemoteView 서비스 이용약관 | E9: 제2조(용어의 정의) 6항 | F9: RemoteView | G9: 약관 제2조 용어의 정의 | H9: 공통 | I9: 공개 | J9: 정책·계약 조건 확인 | K9: https://content.rview.com/ko/terms-and-conditions/ | L9: 본문 § 제2조(용어의 정의) / 6항 | N9: [시행 기준: 2021-02-16] 계약해지 : 회사 또는 회원(회원 신청자 포함)이 서비스 개통 후 장래에 향해 서비스 이용계약을 해약하는 것 | O9: RemoteView 이용약관 제2조(용어의 정의)의 내용은 무엇인가요? | P9: RemoteView, 약관, 용어의 정의 | Q9: RV-POLICY-TNC-008 | R9: Claude(Fable5) | S9: 상 | T9: 미검토 | U9: F형 소재 후보(권한·책임 경계)
A10: 9 | B10: RV-POLICY-TNC-009 | C10: Policy | D10: RemoteView 서비스 이용약관 | E10: 제2조(용어의 정의) 7항 | F10: RemoteView | G10: 약관 제2조 용어의 정의 | H10: 공통 | I10: 공개 | J10: 정책·계약 조건 확인 | K10: https://content.rview.com/ko/terms-and-conditions/ | L10: 본문 § 제2조(용어의 정의) / 7항 | N10: [시행 기준: 2021-02-16] 계약해제 : 회사 또는 회원 신청자가 서비스 개통 전 서비스 이용계약을 해약하는 것 | O10: RemoteView 이용약관 제2조(용어의 정의)의 내용은 무엇인가요? | P10: RemoteView, 약관, 용어의 정의 | Q10: RV-POLICY-TNC-009 | R10: Claude(Fable5) | S10: 상 | T10: 미검토
A11: 10 | B11: RV-POLICY-TNC-010 | C11: Policy | D11: RemoteView 서비스 이용약관 | E11: 제2조(용어의 정의) 8항 | F11: RemoteView | G11: 약관 제2조 용어의 정의 | H11: 공통 | I11: 공개 | J11: 정책·계약 조건 확인 | K11: https://content.rview.com/ko/terms-and-conditions/ | L11: 본문 § 제2조(용어의 정의) / 8항 | N11: [시행 기준: 2021-02-16] 서비스 개통일 : 회원의 서비스 이용신청 후, 회원이 해당 서비스를 이용할 수 있도록 회사가 필요한 조치하여 완료한 일자 | O11: RemoteView 이용약관 제2조(용어의 정의)의 내용은 무엇인가요? | P11: RemoteView, 약관, 용어의 정의 | Q11: RV-POLICY-TNC-010 | R11: Claude(Fable5) | S11: 상 | T11: 미검토
A12: 11 | B12: RV-POLICY-TNC-011 | C12: Policy | D12: RemoteView 서비스 이용약관 | E12: 제2조(용어의 정의) 9항 | F12: RemoteView | G12: 약관 제2조 용어의 정의 | H12: 공통 | I12: 공개 | J12: 정책·계약 조건 확인 | K12: https://content.rview.com/ko/terms-and-conditions/ | L12: 본문 § 제2조(용어의 정의) / 9항 | N12: [시행 기준: 2021-02-16] 불법통신 : 음란한 내용, 비방.허위사실에 의한 타인 명예훼손, 불법복제 등 지적재산권침해, 국가기밀 침해, 청소년보호법상 청소년 유해 매체물 등이 포함된 통신 | O12: RemoteView 이용약관 제2조(용어의 정의)의 내용은 무엇인가요? | P12: RemoteView, 약관, 용어의 정의 | Q12: RV-POLICY-TNC-011 | R12: Claude(Fable5) | S12: 상 | T12: 미검토
A13: 12 | B13: RV-POLICY-TNC-012 | C13: Policy | D13: RemoteView 서비스 이용약관 | E13: 제2조(용어의 정의) 10항 | F13: RemoteView | G13: 약관 제2조 용어의 정의 | H13: 공통 | I13: 공개 | J13: 정책·계약 조건 확인 | K13: https://content.rview.com/ko/terms-and-conditions/ | L13: 본문 § 제2조(용어의 정의) / 10항 | N13: [시행 기준: 2021-02-16] 게시물 : 회원이 서비스를 이용함에 있어 단말기(PC, 휴대형 단말기, TV 등의 각종 유무선 장치를 포함) 또는 회사 홈페이지 등에 게시한 부호ㆍ문자ㆍ음성ㆍ음향ㆍ화상ㆍ동영상 등의 정보 형태의 글, 사진, 동영상 및 각종 파일과 링크 등 | O13: RemoteView 이용약관 제2조(용어의 정의)의 내용은 무엇인가요? | P13: RemoteView, 약관, 용어의 정의 | Q13: RV-POLICY-TNC-012 | R13: Claude(Fable5) | S13: 상 | T13: 미검토
A14: 13 | B14: RV-POLICY-TNC-013 | C14: Policy | D14: RemoteView 서비스 이용약관 | E14: 제2조(용어의 정의) 11항 | F14: RemoteView | G14: 약관 제2조 용어의 정의 | H14: 공통 | I14: 공개 | J14: 정책·계약 조건 확인 | K14: https://content.rview.com/ko/terms-and-conditions/ | L14: 본문 § 제2조(용어의 정의) / 11항 | N14: [시행 기준: 2021-02-16] 결제대행 사업자 : 회원에게 다양한 결제수단을 선택할 수 있도록 하기 위하여 회사가 지정한 전자지불 서비스를 대행하는 전문 업체 | O14: RemoteView 이용약관 제2조(용어의 정의)의 내용은 무엇인가요? | P14: RemoteView, 약관, 용어의 정의 | Q14: RV-POLICY-TNC-013 | R14: Claude(Fable5) | S14: 상 | T14: 미검토
A15: 14 | B15: RV-POLICY-TNC-014 | C15: Policy | D15: RemoteView 서비스 이용약관 | E15: 제2조(용어의 정의) 12항 | F15: RemoteView | G15: 약관 제2조 용어의 정의 | H15: 공통 | I15: 공개 | J15: 정책·계약 조건 확인 | K15: https://content.rview.com/ko/terms-and-conditions/ | L15: 본문 § 제2조(용어의 정의) / 12항 | N15: [시행 기준: 2021-02-16] 이용요금 : 이용자가 서비스를 이용하기 위해 회사에 지불하는 사용료 | O15: RemoteView 이용약관 제2조(용어의 정의)의 내용은 무엇인가요? | P15: RemoteView, 약관, 용어의 정의 | Q15: RV-POLICY-TNC-014 | R15: Claude(Fable5) | S15: 상 | T15: 미검토
A16: 15 | B16: RV-POLICY-TNC-015 | C16: Policy | D16: RemoteView 서비스 이용약관 | E16: 제3조(약관의 효력 및 변경) 1항 | F16: RemoteView | G16: 약관 제3조 약관의 효력 및 변경 | H16: 공통 | I16: 공개 | J16: 정책·계약 조건 확인 | K16: https://content.rview.com/ko/terms-and-conditions/ | L16: 본문 § 제3조(약관의 효력 및 변경) / 1항 | N16: [시행 기준: 2021-02-16] 본 약관은 제품 홈페이지(https://rview.com) 에 공시함으로써 효력이 발생합니다. | O16: RemoteView 이용약관 제3조(약관의 효력 및 변경)의 내용은 무엇인가요? | P16: RemoteView, 약관, 약관의 효력 및 변경 | Q16: RV-POLICY-TNC-015 | R16: Claude(Fable5) | S16: 상 | T16: 미검토
A17: 16 | B17: RV-POLICY-TNC-016 | C17: Policy | D17: RemoteView 서비스 이용약관 | E17: 제3조(약관의 효력 및 변경) 2항 | F17: RemoteView | G17: 약관 제3조 약관의 효력 및 변경 | H17: 공통 | I17: 공개 | J17: 정책·계약 조건 확인 | K17: https://content.rview.com/ko/terms-and-conditions/ | L17: 본문 § 제3조(약관의 효력 및 변경) / 2항 | N17: [시행 기준: 2021-02-16] 이 약관에 동의하고 회원가입을 한 회원은 약관에 동의한 시점부터 동의한 약관의 적용을 받고 약관의 변경이 있을 경우에는 변경의 효력이 발생한 시점부터 변경된 약관의 적용을 받습니다. | O17: RemoteView 이용약관 제3조(약관의 효력 및 변경)의 내용은 무엇인가요? | P17: RemoteView, 약관, 약관의 효력 및 변경 | Q17: RV-POLICY-TNC-016 | R17: Claude(Fable5) | S17: 상 | T17: 미검토
A18: 17 | B18: RV-POLICY-TNC-017 | C18: Policy | D18: RemoteView 서비스 이용약관 | E18: 제3조(약관의 효력 및 변경) 3항 | F18: RemoteView | G18: 약관 제3조 약관의 효력 및 변경 | H18: 공통 | I18: 공개 | J18: 정책·계약 조건 확인 | K18: https://content.rview.com/ko/terms-and-conditions/ | L18: 본문 § 제3조(약관의 효력 및 변경) / 3항 | N18: [시행 기준: 2021-02-16] 회사는 필요하다고 인정되는 경우 이 약관을 변경할 수 있습니다. 회사는 약관이 변경되는 경우에 변경된 약관의 내용과 적용일을 정하여, 그 적용일로부터 7일전(단 변경된 내용이 회원에게 불리하거나 중대한 사항의 변경인 경우에는 30일전)까지 홈페이지에 공지하거나 회원의 이메일로 전난희는 방법으로 회원에게 고지합니다. 변경된 약관은 공시하거나 고지한 적용일로부터 효력을 발생합니다. | O18: RemoteView 이용약관 제3조(약관의 효력 및 변경)의 내용은 무엇인가요? | P18: RemoteView, 약관, 약관의 효력 및 변경 | Q18: RV-POLICY-TNC-017 | R18: Claude(Fable5) | S18: 상 | T18: 미검토
A19: 18 | B19: RV-POLICY-TNC-018 | C19: Policy | D19: RemoteView 서비스 이용약관 | E19: 제3조(약관의 효력 및 변경) 4항 | F19: RemoteView | G19: 약관 제3조 약관의 효력 및 변경 | H19: 공통 | I19: 공개 | J19: 정책·계약 조건 확인 | K19: https://content.rview.com/ko/terms-and-conditions/ | L19: 본문 § 제3조(약관의 효력 및 변경) / 4항 | N19: [시행 기준: 2021-02-16] 본 약관의 변경에 대해 동의하지 않는 회원은 서비스 이용을 중단하고 이용계약을 해지(회원탈퇴) 할 수 있습니다. 약관 시행일까지 회원탈퇴를 하지 않은 회원은 개정약관에 동의한 것으로 간주합니다. | O19: RemoteView 이용약관 제3조(약관의 효력 및 변경)의 내용은 무엇인가요? | P19: RemoteView, 약관, 약관의 효력 및 변경 | Q19: RV-POLICY-TNC-018 | R19: Claude(Fable5) | S19: 상 | T19: 미검토 | U19: F형 소재 후보(권한·책임 경계)
A20: 19 | B20: RV-POLICY-TNC-019 | C20: Policy | D20: RemoteView 서비스 이용약관 | E20: 제4조(약관의 적용 및 이외 준칙) 전문 | F20: RemoteView | G20: 약관 제4조 약관의 적용 및 이외 준칙 | H20: 공통 | I20: 공개 | J20: 정책·계약 조건 확인 | K20: https://content.rview.com/ko/terms-and-conditions/ | L20: 본문 § 제4조(약관의 적용 및 이외 준칙) / 전문 | N20: [시행 기준: 2021-02-16] 1. 회사는 서비스 특성에 따라 개별 서비스별로 별도의 이용약관 및 규정을 제공할 수 있으며, 본 약관에 명시되지 아니한 사항에 대해서는 ‘전자상거래 등에서의 소비자보호에 관한 법률(이하 ‘전자상거래법’), ‘정보통신망이용촉진 및 정보보호 등에 관한 법률(이하 ‘정보통신망법’)’ 등 관계법령, 회사가 제공하는 서비스에 관한 별도의 약관, 이용규정 등에 따릅니다. | O20: RemoteView 이용약관 제4조(약관의 적용 및 이외 준칙)의 내용은 무엇인가요? | P20: RemoteView, 약관, 약관의 적용 및 이외 준칙 | Q20: RV-POLICY-TNC-019 | R20: Claude(Fable5) | S20: 상 | T20: 미검토
A21: 20 | B21: RV-POLICY-TNC-020 | C21: Policy | D21: RemoteView 서비스 이용약관 | E21: 제5조(이용계약의 성립) 1항 | F21: RemoteView | G21: 약관 제5조 이용계약의 성립 | H21: 공통 | I21: 공개 | J21: 정책·계약 조건 확인 | K21: https://content.rview.com/ko/terms-and-conditions/ | L21: 본문 § 제5조(이용계약의 성립) / 1항 | N21: [시행 기준: 2021-02-16] 이용계약은 회사가 제공하는 서비스의 이용을 원하는 회원이 본 약관의 내용에 동의를 한 다음 회사가 제시하는 양식과 절차에 따라 이용신청을 하고, 그 신청한 내용에 대하여 회사가 승낙함으로써 회사와 회원간에 성립됩니다. | O21: RemoteView 이용약관 제5조(이용계약의 성립)의 내용은 무엇인가요? | P21: RemoteView, 약관, 이용계약의 성립 | Q21: RV-POLICY-TNC-020 | R21: Claude(Fable5) | S21: 상 | T21: 미검토 | U21: F형 소재 후보(권한·책임 경계)
A22: 21 | B22: RV-POLICY-TNC-021 | C22: Policy | D22: RemoteView 서비스 이용약관 | E22: 제5조(이용계약의 성립) 2항 | F22: RemoteView | G22: 약관 제5조 이용계약의 성립 | H22: 공통 | I22: 공개 | J22: 정책·계약 조건 확인 | K22: https://content.rview.com/ko/terms-and-conditions/ | L22: 본문 § 제5조(이용계약의 성립) / 2항 | N22: [시행 기준: 2021-02-16] 본 이용약관에 대한 동의의 의사표시는 서비스를 이용하고자 하는 자가 이용 신청 시 본 약관에 동의 체크를 함으로써 완료됩니다. | O22: RemoteView 이용약관 제5조(이용계약의 성립)의 내용은 무엇인가요? | P22: RemoteView, 약관, 이용계약의 성립 | Q22: RV-POLICY-TNC-021 | R22: Claude(Fable5) | S22: 상 | T22: 미검토
A23: 22 | B23: RV-POLICY-TNC-022 | C23: Policy | D23: RemoteView 서비스 이용약관 | E23: 제5조(이용계약의 성립) 3항 | F23: RemoteView | G23: 약관 제5조 이용계약의 성립 | H23: 공통 | I23: 공개 | J23: 정책·계약 조건 확인 | K23: https://content.rview.com/ko/terms-and-conditions/ | L23: 본문 § 제5조(이용계약의 성립) / 3항 | N23: [시행 기준: 2021-02-16] 이용계약이 성립되면 회사는 회원에게 본 약관이 정하는 바에 따라 회원 아이디를 부여합니다. 회원 아이디는 원칙적으로 변경이 불가능합니다. | O23: RemoteView 이용약관 제5조(이용계약의 성립)의 내용은 무엇인가요? | P23: RemoteView, 약관, 이용계약의 성립 | Q23: RV-POLICY-TNC-022 | R23: Claude(Fable5) | S23: 상 | T23: 미검토
A24: 23 | B24: RV-POLICY-TNC-023 | C24: Policy | D24: RemoteView 서비스 이용약관 | E24: 제5조(이용계약의 성립) 4항 | F24: RemoteView | G24: 약관 제5조 이용계약의 성립 | H24: 공통 | I24: 공개 | J24: 정책·계약 조건 확인 | K24: https://content.rview.com/ko/terms-and-conditions/ | L24: 본문 § 제5조(이용계약의 성립) / 4항 | N24: [시행 기준: 2021-02-16] 온라인 이용신청 양식에 기입하는 모든 정보는 실제 데이터인 것으로 간주하며 실명이나 실제 정보를 입력하지 않은 회원은 법적인 보호를 받을 수 없습니다. | O24: RemoteView 이용약관 제5조(이용계약의 성립)의 내용은 무엇인가요? | P24: RemoteView, 약관, 이용계약의 성립 | Q24: RV-POLICY-TNC-023 | R24: Claude(Fable5) | S24: 상 | T24: 미검토
A25: 24 | B25: RV-POLICY-TNC-024 | C25: Policy | D25: RemoteView 서비스 이용약관 | E25: 제6조(이용신청) 1항 | F25: RemoteView | G25: 약관 제6조 이용신청 | H25: 공통 | I25: 공개 | J25: 정책·계약 조건 확인 | K25: https://content.rview.com/ko/terms-and-conditions/ | L25: 본문 § 제6조(이용신청) / 1항 | N25: [시행 기준: 2021-02-16] 이용신청은 홈페이지의 회원 가입 화면(또는 서비스의 이용자 등록 화면)에서 회원이 다음 사항을 가입신청 양식에 기록하는 방식으로 행합니다. 1. 아이디 2. 비밀번호 3. 회원이름 4. 상호이름(회원이 속한 회사이름) 5. 국가 선택 6. 연락처(전화번호, 휴대폰번호) | O25: RemoteView 이용약관 제6조(이용신청)의 내용은 무엇인가요? | P25: RemoteView, 약관, 이용신청 | Q25: RV-POLICY-TNC-024 | R25: Claude(Fable5) | S25: 상 | T25: 미검토
A26: 25 | B26: RV-POLICY-TNC-025 | C26: Policy | D26: RemoteView 서비스 이용약관 | E26: 제6조(이용신청) 2항 | F26: RemoteView | G26: 약관 제6조 이용신청 | H26: 공통 | I26: 공개 | J26: 정책·계약 조건 확인 | K26: https://content.rview.com/ko/terms-and-conditions/ | L26: 본문 § 제6조(이용신청) / 2항 | N26: [시행 기준: 2021-02-16] 유료 서비스를 이용하고자 하는 회원은 상기 1항과 별도로 다음 각호의 서류를 방문, 우편, 팩스 등 기타 회사가 인정하는 방식으로 회사에 제출하여야 합니다. 다만, 앱스토어 사업자와 연계된 방법으로 결제가 이루어지는 개인 대상 서비스의 경우에는 예외로 할 수 있습니다. 1. 서비스 가입신청서(소정양식) 2. 요금납입책임자의 사업자등록증(개인의 경우 주민등록증 사본) 3. 기타 신원확인, 요금납입 등을 위하여 회사가 요청하는 부대 서류 | O26: RemoteView 이용약관 제6조(이용신청)의 내용은 무엇인가요? | P26: RemoteView, 약관, 이용신청 | Q26: RV-POLICY-TNC-025 | R26: Claude(Fable5) | S26: 상 | T26: 미검토 | U26: F형 소재 후보(권한·책임 경계)
A27: 26 | B27: RV-POLICY-TNC-026 | C27: Policy | D27: RemoteView 서비스 이용약관 | E27: 제6조(이용신청) 3항 | F27: RemoteView | G27: 약관 제6조 이용신청 | H27: 공통 | I27: 공개 | J27: 정책·계약 조건 확인 | K27: https://content.rview.com/ko/terms-and-conditions/ | L27: 본문 § 제6조(이용신청) / 3항 | N27: [시행 기준: 2021-02-16] 이용신청회원이 미성년자 또는 한정치산자인 경우에는 신청자 및 요금납입책임자를 부모 또는 법정대리인으로 하여 이용신청을 하여야 합니다. | O27: RemoteView 이용약관 제6조(이용신청)의 내용은 무엇인가요? | P27: RemoteView, 약관, 이용신청 | Q27: RV-POLICY-TNC-026 | R27: Claude(Fable5) | S27: 상 | T27: 미검토 | U27: F형 소재 후보(권한·책임 경계)
A28: 27 | B28: RV-POLICY-TNC-027 | C28: Policy | D28: RemoteView 서비스 이용약관 | E28: 제7조(이용신청의 승낙 및 승낙유보) 전문 | F28: RemoteView | G28: 약관 제7조 이용신청의 승낙 및 승낙유보 | H28: 공통 | I28: 공개 | J28: 정책·계약 조건 확인 | K28: https://content.rview.com/ko/terms-and-conditions/ | L28: 본문 § 제7조(이용신청의 승낙 및 승낙유보) / 전문 | N28: [시행 기준: 2021-02-16] 1. 회원의 신청에 대하여 약관조건, 업무상 또는 기술상 문제가 없는 경우 서비스 이용을 승낙함을 원칙으로 합니다. 다만, 회사는 다음 각 호에 해당하는 신청에 대하여 승낙을 유보하거나 거절할 수 있습니다. 1. 본인의 실명을 사용하지 않고, 타인의 명의로 신청한 경우 2. 가입신청서의 내용을 허위로 기재하였거나 허위의 서류를 첨부하여 신청한 경우 3. 회사가 서비스를 제공하지 않은 국가에서 비정상적이거나 우회적인 방법을 통해 서비스를 이용하는 경우 4. 공공의 안녕질서 및 미풍양속을 해할 우려가 있는 경우 5. 신용정보의 이용 및 보호에 관한 법률에 의한 신용불량자로 등록되어 있는 경우 6. 회사에 미납요금이 있는 경우 7. 회사의 설비에 여유가 없거나 기술상 서비스 제공이 어려운 경우 8. 이용신청자의 귀책사유로 이용승낙이 곤란한 경우 9. 기타 회사가 필요하다고 인정하는 경우 | O28: RemoteView 이용약관 제7조(이용신청의 승낙 및 승낙유보)의 내용은 무엇인가요? | P28: RemoteView, 약관, 이용신청의 승낙 및 승낙유보 | Q28: RV-POLICY-TNC-027 | R28: Claude(Fable5) | S28: 상 | T28: 미검토 | U28: F형 소재 후보(권한·책임 경계)
A29: 28 | B29: RV-POLICY-TNC-028 | C29: Policy | D29: RemoteView 서비스 이용약관 | E29: 제8조(이용계약 사항의 변경) 전문 | F29: RemoteView | G29: 약관 제8조 이용계약 사항의 변경 | H29: 공통 | I29: 공개 | J29: 정책·계약 조건 확인 | K29: https://content.rview.com/ko/terms-and-conditions/ | L29: 본문 § 제8조(이용계약 사항의 변경) / 전문 | N29: [시행 기준: 2021-02-16] 1. 회원은 다음 각호 해당하는 사유가 발생한 경우에는 사유발생 즉시 이메일 또는 회사가 안내에 따라 변경사항을 회사에 알려야 합니다. 1. 회원 및 요금납입책임자의 상호, 성명, 주소 또는 연락처의 변경 2. 서비스의 내용(종류, 계약기간 등)의 변경 3. 요금납부 방식의 변경 | O29: RemoteView 이용약관 제8조(이용계약 사항의 변경)의 내용은 무엇인가요? | P29: RemoteView, 약관, 이용계약 사항의 변경 | Q29: RV-POLICY-TNC-028 | R29: Claude(Fable5) | S29: 상 | T29: 미검토 | U29: F형 소재 후보(권한·책임 경계)
A30: 29 | B30: RV-POLICY-TNC-029 | C30: Policy | D30: RemoteView 서비스 이용약관 | E30: 제9조(계약의 해지) 1항 | F30: RemoteView | G30: 약관 제9조 계약의 해지 | H30: 공통 | I30: 공개 | J30: 정책·계약 조건 확인 | K30: https://content.rview.com/ko/terms-and-conditions/ | L30: 본문 § 제9조(계약의 해지) / 1항 | N30: [시행 기준: 2021-02-16] 회원이 계약을 해지하고자 하는 경우에는 회원 본인이 직접 온라인, 전화, 팩스, 이메일 등의 방법으로 해약 7일전까지 회사에 해지신청서를 제출해야 합니다. | O30: RemoteView 이용약관 제9조(계약의 해지)의 내용은 무엇인가요? | P30: RemoteView, 약관, 계약의 해지 | Q30: RV-POLICY-TNC-029 | R30: Claude(Fable5) | S30: 상 | T30: 미검토 | U30: F형 소재 후보(권한·책임 경계)
A31: 30 | B31: RV-POLICY-TNC-030 | C31: Policy | D31: RemoteView 서비스 이용약관 | E31: 제9조(계약의 해지) 2항 | F31: RemoteView | G31: 약관 제9조 계약의 해지 | H31: 공통 | I31: 공개 | J31: 정책·계약 조건 확인 | K31: https://content.rview.com/ko/terms-and-conditions/ | L31: 본문 § 제9조(계약의 해지) / 2항 | N31: [시행 기준: 2021-02-16] 회원의 해지요청에 따라 서비스가 해지된 후 발생된 게시물 또는 회원정보 소멸 등에 대한 책임은 회원에게 있으며, 회사에 이로 인한 손해배상을 청구할 수 없습니다. | O31: RemoteView 이용약관 제9조(계약의 해지)의 내용은 무엇인가요? | P31: RemoteView, 약관, 계약의 해지 | Q31: RV-POLICY-TNC-030 | R31: Claude(Fable5) | S31: 상 | T31: 미검토 | U31: F형 소재 후보(권한·책임 경계)
A32: 31 | B32: RV-POLICY-TNC-031 | C32: Policy | D32: RemoteView 서비스 이용약관 | E32: 제9조(계약의 해지) 3항 | F32: RemoteView | G32: 약관 제9조 계약의 해지 | H32: 공통 | I32: 공개 | J32: 정책·계약 조건 확인 | K32: https://content.rview.com/ko/terms-and-conditions/ | L32: 본문 § 제9조(계약의 해지) / 3항 | N32: [시행 기준: 2021-02-16] 회사는 다음 각호의 경우에는 계약을 해지할 수 있습니다. 1. 회원이 제29조(서비스 이용제한)에 관한 각호의 사유에 해당하는 경우 2. 회원이 제32조(회원의 의무)에 관한 조항을 위반한 경우 | O32: RemoteView 이용약관 제9조(계약의 해지)의 내용은 무엇인가요? | P32: RemoteView, 약관, 계약의 해지 | Q32: RV-POLICY-TNC-031 | R32: Claude(Fable5) | S32: 상 | T32: 미검토 | U32: F형 소재 후보(권한·책임 경계)
A33: 32 | B33: RV-POLICY-TNC-032 | C33: Policy | D33: RemoteView 서비스 이용약관 | E33: 제10조(서비스의 개시/개통) 1항 | F33: RemoteView | G33: 약관 제10조 서비스의 개시/개통 | H33: 공통 | I33: 공개 | J33: 정책·계약 조건 확인 | K33: https://content.rview.com/ko/terms-and-conditions/ | L33: 본문 § 제10조(서비스의 개시/개통) / 1항 | N33: [시행 기준: 2021-02-16] 회사는 회원의 이용신청을 승낙하고, 회사와 회원간에 상호 협의한 경우를 제외하고는 회사에서 제시한 절차에 따라 서비스 이용료를 선불로 납입한 때부터 서비스가 개시됨을 원칙으로 합니다. | O33: RemoteView 이용약관 제10조(서비스의 개시/개통)의 내용은 무엇인가요? | P33: RemoteView, 약관, 서비스의 개시/개통 | Q33: RV-POLICY-TNC-032 | R33: Claude(Fable5) | S33: 상 | T33: 미검토 | U33: F형 소재 후보(권한·책임 경계)
A34: 33 | B34: RV-POLICY-TNC-033 | C34: Policy | D34: RemoteView 서비스 이용약관 | E34: 제10조(서비스의 개시/개통) 2항 | F34: RemoteView | G34: 약관 제10조 서비스의 개시/개통 | H34: 공통 | I34: 공개 | J34: 정책·계약 조건 확인 | K34: https://content.rview.com/ko/terms-and-conditions/ | L34: 본문 § 제10조(서비스의 개시/개통) / 2항 | N34: [시행 기준: 2021-02-16] 회사는 회사의 업무상 또는 기술상의 장애로 인하여 서비스를 개시/개통하지 못하는 경우에는 홈페이지 또는 개별 서비스 관련 홈페이지에 공시하거나 회원에게 이를 통지합니다. | O34: RemoteView 이용약관 제10조(서비스의 개시/개통)의 내용은 무엇인가요? | P34: RemoteView, 약관, 서비스의 개시/개통 | Q34: RV-POLICY-TNC-033 | R34: Claude(Fable5) | S34: 상 | T34: 미검토
A35: 34 | B35: RV-POLICY-TNC-034 | C35: Policy | D35: RemoteView 서비스 이용약관 | E35: 제11조(서비스의 이용시간) 1항 | F35: RemoteView | G35: 약관 제11조 서비스의 이용시간 | H35: 공통 | I35: 공개 | J35: 정책·계약 조건 확인 | K35: https://content.rview.com/ko/terms-and-conditions/ | L35: 본문 § 제11조(서비스의 이용시간) / 1항 | N35: [시행 기준: 2021-02-16] 회원은 본 약관이 정하는 바에 따라 회사가 제공하는 서비스를 이용할 수 있습니다. | O35: RemoteView 이용약관 제11조(서비스의 이용시간)의 내용은 무엇인가요? | P35: RemoteView, 약관, 서비스의 이용시간 | Q35: RV-POLICY-TNC-034 | R35: Claude(Fable5) | S35: 상 | T35: 미검토
A36: 35 | B36: RV-POLICY-TNC-035 | C36: Policy | D36: RemoteView 서비스 이용약관 | E36: 제11조(서비스의 이용시간) 2항 | F36: RemoteView | G36: 약관 제11조 서비스의 이용시간 | H36: 공통 | I36: 공개 | J36: 정책·계약 조건 확인 | K36: https://content.rview.com/ko/terms-and-conditions/ | L36: 본문 § 제11조(서비스의 이용시간) / 2항 | N36: [시행 기준: 2021-02-16] 서비스의 이용은 회사의 업무상 또는 기술상 특별한 지장이 없는 한 연중 무휴 1일 24시간을 원칙으로 합니다. 다만, 시스템 정기점검 또는 수시점검이나 기타 회사가 필요한 경우, 서비스의 일부 또는 전부의 사용을 제한할 수 있습니다. | O36: RemoteView 이용약관 제11조(서비스의 이용시간)의 내용은 무엇인가요? | P36: RemoteView, 약관, 서비스의 이용시간 | Q36: RV-POLICY-TNC-035 | R36: Claude(Fable5) | S36: 상 | T36: 미검토 | U36: F형 소재 후보(권한·책임 경계)
A37: 36 | B37: RV-POLICY-TNC-036 | C37: Policy | D37: RemoteView 서비스 이용약관 | E37: 제12조(서비스 내용의 추가 또는 변경) 1항 | F37: RemoteView | G37: 약관 제12조 서비스 내용의 추가 또는 변경 | H37: 공통 | I37: 공개 | J37: 정책·계약 조건 확인 | K37: https://content.rview.com/ko/terms-and-conditions/ | L37: 본문 § 제12조(서비스 내용의 추가 또는 변경) / 1항 | N37: [시행 기준: 2021-02-16] 회사는 회사의 필요에 의해서 사전고지 없이 서비스 내용을 추가 또는 변경할 수 있으며, 필요한 경우 서비스의 추가 또는 변경된 사항을 서비스 제공 사이트에 게시하거나 이메일 등으로 별도 공지할 수 있습니다. | O37: RemoteView 이용약관 제12조(서비스 내용의 추가 또는 변경)의 내용은 무엇인가요? | P37: RemoteView, 약관, 서비스 내용의 추가 또는 변 | Q37: RV-POLICY-TNC-036 | R37: Claude(Fable5) | S37: 상 | T37: 미검토
A38: 37 | B38: RV-POLICY-TNC-037 | C38: Policy | D38: RemoteView 서비스 이용약관 | E38: 제12조(서비스 내용의 추가 또는 변경) 2항 | F38: RemoteView | G38: 약관 제12조 서비스 내용의 추가 또는 변경 | H38: 공통 | I38: 공개 | J38: 정책·계약 조건 확인 | K38: https://content.rview.com/ko/terms-and-conditions/ | L38: 본문 § 제12조(서비스 내용의 추가 또는 변경) / 2항 | N38: [시행 기준: 2021-02-16] 회사는 무료로 제공되는 서비스의 일부 또는 전부를 회사의 정책 및 운영의 필요상 수정, 중단, 변경할 수 있으며, 이에 대하여 관계법령에 특별한 규정이 없는 한 회원에게 별도의 보상을 하지 않습니다. | O38: RemoteView 이용약관 제12조(서비스 내용의 추가 또는 변경)의 내용은 무엇인가요? | P38: RemoteView, 약관, 서비스 내용의 추가 또는 변 | Q38: RV-POLICY-TNC-037 | R38: Claude(Fable5) | S38: 상 | T38: 미검토
A39: 38 | B39: RV-POLICY-TNC-038 | C39: Policy | D39: RemoteView 서비스 이용약관 | E39: 제13조(회원정보 사용에 대한 동의) 1항 | F39: RemoteView | G39: 약관 제13조 회원정보 사용에 대한 동의 | H39: 공통 | I39: 공개 | J39: 정책·계약 조건 확인 | K39: https://content.rview.com/ko/terms-and-conditions/ | L39: 본문 § 제13조(회원정보 사용에 대한 동의) / 1항 | N39: [시행 기준: 2021-02-16] 회원은 회사의 “개인정보보호정책”에 동의하며, 회사는 회원의 개인정보를 본 이용계약의 이행과 본 이용계약상의 서비스제공을 위한 목적으로 이용합니다. | O39: RemoteView 이용약관 제13조(회원정보 사용에 대한 동의)의 내용은 무엇인가요? | P39: RemoteView, 약관, 회원정보 사용에 대한 동의 | Q39: RV-POLICY-TNC-038 | R39: Claude(Fable5) | S39: 상 | T39: 미검토
A40: 39 | B40: RV-POLICY-TNC-039 | C40: Policy | D40: RemoteView 서비스 이용약관 | E40: 제13조(회원정보 사용에 대한 동의) 2항 | F40: RemoteView | G40: 약관 제13조 회원정보 사용에 대한 동의 | H40: 공통 | I40: 공개 | J40: 정책·계약 조건 확인 | K40: https://content.rview.com/ko/terms-and-conditions/ | L40: 본문 § 제13조(회원정보 사용에 대한 동의) / 2항 | N40: [시행 기준: 2021-02-16] 회사는 회원의 실명여부를 확인하기 위해 회원의 사전동의 없이 회사가 별도로 계약한 신용정보회사에 회사가 기재한 정보를 제공하여 실명여부를 확인할 수 있습니다. | O40: RemoteView 이용약관 제13조(회원정보 사용에 대한 동의)의 내용은 무엇인가요? | P40: RemoteView, 약관, 회원정보 사용에 대한 동의 | Q40: RV-POLICY-TNC-039 | R40: Claude(Fable5) | S40: 상 | T40: 미검토
A41: 40 | B41: RV-POLICY-TNC-040 | C41: Policy | D41: RemoteView 서비스 이용약관 | E41: 제13조(회원정보 사용에 대한 동의) 3항 | F41: RemoteView | G41: 약관 제13조 회원정보 사용에 대한 동의 | H41: 공통 | I41: 공개 | J41: 정책·계약 조건 확인 | K41: https://content.rview.com/ko/terms-and-conditions/ | L41: 본문 § 제13조(회원정보 사용에 대한 동의) / 3항 | N41: [시행 기준: 2021-02-16] 회사는 업무와 관련하여 회원 전체 또는 일부의 개인정보에 관한 통계를 작성하여 이를 사용할 수 있고, 서비스를 통하여 회원의 컴퓨터에 쿠키를 전송할 수 있습니다. 이 경우 회원은 쿠키의 수신을 거부하거나 쿠키의 수신에 대하여 경고하도록 사용하는 컴퓨터 브라우저의 설정을 변경할 수 있습니다. 다만 이렇게 수집된 개인정보는 전체적인 통계자료로만 활용합니다. | O41: RemoteView 이용약관 제13조(회원정보 사용에 대한 동의)의 내용은 무엇인가요? | P41: RemoteView, 약관, 회원정보 사용에 대한 동의 | Q41: RV-POLICY-TNC-040 | R41: Claude(Fable5) | S41: 상 | T41: 미검토
A42: 41 | B42: RV-POLICY-TNC-041 | C42: Policy | D42: RemoteView 서비스 이용약관 | E42: 제14조(웹로그 사용에 대한 동의) 1항 | F42: RemoteView | G42: 약관 제14조 웹로그 사용에 대한 동의 | H42: 공통 | I42: 공개 | J42: 정책·계약 조건 확인 | K42: https://content.rview.com/ko/terms-and-conditions/ | L42: 본문 § 제14조(웹로그 사용에 대한 동의) / 1항 | N42: [시행 기준: 2021-02-16] 회사는 서비스의 웹사이트를 방문한 사용자의 웹로그를 수집, 통계를 작성하여 이를 사용할 수 있으며, 웹로그에 대한 수집, 통계를 위하여 다음의 조치를 취하고 있습니다. 1. 사용자의 웹로그 수집을 위해 웹사이트에 스크립트 삽입 | O42: RemoteView 이용약관 제14조(웹로그 사용에 대한 동의)의 내용은 무엇인가요? | P42: RemoteView, 약관, 웹로그 사용에 대한 동의 | Q42: RV-POLICY-TNC-041 | R42: Claude(Fable5) | S42: 상 | T42: 미검토
A43: 42 | B43: RV-POLICY-TNC-042 | C43: Policy | D43: RemoteView 서비스 이용약관 | E43: 제14조(웹로그 사용에 대한 동의) 2항 | F43: RemoteView | G43: 약관 제14조 웹로그 사용에 대한 동의 | H43: 공통 | I43: 공개 | J43: 정책·계약 조건 확인 | K43: https://content.rview.com/ko/terms-and-conditions/ | L43: 본문 § 제14조(웹로그 사용에 대한 동의) / 2항 | N43: [시행 기준: 2021-02-16] 웹로그에는 사용자 개인 정보(이름, 나이, 주민등록번호 등)는 포함되어있지 않으며, 사용자의 사용 패턴 분석을 위한 방문기록과 이동경로 등의 비개인성 정보만이 포함됩니다. | O43: RemoteView 이용약관 제14조(웹로그 사용에 대한 동의)의 내용은 무엇인가요? | P43: RemoteView, 약관, 웹로그 사용에 대한 동의 | Q43: RV-POLICY-TNC-042 | R43: Claude(Fable5) | S43: 상 | T43: 미검토
A44: 43 | B44: RV-POLICY-TNC-043 | C44: Policy | D44: RemoteView 서비스 이용약관 | E44: 제15조(정보의 제공 및 광고의 게재) 1항 | F44: RemoteView | G44: 약관 제15조 정보의 제공 및 광고의 게재 | H44: 공통 | I44: 공개 | J44: 정책·계약 조건 확인 | K44: https://content.rview.com/ko/terms-and-conditions/ | L44: 본문 § 제15조(정보의 제공 및 광고의 게재) / 1항 | N44: [시행 기준: 2021-02-16] 회사는 회원이 서비스 이용 중 필요하다고 인정되는 다양한 정보를 공지사항이나 이메일 등의 방법으로 회원에게 제공할 수 있습니다. 다만, 회원은 언제든지 이메일 등을 통하여 수신거부를 할 수 있습니다. | O44: RemoteView 이용약관 제15조(정보의 제공 및 광고의 게재)의 내용은 무엇인가요? | P44: RemoteView, 약관, 정보의 제공 및 광고의 게재 | Q44: RV-POLICY-TNC-043 | R44: Claude(Fable5) | S44: 상 | T44: 미검토
A45: 44 | B45: RV-POLICY-TNC-044 | C45: Policy | D45: RemoteView 서비스 이용약관 | E45: 제15조(정보의 제공 및 광고의 게재) 2항 | F45: RemoteView | G45: 약관 제15조 정보의 제공 및 광고의 게재 | H45: 공통 | I45: 공개 | J45: 정책·계약 조건 확인 | K45: https://content.rview.com/ko/terms-and-conditions/ | L45: 본문 § 제15조(정보의 제공 및 광고의 게재) / 2항 | N45: [시행 기준: 2021-02-16] 회사는 서비스의 운영과 관련하여 서비스 화면, 홈페이지, 이메일 등에 광고를 게재할 수 있습니다. 광고가 게재된 이메일 등을 수신한 회원은 회사에 수신거부를 할 수 있습니다. | O45: RemoteView 이용약관 제15조(정보의 제공 및 광고의 게재)의 내용은 무엇인가요? | P45: RemoteView, 약관, 정보의 제공 및 광고의 게재 | Q45: RV-POLICY-TNC-044 | R45: Claude(Fable5) | S45: 상 | T45: 미검토
A46: 45 | B46: RV-POLICY-TNC-045 | C46: Policy | D46: RemoteView 서비스 이용약관 | E46: 제15조(정보의 제공 및 광고의 게재) 3항 | F46: RemoteView | G46: 약관 제15조 정보의 제공 및 광고의 게재 | H46: 공통 | I46: 공개 | J46: 정책·계약 조건 확인 | K46: https://content.rview.com/ko/terms-and-conditions/ | L46: 본문 § 제15조(정보의 제공 및 광고의 게재) / 3항 | N46: [시행 기준: 2021-02-16] 회사가 제공하는 서비스는 배너와 링크(Link) 등 다양한 형태의 광고가 포함되어 있을 수 있으며, 이는 제 3자가 제공하는 페이지와 연결될 수 있습니다. 이에 따라 제 3자가 제공하는 페이지로 연결될 경우 해당 페이지는 회사의 서비스 영역이 아니므로 회사가 신뢰성, 안정성 등을 보장하지 않으며 그로 인한 회원의 손해에 대하여도 회사는 일체의 책임을 지지 않습니다. | O46: RemoteView 이용약관 제15조(정보의 제공 및 광고의 게재)의 내용은 무엇인가요? | P46: RemoteView, 약관, 정보의 제공 및 광고의 게재 | Q46: RV-POLICY-TNC-045 | R46: Claude(Fable5) | S46: 상 | T46: 미검토 | U46: F형 소재 후보(권한·책임 경계)
A47: 46 | B47: RV-POLICY-TNC-046 | C47: Policy | D47: RemoteView 서비스 이용약관 | E47: 제16조(이벤트 및 상품) 1항 | F47: RemoteView | G47: 약관 제16조 이벤트 및 상품 | H47: 공통 | I47: 공개 | J47: 정책·계약 조건 확인 | K47: https://content.rview.com/ko/terms-and-conditions/ | L47: 본문 § 제16조(이벤트 및 상품) / 1항 | N47: [시행 기준: 2021-02-16] 각종 이벤트를 통한 당첨경품 수령 시 수령하는 회원이 회원 가입 시 입력한 회원정보에서 허위로 기재한 사항이 있을 경우 모든 권리(당첨자 대상 및 상품수령 포함)가 박탈될 수 있습니다. | O47: RemoteView 이용약관 제16조(이벤트 및 상품)의 내용은 무엇인가요? | P47: RemoteView, 약관, 이벤트 및 상품 | Q47: RV-POLICY-TNC-046 | R47: Claude(Fable5) | S47: 상 | T47: 미검토 | U47: F형 소재 후보(권한·책임 경계)
A48: 47 | B48: RV-POLICY-TNC-047 | C48: Policy | D48: RemoteView 서비스 이용약관 | E48: 제16조(이벤트 및 상품) 2항 | F48: RemoteView | G48: 약관 제16조 이벤트 및 상품 | H48: 공통 | I48: 공개 | J48: 정책·계약 조건 확인 | K48: https://content.rview.com/ko/terms-and-conditions/ | L48: 본문 § 제16조(이벤트 및 상품) / 2항 | N48: [시행 기준: 2021-02-16] 별도로 정한 기준에 의거 부여하는 각종 상품은 미리 정해진 날에 본인 확인 후 제공하거나 또는 온라인 송금되며 상품 에 따라 각종 세금 및 배송료가 부과될 수 있습니다. | O48: RemoteView 이용약관 제16조(이벤트 및 상품)의 내용은 무엇인가요? | P48: RemoteView, 약관, 이벤트 및 상품 | Q48: RV-POLICY-TNC-047 | R48: Claude(Fable5) | S48: 상 | T48: 미검토
A49: 48 | B49: RV-POLICY-TNC-048 | C49: Policy | D49: RemoteView 서비스 이용약관 | E49: 제17조(서비스의 중지) 1항 | F49: RemoteView | G49: 약관 제17조 서비스의 중지 | H49: 공통 | I49: 공개 | J49: 정책·계약 조건 확인 | K49: https://content.rview.com/ko/terms-and-conditions/ | L49: 본문 § 제17조(서비스의 중지) / 1항 | N49: [시행 기준: 2021-02-16] 회사는 다음 각 호에 해당하는 경우 서비스의 전부 또는 일부를 제한하거나 중지할 수 있습니다. 1. 전기통신사업법에 규정된 기간통신사업자가 전기통신서비스를 중지하였을 경우 2. 서비스용 설비의 보수, 정기점검 등 공사로 인한 부득이한 경우 3. 정전, 제반 설비의 장애 또는 이용량의 폭주 등으로 정상적인 서비스 이용에 지장이 있는 경우 4. 천재지변, 국가비상사태 등 불가항력적인 사유가 있는 경우 5. 기타 회사의 업무상이나 기술상의 이유로 서비스 중지가 필요하다고 판단되는 경우 | O49: RemoteView 이용약관 제17조(서비스의 중지)의 내용은 무엇인가요? | P49: RemoteView, 약관, 서비스의 중지 | Q49: RV-POLICY-TNC-048 | R49: Claude(Fable5) | S49: 상 | T49: 미검토 | U49: F형 소재 후보(권한·책임 경계)
A50: 49 | B50: RV-POLICY-TNC-049 | C50: Policy | D50: RemoteView 서비스 이용약관 | E50: 제17조(서비스의 중지) 2항 | F50: RemoteView | G50: 약관 제17조 서비스의 중지 | H50: 공통 | I50: 공개 | J50: 정책·계약 조건 확인 | K50: https://content.rview.com/ko/terms-and-conditions/ | L50: 본문 § 제17조(서비스의 중지) / 2항 | N50: [시행 기준: 2021-02-16] 서비스 중단이 있는 경우에는 회사가 제34조(회원에 대한 통지)에 정한 방법으로 회원에게 사전 통지합니다. 단, 회사가 통제할 수 없는 사유로 인한 서비스 중단으로 인한 사전 통지가 불가능한 경우에는 사후에 이를 홈페이지 또는 개별 서비스 관련 홈페이지에 공지할 수 있습니다. | O50: RemoteView 이용약관 제17조(서비스의 중지)의 내용은 무엇인가요? | P50: RemoteView, 약관, 서비스의 중지 | Q50: RV-POLICY-TNC-049 | R50: Claude(Fable5) | S50: 상 | T50: 미검토 | U50: F형 소재 후보(권한·책임 경계)
A51: 50 | B51: RV-POLICY-TNC-050 | C51: Policy | D51: RemoteView 서비스 이용약관 | E51: 제17조(서비스의 중지) 3항 | F51: RemoteView | G51: 약관 제17조 서비스의 중지 | H51: 공통 | I51: 공개 | J51: 정책·계약 조건 확인 | K51: https://content.rview.com/ko/terms-and-conditions/ | L51: 본문 § 제17조(서비스의 중지) / 3항 | N51: [시행 기준: 2021-02-16] 회사는 본 조 제1항의 사유로 서비스의 제공이 일시적으로 중단됨으로 인하여 회원의 손해에 대하여 책임지지 않습니다. | O51: RemoteView 이용약관 제17조(서비스의 중지)의 내용은 무엇인가요? | P51: RemoteView, 약관, 서비스의 중지 | Q51: RV-POLICY-TNC-050 | R51: Claude(Fable5) | S51: 상 | T51: 미검토 | U51: F형 소재 후보(권한·책임 경계)
A52: 51 | B52: RV-POLICY-TNC-051 | C52: Policy | D52: RemoteView 서비스 이용약관 | E52: 제18조(게시물 또는 내용물의 삭제) 1항 | F52: RemoteView | G52: 약관 제18조 게시물 또는 내용물의 삭제 | H52: 공통 | I52: 공개 | J52: 정책·계약 조건 확인 | K52: https://content.rview.com/ko/terms-and-conditions/ | L52: 본문 § 제18조(게시물 또는 내용물의 삭제) / 1항 | N52: [시행 기준: 2021-02-16] 회사는 회원이 게시하거나 전달하는 서비스 내의 모든 내용물(회원간 전달 포함)이 다음 각호의 경우에 해당한다고 판단되는 경우 사전통지 없이 삭제하거나 등록 자체를 거부할 수 있으며, 이에 대해 회사는 어떠한 책임도 지지 않습니다. 1. 회사, 다른 회원 또는 제3자를 비방하거나 중상모략으로 명예를 손상시키는 내용인 경우 2. 공공질서 및 미풍양속에 위반되는 내용의 정보, 문장, 도형 등의 유포에 해당하는 경우 3. 범죄적 행위에 결부된다고 인정되는 내용인 경우 4. 회사의 저작권, 제3자의 저작권 등 기타 권리를 침해하는 내용인 경우 5. 회사에서 제공하는 서비스와 관련 없는 내용인 경우 6. 불필요하거나 승인되지 않은 광고, 판촉물을 게재하는 경우 7. 타인의 아이디, 성명 등을 무단으로 도용하여 작성한 내용이거나, 타인이 입력한 정보를 무단으로 위조, 변조한 내용인 경우 8. 동일한 내용을 중복하여 다수 게시하는 등 게시의 목적에 어긋나는 경우 9. 불법통신에 해당하거나 기타 관계 법령 및 회사의 지침 등에 위반된다고 판단되는 경우 | O52: RemoteView 이용약관 제18조(게시물 또는 내용물의 삭제)의 내용은 무엇인가요? | P52: RemoteView, 약관, 게시물 또는 내용물의 삭제 | Q52: RV-POLICY-TNC-051 | R52: Claude(Fable5) | S52: 상 | T52: 미검토 | U52: F형 소재 후보(권한·책임 경계)
A53: 52 | B53: RV-POLICY-TNC-052 | C53: Policy | D53: RemoteView 서비스 이용약관 | E53: 제18조(게시물 또는 내용물의 삭제) 2항 | F53: RemoteView | G53: 약관 제18조 게시물 또는 내용물의 삭제 | H53: 공통 | I53: 공개 | J53: 정책·계약 조건 확인 | K53: https://content.rview.com/ko/terms-and-conditions/ | L53: 본문 § 제18조(게시물 또는 내용물의 삭제) / 2항 | N53: [시행 기준: 2021-02-16] 회사는 게시물에 관련된 세부 이용지침을 별도로 정하여 시행할 수 있으며, 회원은 그 지침에 따라 각 게시물(회원간 전달 포함)을 등록하거나 삭제하여야 합니다. | O53: RemoteView 이용약관 제18조(게시물 또는 내용물의 삭제)의 내용은 무엇인가요? | P53: RemoteView, 약관, 게시물 또는 내용물의 삭제 | Q53: RV-POLICY-TNC-052 | R53: Claude(Fable5) | S53: 상 | T53: 미검토
A54: 53 | B54: RV-POLICY-TNC-053 | C54: Policy | D54: RemoteView 서비스 이용약관 | E54: 제19조(게시물의 저작권) 1항 | F54: RemoteView | G54: 약관 제19조 게시물의 저작권 | H54: 공통 | I54: 공개 | J54: 정책·계약 조건 확인 | K54: https://content.rview.com/ko/terms-and-conditions/ | L54: 본문 § 제19조(게시물의 저작권) / 1항 | N54: [시행 기준: 2021-02-16] 회사가 작성한 저작물에 대한 저작권 및 기타 지적재산권은 회사에 귀속합니다. 회원이 서비스내에 게시한 게시물의 저작권은 해당 저작권자에게 귀속합니다. | O54: RemoteView 이용약관 제19조(게시물의 저작권)의 내용은 무엇인가요? | P54: RemoteView, 약관, 게시물의 저작권 | Q54: RV-POLICY-TNC-053 | R54: Claude(Fable5) | S54: 상 | T54: 미검토
A55: 54 | B55: RV-POLICY-TNC-054 | C55: Policy | D55: RemoteView 서비스 이용약관 | E55: 제19조(게시물의 저작권) 2항 | F55: RemoteView | G55: 약관 제19조 게시물의 저작권 | H55: 공통 | I55: 공개 | J55: 정책·계약 조건 확인 | K55: https://content.rview.com/ko/terms-and-conditions/ | L55: 본문 § 제19조(게시물의 저작권) / 2항 | N55: [시행 기준: 2021-02-16] 회원은 서비스를 이용하면서 얻은 정보를 회사의 승낙 없이 영리목적으로 이용하거나 제3자에게 이용하게 할 수 없습니다. | O55: RemoteView 이용약관 제19조(게시물의 저작권)의 내용은 무엇인가요? | P55: RemoteView, 약관, 게시물의 저작권 | Q55: RV-POLICY-TNC-054 | R55: Claude(Fable5) | S55: 상 | T55: 미검토 | U55: F형 소재 후보(권한·책임 경계)
A56: 55 | B56: RV-POLICY-TNC-055 | C56: Policy | D56: RemoteView 서비스 이용약관 | E56: 제19조(게시물의 저작권) 3항 | F56: RemoteView | G56: 약관 제19조 게시물의 저작권 | H56: 공통 | I56: 공개 | J56: 정책·계약 조건 확인 | K56: https://content.rview.com/ko/terms-and-conditions/ | L56: 본문 § 제19조(게시물의 저작권) / 3항 | N56: [시행 기준: 2021-02-16] 회원은 회사의 저작물에 대하여 전부 또는 일부의 수정, 대여, 대출, 판매, 배포, 제작, 양도, 재 라이센스, 담보권 설정 행위, 상업적 이용 행위를 할 수 없으며, 제3자로 하여금 이와 같은 행위를 하도록 허락할 수 없습니다. 1. 서비스내에서 회원 게시물의 복제, 수정, 전시, 배포, 출판 및 2차 저작물과 편집저작물의 작성 등 2. 미디어, 통신사 등 서비스 제휴 파트너에게 회원의 게시물 제공, 사용하도록 허용 3. 기타 회사의 홍보 등의 목적 | O56: RemoteView 이용약관 제19조(게시물의 저작권)의 내용은 무엇인가요? | P56: RemoteView, 약관, 게시물의 저작권 | Q56: RV-POLICY-TNC-055 | R56: Claude(Fable5) | S56: 상 | T56: 미검토
A57: 56 | B57: RV-POLICY-TNC-056 | C57: Policy | D57: RemoteView 서비스 이용약관 | E57: 제19조(게시물의 저작권) 4항 | F57: RemoteView | G57: 약관 제19조 게시물의 저작권 | H57: 공통 | I57: 공개 | J57: 정책·계약 조건 확인 | K57: https://content.rview.com/ko/terms-and-conditions/ | L57: 본문 § 제19조(게시물의 저작권) / 4항 | N57: [시행 기준: 2021-02-16] 전항의 사용권부여는 회사가 서비스를 운영하는 동안 유효하며, 회원이 탈퇴한 이후에도 별도의 회원의 요청이 없으면 지속적으로 적용됩니다. | O57: RemoteView 이용약관 제19조(게시물의 저작권)의 내용은 무엇인가요? | P57: RemoteView, 약관, 게시물의 저작권 | Q57: RV-POLICY-TNC-056 | R57: Claude(Fable5) | S57: 상 | T57: 미검토
A58: 57 | B58: RV-POLICY-TNC-057 | C58: Policy | D58: RemoteView 서비스 이용약관 | E58: 제20조(테스트 목적 서비스 등) 1항 | F58: RemoteView | G58: 약관 제20조 테스트 목적 서비스 등 | H58: 공통 | I58: 공개 | J58: 정책·계약 조건 확인 | K58: https://content.rview.com/ko/terms-and-conditions/ | L58: 본문 § 제20조(테스트 목적 서비스 등) / 1항 | N58: [시행 기준: 2021-02-16] 사는 새로운 서비스를 유료로 제공하기 전 회원들을 대상으로 일정 기간 테스트 목적의 서비스를 제공할 수 있습니다. | O58: RemoteView 이용약관 제20조(테스트 목적 서비스 등)의 내용은 무엇인가요? | P58: RemoteView, 약관, 테스트 목적 서비스 등 | Q58: RV-POLICY-TNC-057 | R58: Claude(Fable5) | S58: 상 | T58: 미검토
A59: 58 | B59: RV-POLICY-TNC-058 | C59: Policy | D59: RemoteView 서비스 이용약관 | E59: 제20조(테스트 목적 서비스 등) 2항 | F59: RemoteView | G59: 약관 제20조 테스트 목적 서비스 등 | H59: 공통 | I59: 공개 | J59: 정책·계약 조건 확인 | K59: https://content.rview.com/ko/terms-and-conditions/ | L59: 본문 § 제20조(테스트 목적 서비스 등) / 2항 | N59: [시행 기준: 2021-02-16] 스트 목적 서비스의 경우는 서비스 안정성 등을 위해 사전 공지 없이 수시로 프로그램 업데이트될 수 있습니다. | O59: RemoteView 이용약관 제20조(테스트 목적 서비스 등)의 내용은 무엇인가요? | P59: RemoteView, 약관, 테스트 목적 서비스 등 | Q59: RV-POLICY-TNC-058 | R59: Claude(Fable5) | S59: 상 | T59: 미검토
A60: 59 | B60: RV-POLICY-TNC-059 | C60: Policy | D60: RemoteView 서비스 이용약관 | E60: 제20조(테스트 목적 서비스 등) 3항 | F60: RemoteView | G60: 약관 제20조 테스트 목적 서비스 등 | H60: 공통 | I60: 공개 | J60: 정책·계약 조건 확인 | K60: https://content.rview.com/ko/terms-and-conditions/ | L60: 본문 § 제20조(테스트 목적 서비스 등) / 3항 | N60: [시행 기준: 2021-02-16] 스트 서비스 종료와 함께 회원정보, 게시물은 삭제되며, 서비스 이용권한도 정지되는 것을 원칙으로 합니다. | O60: RemoteView 이용약관 제20조(테스트 목적 서비스 등)의 내용은 무엇인가요? | P60: RemoteView, 약관, 테스트 목적 서비스 등 | Q60: RV-POLICY-TNC-059 | R60: Claude(Fable5) | S60: 상 | T60: 미검토
A61: 60 | B61: RV-POLICY-TNC-060 | C61: Policy | D61: RemoteView 서비스 이용약관 | E61: 제21조(서비스 종류) 1항 | F61: RemoteView | G61: 약관 제21조 서비스 종류 | H61: 공통 | I61: 공개 | J61: 정책·계약 조건 확인 | K61: https://content.rview.com/ko/terms-and-conditions/ | L61: 본문 § 제21조(서비스 종류) / 1항 | N61: [시행 기준: 2021-02-16] 리모트콜(RemoteCall) 서비스 | O61: RemoteView 이용약관 제21조(서비스 종류)의 내용은 무엇인가요? | P61: RemoteView, 약관, 서비스 종류 | Q61: RV-POLICY-TNC-060 | R61: Claude(Fable5) | S61: 하 | T61: 근거약함 | U61: 본문 25자 미만
A62: 61 | B62: RV-POLICY-TNC-061 | C62: Policy | D62: RemoteView 서비스 이용약관 | E62: 제21조(서비스 종류) 1항 | F62: RemoteView | G62: 약관 제21조 서비스 종류 | H62: 공통 | I62: 공개 | J62: 정책·계약 조건 확인 | K62: https://content.rview.com/ko/terms-and-conditions/ | L62: 본문 § 제21조(서비스 종류) / 1항 | N62: [시행 기준: 2021-02-16] 리모트콜은 인터넷을 통한 원격지원 서비스로서, 리모트콜 사용자는 원거리에 있는 고객과 채팅 또는 고객 PC 혹은 모바일 화면을 공유 및 제어하여 고객의 문제점을 원격으로 쉽고, 빠르게 진단, 해결할 수 있도록 도와주는 서비스 입니다. | O62: RemoteView 이용약관 제21조(서비스 종류)의 내용은 무엇인가요? | P62: RemoteView, 약관, 서비스 종류 | Q62: RV-POLICY-TNC-061 | R62: Claude(Fable5) | S62: 상 | T62: 미검토
A63: 62 | B63: RV-POLICY-TNC-062 | C63: Policy | D63: RemoteView 서비스 이용약관 | E63: 제21조(서비스 종류) 2항 | F63: RemoteView | G63: 약관 제21조 서비스 종류 | H63: 공통 | I63: 공개 | J63: 정책·계약 조건 확인 | K63: https://content.rview.com/ko/terms-and-conditions/ | L63: 본문 § 제21조(서비스 종류) / 2항 | N63: [시행 기준: 2021-02-16] 리모트콜 서비스의 구체적인 종류 및 요금제, 이용요금은 회사 홈페이지(www.rsupport.com) 및 개별 서비스 페이지(https://www.remotecall.com)에 공시하는 바에 따릅니다. | O63: RemoteView 이용약관 제21조(서비스 종류)의 내용은 무엇인가요? | P63: RemoteView, 약관, 서비스 종류 | Q63: RV-POLICY-TNC-062 | R63: Claude(Fable5) | S63: 상 | T63: 미검토
A64: 63 | B64: RV-POLICY-TNC-063 | C64: Policy | D64: RemoteView 서비스 이용약관 | E64: 제21조(서비스 종류) 2항 | F64: RemoteView | G64: 약관 제21조 서비스 종류 | H64: 공통 | I64: 공개 | J64: 정책·계약 조건 확인 | K64: https://content.rview.com/ko/terms-and-conditions/ | L64: 본문 § 제21조(서비스 종류) / 2항 | N64: [시행 기준: 2021-02-16] 리모트뷰(RemoteView) 서비스 | O64: RemoteView 이용약관 제21조(서비스 종류)의 내용은 무엇인가요? | P64: RemoteView, 약관, 서비스 종류 | Q64: RV-POLICY-TNC-063 | R64: Claude(Fable5) | S64: 하 | T64: 근거약함 | U64: 본문 25자 미만
A65: 64 | B65: RV-POLICY-TNC-064 | C65: Policy | D65: RemoteView 서비스 이용약관 | E65: 제21조(서비스 종류) 1항 | F65: RemoteView | G65: 약관 제21조 서비스 종류 | H65: 공통 | I65: 공개 | J65: 정책·계약 조건 확인 | K65: https://content.rview.com/ko/terms-and-conditions/ | L65: 본문 § 제21조(서비스 종류) / 1항 | N65: [시행 기준: 2021-02-16] 리모트뷰는 원거리의 내 PC 또는 관리할 서버에 ‘에이전트(Agent)’ 프로그램 설치 후 인터넷을 통해 언제 어디서나 내 컴퓨터에 원격 접속하여 쉽고, 빠르고, 안전하게 실시간으로 제어할 수 있는 서비스 입니다. | O65: RemoteView 이용약관 제21조(서비스 종류)의 내용은 무엇인가요? | P65: RemoteView, 약관, 서비스 종류 | Q65: RV-POLICY-TNC-064 | R65: Claude(Fable5) | S65: 상 | T65: 미검토
A66: 65 | B66: RV-POLICY-TNC-065 | C66: Policy | D66: RemoteView 서비스 이용약관 | E66: 제21조(서비스 종류) 2항 | F66: RemoteView | G66: 약관 제21조 서비스 종류 | H66: 공통 | I66: 공개 | J66: 정책·계약 조건 확인 | K66: https://content.rview.com/ko/terms-and-conditions/ | L66: 본문 § 제21조(서비스 종류) / 2항 | N66: [시행 기준: 2021-02-16] 리모트뷰 서비스의 구체적인 종류 및 요금제, 이용요금은 회사 홈페이지 및 개별 서비스 페이지(https://rview.com)에 공시하는 바에 따릅니다. | O66: RemoteView 이용약관 제21조(서비스 종류)의 내용은 무엇인가요? | P66: RemoteView, 약관, 서비스 종류 | Q66: RV-POLICY-TNC-065 | R66: Claude(Fable5) | S66: 상 | T66: 미검토
A67: 66 | B67: RV-POLICY-TNC-066 | C67: Policy | D67: RemoteView 서비스 이용약관 | E67: 제21조(서비스 종류) 3항 | F67: RemoteView | G67: 약관 제21조 서비스 종류 | H67: 공통 | I67: 공개 | J67: 정책·계약 조건 확인 | K67: https://content.rview.com/ko/terms-and-conditions/ | L67: 본문 § 제21조(서비스 종류) / 3항 | N67: [시행 기준: 2021-02-16] 리모트에이피아이(RemoteAPI) 서비스 | O67: RemoteView 이용약관 제21조(서비스 종류)의 내용은 무엇인가요? | P67: RemoteView, 약관, 서비스 종류 | Q67: RV-POLICY-TNC-066 | R67: Claude(Fable5) | S67: 하 | T67: 근거약함 | U67: 본문 25자 미만
A68: 67 | B68: RV-POLICY-TNC-067 | C68: Policy | D68: RemoteView 서비스 이용약관 | E68: 제21조(서비스 종류) 1항 | F68: RemoteView | G68: 약관 제21조 서비스 종류 | H68: 공통 | I68: 공개 | J68: 정책·계약 조건 확인 | K68: https://content.rview.com/ko/terms-and-conditions/ | L68: 본문 § 제21조(서비스 종류) / 1항 | N68: [시행 기준: 2021-02-16] 리모트에이피아이는 18개의 Function의 원격 지원을 기존의 소프트웨어에 탑재할 수 있도록 설계된 모듈식 제품으로 간단한 API 구성으로 누구나 손쉽게 원격제어 기능을 구현할 수 있는 서비스입니다. | O68: RemoteView 이용약관 제21조(서비스 종류)의 내용은 무엇인가요? | P68: RemoteView, 약관, 서비스 종류 | Q68: RV-POLICY-TNC-067 | R68: Claude(Fable5) | S68: 상 | T68: 미검토
A69: 68 | B69: RV-POLICY-TNC-068 | C69: Policy | D69: RemoteView 서비스 이용약관 | E69: 제21조(서비스 종류) 2항 | F69: RemoteView | G69: 약관 제21조 서비스 종류 | H69: 공통 | I69: 공개 | J69: 정책·계약 조건 확인 | K69: https://content.rview.com/ko/terms-and-conditions/ | L69: 본문 § 제21조(서비스 종류) / 2항 | N69: [시행 기준: 2021-02-16] 리모트에이피아이 서비스의 구체적인 종류 및 요금제, 이용요금은 회사 홈페이지 및 개별 서비스 페이지에 공시하는 바에 따릅니다. | O69: RemoteView 이용약관 제21조(서비스 종류)의 내용은 무엇인가요? | P69: RemoteView, 약관, 서비스 종류 | Q69: RV-POLICY-TNC-068 | R69: Claude(Fable5) | S69: 상 | T69: 미검토
A70: 69 | B70: RV-POLICY-TNC-069 | C70: Policy | D70: RemoteView 서비스 이용약관 | E70: 제21조(서비스 종류) 4항 | F70: RemoteView | G70: 약관 제21조 서비스 종류 | H70: 공통 | I70: 공개 | J70: 정책·계약 조건 확인 | K70: https://content.rview.com/ko/terms-and-conditions/ | L70: 본문 § 제21조(서비스 종류) / 4항 | N70: [시행 기준: 2021-02-16] 리모트미팅(RemoteMeeting) 서비스 | O70: RemoteView 이용약관 제21조(서비스 종류)의 내용은 무엇인가요? | P70: RemoteView, 약관, 서비스 종류 | Q70: RV-POLICY-TNC-069 | R70: Claude(Fable5) | S70: 하 | T70: 근거약함 | U70: 본문 25자 미만
A71: 70 | B71: RV-POLICY-TNC-070 | C71: Policy | D71: RemoteView 서비스 이용약관 | E71: 제21조(서비스 종류) 1항 | F71: RemoteView | G71: 약관 제21조 서비스 종류 | H71: 공통 | I71: 공개 | J71: 정책·계약 조건 확인 | K71: https://content.rview.com/ko/terms-and-conditions/ | L71: 본문 § 제21조(서비스 종류) / 1항 | N71: [시행 기준: 2021-02-16] 리모트미팅은 화상회의 서비스로, 프로그램 설치 또는 다운로드 없이 웹 브라우저에서 작동하는 서비스입니다. | O71: RemoteView 이용약관 제21조(서비스 종류)의 내용은 무엇인가요? | P71: RemoteView, 약관, 서비스 종류 | Q71: RV-POLICY-TNC-070 | R71: Claude(Fable5) | S71: 상 | T71: 미검토
A72: 71 | B72: RV-POLICY-TNC-071 | C72: Policy | D72: RemoteView 서비스 이용약관 | E72: 제21조(서비스 종류) 2항 | F72: RemoteView | G72: 약관 제21조 서비스 종류 | H72: 공통 | I72: 공개 | J72: 정책·계약 조건 확인 | K72: https://content.rview.com/ko/terms-and-conditions/ | L72: 본문 § 제21조(서비스 종류) / 2항 | N72: [시행 기준: 2021-02-16] 리모트미팅 서비스의 구체적인 종류 및 요금제, 이용요금은 회사 홈페이지 및 개별 서비스 페이지(www.remotemeeting.com)에 공시하는 바에 따릅니다. | O72: RemoteView 이용약관 제21조(서비스 종류)의 내용은 무엇인가요? | P72: RemoteView, 약관, 서비스 종류 | Q72: RV-POLICY-TNC-071 | R72: Claude(Fable5) | S72: 상 | T72: 미검토
A73: 72 | B73: RV-POLICY-TNC-072 | C73: Policy | D73: RemoteView 서비스 이용약관 | E73: 제21조(서비스 종류) 5항 | F73: RemoteView | G73: 약관 제21조 서비스 종류 | H73: 공통 | I73: 공개 | J73: 정책·계약 조건 확인 | K73: https://content.rview.com/ko/terms-and-conditions/ | L73: 본문 § 제21조(서비스 종류) / 5항 | N73: [시행 기준: 2021-02-16] 리모트세미나(RemoteSeminar) 서비스 | O73: RemoteView 이용약관 제21조(서비스 종류)의 내용은 무엇인가요? | P73: RemoteView, 약관, 서비스 종류 | Q73: RV-POLICY-TNC-072 | R73: Claude(Fable5) | S73: 상 | T73: 미검토
